Workbook
Name uHead: #REF!
Name uHead: #REF!

Sheet YuHui
A1: 買進日期 | B1: 種類 | C1: 股票代號 | D1: 股票名稱 | E1: 股數 | F1: 買進價 | G1: 成交金額 | H1: 手續費 | I1: 賣出日期 | J1: 賣出價 | K1: 成交金額 | L1: 手續費 | M1: 交易稅 | N1: 證所稅 | O1: 參考現值 | P1: 已實現損益 | Q1: 未實現損益 | R1: 除息 | S1: 手續費 | T1: 健保補充保費 | U1: 實質扣抵稅率 | V1: 扣抵稅率 | W1: 所得稅率 | X1: 投資報酬率 | Y1: 今日股價 | Z1: 漲跌 | AB1: 分類
A2: 45707 | C2: 3078 | D2: 僑威 | E2: 1000 | F2: 87.9 | G2: =E2*F2 -> 87900 | H2: 75 | I2: 45709 | J2: 85.3 | K2: =E2*J2 -> 85300 | L2: 72 | M2: 255 | N2: 0 | O2: =IF(I2="",E2*Y2,0) -> 0 | P2: =IF(I2="",R2-H2,(K2-H2-SUM(L2:N2)+R2-S2-T2)-G2)+(ROUND(R2*V2,0)-ROUND(R2*(1+V2),0)*W2) -> -3012 | Q2: =IF(I2="",(O2-G2-(O2*0.1425%*0.65)-(O2*0.3%)-S2-T2),0) -> 0 | S2: 10 | U2: =(V2*50%)/(1+50%*V2) -> 0 | W2: 0.11 | X2: =(P2+Q2)/G2 -> -0.034266212 | Y2: =VLOOKUP(C2,每日行情!A:D,4,FALSE) -> 47.3 | Z2: =VLOOKUP(C2,每日行情!A:E,5,FALSE) -> -0.1 | AA2: =IF(I2="",((TODAY()-A2)*G2)/365.24,((I2-A2)*G2)/365.24) -> 481.32735 | AB2: 台股
A3: 45698 | C3: 6245 | D3: 立端 | E3: 1000 | F3: 113.5 | G3: =E3*F3 -> 113500 | H3: 97 | I3: 45713 | J3: 115.5 | K3: =E3*J3 -> 115500 | L3: 98 | M3: 346 | N3: 0 | O3: =IF(I3="",E3*Y3,0) -> 0 | P3: =IF(I3="",R3-H3,(K3-H3-SUM(L3:N3)+R3-S3-T3)-G3)+(ROUND(R3*V3,0)-ROUND(R3*(1+V3),0)*W3) -> 1449 | Q3: =IF(I3="",(O3-G3-(O3*0.1425%*0.65)-(O3*0.3%)-S3-T3),0) -> 0 | S3: 10 | U3: =(V3*50%)/(1+50%*V3) -> 0 | W3: 0.11 | X3: =(P3+Q3)/G3 -> 0.01276652 | Y3: =VLOOKUP(C3,每日行情!A:D,4,FALSE) -> 89.3 | Z3: =VLOOKUP(C3,每日行情!A:E,5,FALSE) -> 1.6 | AA3: =IF(I3="",((TODAY()-A3)*G3)/365.24,((I3-A3)*G3)/365.24) -> 4661.3186 | AB3: 台股
A4: 45699 | C4: 6596 | D4: 寬宏藝術 | E4: 1000 | F4: 92.5 | G4: =E4*F4 -> 92500 | H4: 79 | I4: 45714 | J4: 91.9 | K4: =E4*J4 -> 91900 | L4: 78 | M4: 275 | N4: 0 | O4: =IF(I4="",E4*Y4,0) -> 0 | P4: =IF(I4="",R4-H4,(K4-H4-SUM(L4:N4)+R4-S4-T4)-G4)+(ROUND(R4*V4,0)-ROUND(R4*(1+V4),0)*W4) -> -1042 | Q4: =IF(I4="",(O4-G4-(O4*0.1425%*0.65)-(O4*0.3%)-S4-T4),0) -> 0 | S4: 10 | U4: =(V4*50%)/(1+50%*V4) -> 0 | W4: 0.11 | X4: =(P4+Q4)/G4 -> -0.011264865 | Y4: =VLOOKUP(C4,每日行情!A:D,4,FALSE) -> 96.1 | Z4: =VLOOKUP(C4,每日行情!A:E,5,FALSE) -> 0.8 | AA4: =IF(I4="",((TODAY()-A4)*G4)/365.24,((I4-A4)*G4)/365.24) -> 3798.872 | AB4: 台股
A5: 45702 | C5: 2301 | D5: 光寶科 | E5: 1000 | F5: 110.5 | G5: =E5*F5 -> 110500 | H5: 94 | I5: 45715 | J5: 110 | K5: =E5*J5 -> 110000 | L5: 94 | M5: 330 | N5: 0 | O5: =IF(I5="",E5*Y5,0) -> 0 | P5: =IF(I5="",R5-H5,(K5-H5-SUM(L5:N5)+R5-S5-T5)-G5)+(ROUND(R5*V5,0)-ROUND(R5*(1+V5),0)*W5) -> -1028 | Q5: =IF(I5="",(O5-G5-(O5*0.1425%*0.65)-(O5*0.3%)-S5-T5),0) -> 0 | S5: 10 | U5: =(V5*50%)/(1+50%*V5) -> 0 | W5: 0.11 | X5: =(P5+Q5)/G5 -> -0.0093031674 | Y5: =VLOOKUP(C5,每日行情!A:D,4,FALSE) -> 264.5 | Z5: =VLOOKUP(C5,每日行情!A:E,5,FALSE) -> -3.5 | AA5: =IF(I5="",((TODAY()-A5)*G5)/365.24,((I5-A5)*G5)/365.24) -> 3933.0303 | AB5: 台股
A6: 45706 | C6: 2883 | D6: 凱基金 | E6: 1000 | F6: 17.9 | G6: =E6*F6 -> 17900 | H6: 20 | I6: 45715 | J6: 18.15 | K6: =E6*J6 -> 18150 | L6: 20 | M6: 54 | N6: 0 | O6: =IF(I6="",E6*Y6,0) -> 0 | P6: =IF(I6="",R6-H6,(K6-H6-SUM(L6:N6)+R6-S6-T6)-G6)+(ROUND(R6*V6,0)-ROUND(R6*(1+V6),0)*W6) -> 146 | Q6: =IF(I6="",(O6-G6-(O6*0.1425%*0.65)-(O6*0.3%)-S6-T6),0) -> 0 | S6: 10 | U6: =(V6*50%)/(1+50%*V6) -> 0 | W6: 0.11 | X6: =(P6+Q6)/G6 -> 0.0081564246 | Y6: =VLOOKUP(C6,每日行情!A:D,4,FALSE) -> 39.1 | Z6: =VLOOKUP(C6,每日行情!A:E,5,FALSE) -> 0.7 | AA6: =IF(I6="",((TODAY()-A6)*G6)/365.24,((I6-A6)*G6)/365.24) -> 441.07984 | AB6: 台股
A7: 45702 | C7: 2884 | D7: 玉山金 | E7: 1000 | F7: 29.1 | G7: =E7*F7 -> 29100 | H7: 24 | I7: 45715 | J7: 29.5 | K7: =E7*J7 -> 29500 | L7: 25 | M7: 88 | N7: 0 | O7: =IF(I7="",E7*Y7,0) -> 0 | P7: =IF(I7="",R7-H7,(K7-H7-SUM(L7:N7)+R7-S7-T7)-G7)+(ROUND(R7*V7,0)-ROUND(R7*(1+V7),0)*W7) -> 253 | Q7: =IF(I7="",(O7-G7-(O7*0.1425%*0.65)-(O7*0.3%)-S7-T7),0) -> 0 | S7: 10 | U7: =(V7*50%)/(1+50%*V7) -> 0 | W7: 0.11 | X7: =(P7+Q7)/G7 -> 0.0086941581 | Y7: =VLOOKUP(C7,每日行情!A:D,4,FALSE) -> 49.15 | Z7: =VLOOKUP(C7,每日行情!A:E,5,FALSE) -> 0.35 | AA7: =IF(I7="",((TODAY()-A7)*G7)/365.24,((I7-A7)*G7)/365.24) -> 1035.7573 | AB7: 台股
A8: 45698 | C8: 6206 | D8: 飛捷 | E8: 1000 | F8: 118.5 | G8: =E8*F8 -> 118500 | H8: 101 | I8: 45715 | J8: 162.5 | K8: =E8*J8 -> 162500 | L8: 138 | M8: 487 | N8: 0 | O8: =IF(I8="",E8*Y8,0) -> 0 | P8: =IF(I8="",R8-H8,(K8-H8-SUM(L8:N8)+R8-S8-T8)-G8)+(ROUND(R8*V8,0)-ROUND(R8*(1+V8),0)*W8) -> 43264 | Q8: =IF(I8="",(O8-G8-(O8*0.1425%*0.65)-(O8*0.3%)-S8-T8),0) -> 0 | S8: 10 | U8: =(V8*50%)/(1+50%*V8) -> 0 | W8: 0.11 | X8: =(P8+Q8)/G8 -> 0.36509705 | Y8: =VLOOKUP(C8,每日行情!A:D,4,FALSE) -> 36.56 | Z8: =VLOOKUP(C8,每日行情!A:E,5,FALSE) -> 0.4 | AA8: =IF(I8="",((TODAY()-A8)*G8)/365.24,((I8-A8)*G8)/365.24) -> 5515.5514 | AB8: 台股
A9: 45702 | C9: 1605 | D9: 華新 | E9: 1000 | F9: 26.65 | G9: =E9*F9 -> 26650 | H9: 23 | I9: 45720 | J9: 27.6 | K9: =E9*J9 -> 27600 | L9: 23 | M9: 82 | N9: 0 | O9: =IF(I9="",E9*Y9,0) -> 0 | P9: =IF(I9="",R9-H9,(K9-H9-SUM(L9:N9)+R9-S9-T9)-G9)+(ROUND(R9*V9,0)-ROUND(R9*(1+V9),0)*W9) -> 812 | Q9: =IF(I9="",(O9-G9-(O9*0.1425%*0.65)-(O9*0.3%)-S9-T9),0) -> 0 | S9: 10 | U9: =(V9*50%)/(1+50%*V9) -> 0 | W9: 0.11 | X9: =(P9+Q9)/G9 -> 0.030469043 | Y9: =VLOOKUP(C9,每日行情!A:D,4,FALSE) -> 38.5 | Z9: =VLOOKUP(C9,每日行情!A:E,5,FALSE) -> 0.8 | AA9: =IF(I9="",((TODAY()-A9)*G9)/365.24,((I9-A9)*G9)/365.24) -> 1313.383 | AB9: 台股
A10: 45702 | C10: 1605 | D10: 華新 | E10: 1000 | F10: 26.65 | G10: =E10*F10 -> 26650 | H10: 22 | I10: 45721 | J10: 27.75 | K10: =E10*J10 -> 27750 | L10: 23 | M10: 83 | N10: 0 | O10: =IF(I10="",E10*Y10,0) -> 0 | P10: =IF(I10="",R10-H10,(K10-H10-SUM(L10:N10)+R10-S10-T10)-G10)+(ROUND(R10*V10,0)-ROUND(R10*(1+V10),0)*W10) -> 962 | Q10: =IF(I10="",(O10-G10-(O10*0.1425%*0.65)-(O10*0.3%)-S10-T10),0) -> 0 | S10: 10 | U10: =(V10*50%)/(1+50%*V10) -> 0 | W10: 0.11 | X10: =(P10+Q10)/G10 -> 0.036097561 | Y10: =VLOOKUP(C10,每日行情!A:D,4,FALSE) -> 38.5 | Z10: =VLOOKUP(C10,每日行情!A:E,5,FALSE) -> 0.8 | AA10: =IF(I10="",((TODAY()-A10)*G10)/365.24,((I10-A10)*G10)/365.24) -> 1386.3487 | AB10: 台股
A11: 45709 | C11: 2357 | D11: 華碩 | E11: 100 | F11: 700 | G11: =E11*F11 -> 70000 | H11: 59 | I11: 45727 | J11: 646 | K11: =E11*J11 -> 64600 | L11: 55 | M11: 193 | N11: 0 | O11: =IF(I11="",E11*Y11,0) -> 0 | P11: =IF(I11="",R11-H11,(K11-H11-SUM(L11:N11)+R11-S11-T11)-G11)+(ROUND(R11*V11,0)-ROUND(R11*(1+V11),0)*W11) -> -5717 | Q11: =IF(I11="",(O11-G11-(O11*0.1425%*0.65)-(O11*0.3%)-S11-T11),0) -> 0 | S11: 10 | U11: =(V11*50%)/(1+50%*V11) -> 0 | W11: 0.11 | X11: =(P11+Q11)/G11 -> -0.081671429 | Y11: =VLOOKUP(C11,每日行情!A:D,4,FALSE) -> 994 | Z11: =VLOOKUP(C11,每日行情!A:E,5,FALSE) -> 19 | AA11: =IF(I11="",((TODAY()-A11)*G11)/365.24,((I11-A11)*G11)/365.24) -> 3449.7864 | AB11: 台股
A12: 45713 | C12: 1519 | D12: 華城 | E12: 1000 | F12: 654 | G12: =E12*F12 -> 654000 | H12: 559 | I12: 45727 | J12: 590 | K12: =E12*J12 -> 590000 | L12: 504 | M12: 1770 | N12: 0 | O12: =IF(I12="",E12*Y12,0) -> 0 | P12: =IF(I12="",R12-H12,(K12-H12-SUM(L12:N12)+R12-S12-T12)-G12)+(ROUND(R12*V12,0)-ROUND(R12*(1+V12),0)*W12) -> -66843 | Q12: =IF(I12="",(O12-G12-(O12*0.1425%*0.65)-(O12*0.3%)-S12-T12),0) -> 0 | S12: 10 | U12: =(V12*50%)/(1+50%*V12) -> 0 | W12: 0.11 | X12: =(P12+Q12)/G12 -> -0.10220642 | Y12: =VLOOKUP(C12,每日行情!A:D,4,FALSE) -> 656 | Z12: =VLOOKUP(C12,每日行情!A:E,5,FALSE) -> 7 | AA12: =IF(I12="",((TODAY()-A12)*G12)/365.24,((I12-A12)*G12)/365.24) -> 25068.448 | AB12: 台股
A13: 45723 | C13: 6257 | D13: 矽格 | E13: 1000 | F13: 81.7 | G13: =E13*F13 -> 81700 | H13: 69 | I13: 45727 | J13: 75.5 | K13: =E13*J13 -> 75500 | L13: 64 | M13: 226 | N13: 0 | O13: =IF(I13="",E13*Y13,0) -> 0 | P13: =IF(I13="",R13-H13,(K13-H13-SUM(L13:N13)+R13-S13-T13)-G13)+(ROUND(R13*V13,0)-ROUND(R13*(1+V13),0)*W13) -> -6569 | Q13: =IF(I13="",(O13-G13-(O13*0.1425%*0.65)-(O13*0.3%)-S13-T13),0) -> 0 | S13: 10 | U13: =(V13*50%)/(1+50%*V13) -> 0 | W13: 0.11 | X13: =(P13+Q13)/G13 -> -0.080403917 | Y13: =VLOOKUP(C13,每日行情!A:D,4,FALSE) -> 252 | Z13: =VLOOKUP(C13,每日行情!A:E,5,FALSE) -> -6 | AA13: =IF(I13="",((TODAY()-A13)*G13)/365.24,((I13-A13)*G13)/365.24) -> 894.75413 | AB13: 台股
A14: 45723 | C14: 2027 | D14: =VLOOKUP(C14,每日行情!A:B,2,FALSE) -> 大成鋼 | E14: 1000 | F14: 49.2 | G14: =E14*F14 -> 49200 | H14: 42 | I14: 45728 | J14: 48.85 | K14: =E14*J14 -> 48850 | L14: 41 | M14: 146 | N14: 0 | O14: =IF(I14="",E14*Y14,0) -> 0 | P14: =IF(I14="",R14-H14,(K14-H14-SUM(L14:N14)+R14-S14-T14)-G14)+(ROUND(R14*V14,0)-ROUND(R14*(1+V14),0)*W14) -> -589 | Q14: =IF(I14="",(O14-G14-(O14*0.1425%*0.65)-(O14*0.3%)-S14-T14),0) -> 0 | S14: 10 | U14: =(V14*50%)/(1+50%*V14) -> 0 | W14: 0.11 | X14: =(P14+Q14)/G14 -> -0.011971545 | Y14: =VLOOKUP(C14,每日行情!A:D,4,FALSE) -> 50.9 | Z14: =VLOOKUP(C14,每日行情!A:E,5,FALSE) -> 1.6 | AA14: =IF(I14="",((TODAY()-A14)*G14)/365.24,((I14-A14)*G14)/365.24) -> 673.52973 | AB14: 台股
A15: 45702 | C15: 2606 | D15: =VLOOKUP(C15,每日行情!A:B,2,FALSE) -> 裕民 | E15: 1000 | F15: 69.3 | G15: =E15*F15 -> 69300 | H15: 59 | I15: 45728 | J15: 70.6 | K15: =E15*J15 -> 70600 | L15: 60 | M15: 211 | N15: 0 | O15: =IF(I15="",E15*Y15,0) -> 0 | P15: =IF(I15="",R15-H15,(K15-H15-SUM(L15:N15)+R15-S15-T15)-G15)+(ROUND(R15*V15,0)-ROUND(R15*(1+V15),0)*W15) -> 960 | Q15: =IF(I15="",(O15-G15-(O15*0.1425%*0.65)-(O15*0.3%)-S15-T15),0) -> 0 | S15: 10 | U15: =(V15*50%)/(1+50%*V15) -> 0 | W15: 0.11 | X15: =(P15+Q15)/G15 -> 0.013852814 | Y15: =VLOOKUP(C15,每日行情!A:D,4,FALSE) -> 75.2 | Z15: =VLOOKUP(C15,每日行情!A:E,5,FALSE) -> -0.8 | AA15: =IF(I15="",((TODAY()-A15)*G15)/365.24,((I15-A15)*G15)/365.24) -> 4933.1946 | AB15: 台股
A16: 45729 | C16: 3211 | D16: =VLOOKUP(C16,每日行情!A:B,2,FALSE) -> 順達 | E16: 1000 | F16: 210.5 | G16: =E16*F16 -> 210500 | H16: 179 | I16: 45729 | J16: 213.5 | K16: =E16*J16 -> 213500 | L16: 182 | M16: 320 | N16: 0 | O16: =IF(I16="",E16*Y16,0) -> 0 | P16: =IF(I16="",R16-H16,(K16-H16-SUM(L16:N16)+R16-S16-T16)-G16)+(ROUND(R16*V16,0)-ROUND(R16*(1+V16),0)*W16) -> 2309 | Q16: =IF(I16="",(O16-G16-(O16*0.1425%*0.65)-(O16*0.3%)-S16-T16),0) -> 0 | S16: 10 | U16: =(V16*50%)/(1+50%*V16) -> 0 | W16: 0.11 | X16: =(P16+Q16)/G16 -> 0.010969121 | Y16: =VLOOKUP(C16,每日行情!A:D,4,FALSE) -> 346 | Z16: =VLOOKUP(C16,每日行情!A:E,5,FALSE) -> -3 | AA16: =IF(I16="",((TODAY()-A16)*G16)/365.24,((I16-A16)*G16)/365.24) -> 0 | AB16: 台股
A17: 45721 | C17: 6196 | D17: =VLOOKUP(C17,每日行情!A:B,2,FALSE) -> 帆宣 | E17: 1000 | F17: 172 | G17: =E17*F17 -> 172000 | H17: 147 | I17: 45729 | J17: 162 | K17: =E17*J17 -> 162000 | L17: 138 | M17: 486 | N17: 0 | O17: =IF(I17="",E17*Y17,0) -> 0 | P17: =IF(I17="",R17-H17,(K17-H17-SUM(L17:N17)+R17-S17-T17)-G17)+(ROUND(R17*V17,0)-ROUND(R17*(1+V17),0)*W17) -> -10781 | Q17: =IF(I17="",(O17-G17-(O17*0.1425%*0.65)-(O17*0.3%)-S17-T17),0) -> 0 | S17: 10 | U17: =(V17*50%)/(1+50%*V17) -> 0 | W17: 0.11 | X17: =(P17+Q17)/G17 -> -0.062680233 | Y17: =VLOOKUP(C17,每日行情!A:D,4,FALSE) -> 609 | Z17: =VLOOKUP(C17,每日行情!A:E,5,FALSE) -> -4 | AA17: =IF(I17="",((TODAY()-A17)*G17)/365.24,((I17-A17)*G17)/365.24) -> 3767.3858 | AB17: 台股
A18: 45728 | C18: 4931 | D18: =VLOOKUP(C18,每日行情!A:B,2,FALSE) -> 新盛力 | E18: 1000 | F18: 86.8 | G18: =E18*F18 -> 86800 | H18: 74 | I18: 45730 | J18: 87.6 | K18: =E18*J18 -> 87600 | L18: 74 | M18: 262 | N18: 0 | O18: =IF(I18="",E18*Y18,0) -> 0 | P18: =IF(I18="",R18-H18,(K18-H18-SUM(L18:N18)+R18-S18-T18)-G18)+(ROUND(R18*V18,0)-ROUND(R18*(1+V18),0)*W18) -> 380 | Q18: =IF(I18="",(O18-G18-(O18*0.1425%*0.65)-(O18*0.3%)-S18-T18),0) -> 0 | S18: 10 | U18: =(V18*50%)/(1+50%*V18) -> 0 | W18: 0.11 | X18: =(P18+Q18)/G18 -> 0.0043778802 | Y18: =VLOOKUP(C18,每日行情!A:D,4,FALSE) -> 217 | Z18: =VLOOKUP(C18,每日行情!A:E,5,FALSE) -> 4 | AA18: =IF(I18="",((TODAY()-A18)*G18)/365.24,((I18-A18)*G18)/365.24) -> 475.30391 | AB18: 台股
A19: 45730 | C19: 3163 | D19: =VLOOKUP(C19,每日行情!A:B,2,FALSE) -> 波若威 | E19: 1000 | F19: 170 | G19: =E19*F19 -> 170000 | H19: 145 | I19: 45730 | J19: 173 | K19: =E19*J19 -> 173000 | L19: 147 | M19: 259 | N19: 0 | O19: =IF(I19="",E19*Y19,0) -> 0 | P19: =IF(I19="",R19-H19,(K19-H19-SUM(L19:N19)+R19-S19-T19)-G19)+(ROUND(R19*V19,0)-ROUND(R19*(1+V19),0)*W19) -> 2439 | Q19: =IF(I19="",(O19-G19-(O19*0.1425%*0.65)-(O19*0.3%)-S19-T19),0) -> 0 | S19: 10 | U19: =(V19*50%)/(1+50%*V19) -> 0 | W19: 0.11 | X19: =(P19+Q19)/G19 -> 0.014347059 | Y19: =VLOOKUP(C19,每日行情!A:D,4,FALSE) -> 589 | Z19: =VLOOKUP(C19,每日行情!A:E,5,FALSE) -> -15 | AA19: =IF(I19="",((TODAY()-A19)*G19)/365.24,((I19-A19)*G19)/365.24) -> 0 | AB19: 台股
A20: 45736 | C20: 2634 | D20: =VLOOKUP(C20,每日行情!A:B,2,FALSE) -> 漢翔 | E20: 1000 | F20: 52.9 | G20: =E20*F20 -> 52900 | H20: 45 | I20: 45736 | J20: 51.1 | K20: =E20*J20 -> 51100 | L20: 43 | M20: 76 | N20: 0 | O20: =IF(I20="",E20*Y20,0) -> 0 | P20: =IF(I20="",R20-H20,(K20-H20-SUM(L20:N20)+R20-S20-T20)-G20)+(ROUND(R20*V20,0)-ROUND(R20*(1+V20),0)*W20) -> -1974 | Q20: =IF(I20="",(O20-G20-(O20*0.1425%*0.65)-(O20*0.3%)-S20-T20),0) -> 0 | S20: 10 | U20: =(V20*50%)/(1+50%*V20) -> 0 | W20: 0.11 | X20: =(P20+Q20)/G20 -> -0.03731569 | Y20: =VLOOKUP(C20,每日行情!A:D,4,FALSE) -> 62.1 | Z20: =VLOOKUP(C20,每日行情!A:E,5,FALSE) -> 1.4 | AA20: =IF(I20="",((TODAY()-A20)*G20)/365.24,((I20-A20)*G20)/365.24) -> 0 | AB20: 台股
A21: 45714 | C21: 8299 | D21: =VLOOKUP(C21,每日行情!A:B,2,FALSE) -> 群聯 | E21: 1000 | F21: 564 | G21: =E21*F21 -> 564000 | H21: 482 | I21: 45741 | J21: 573 | K21: =E21*J21 -> 573000 | L21: 489 | M21: 1719 | N21: 0 | O21: =IF(I21="",E21*Y21,0) -> 0 | P21: =IF(I21="",R21-H21,(K21-H21-SUM(L21:N21)+R21-S21-T21)-G21)+(ROUND(R21*V21,0)-ROUND(R21*(1+V21),0)*W21) -> 6300 | Q21: =IF(I21="",(O21-G21-(O21*0.1425%*0.65)-(O21*0.3%)-S21-T21),0) -> 0 | S21: 10 | U21: =(V21*50%)/(1+50%*V21) -> 0 | W21: 0.11 | X21: =(P21+Q21)/G21 -> 0.011170213 | Y21: =VLOOKUP(C21,每日行情!A:D,4,FALSE) -> 1890 | Z21: =VLOOKUP(C21,每日行情!A:E,5,FALSE) -> 60 | AA21: =IF(I21="",((TODAY()-A21)*G21)/365.24,((I21-A21)*G21)/365.24) -> 41693.133 | AB21: 台股
A22: 45737 | C22: 1319 | D22: =VLOOKUP(C22,每日行情!A:B,2,FALSE) -> 東陽 | E22: 1000 | F22: 138 | G22: =E22*F22 -> 138000 | H22: 117 | I22: 45742 | J22: 133 | K22: =E22*J22 -> 133000 | L22: 113 | M22: 399 | N22: 0 | O22: =IF(I22="",E22*Y22,0) -> 0 | P22: =IF(I22="",R22-H22,(K22-H22-SUM(L22:N22)+R22-S22-T22)-G22)+(ROUND(R22*V22,0)-ROUND(R22*(1+V22),0)*W22) -> -5639 | Q22: =IF(I22="",(O22-G22-(O22*0.1425%*0.65)-(O22*0.3%)-S22-T22),0) -> 0 | S22: 10 | U22: =(V22*50%)/(1+50%*V22) -> 0 | W22: 0.11 | X22: =(P22+Q22)/G22 -> -0.040862319 | Y22: =VLOOKUP(C22,每日行情!A:D,4,FALSE) -> 83.5 | Z22: =VLOOKUP(C22,每日行情!A:E,5,FALSE) -> 0.2 | AA22: =IF(I22="",((TODAY()-A22)*G22)/365.24,((I22-A22)*G22)/365.24) -> 1889.1688 | AB22: 台股
A23: 45735 | C23: 2609 | D23: =VLOOKUP(C23,每日行情!A:B,2,FALSE) -> 陽明 | E23: 1000 | F23: 77.2 | G23: =E23*F23 -> 77200 | H23: 45 | I23: 45743 | J23: 76.2 | K23: =E23*J23 -> 76200 | L23: 65 | M23: 228 | N23: 0 | O23: =IF(I23="",E23*Y23,0) -> 0 | P23: =IF(I23="",R23-H23,(K23-H23-SUM(L23:N23)+R23-S23-T23)-G23)+(ROUND(R23*V23,0)-ROUND(R23*(1+V23),0)*W23) -> -1348 | Q23: =IF(I23="",(O23-G23-(O23*0.1425%*0.65)-(O23*0.3%)-S23-T23),0) -> 0 | S23: 10 | U23: =(V23*50%)/(1+50%*V23) -> 0 | W23: 0.11 | X23: =(P23+Q23)/G23 -> -0.01746114 | Y23: =VLOOKUP(C23,每日行情!A:D,4,FALSE) -> 64.7 | Z23: =VLOOKUP(C23,每日行情!A:E,5,FALSE) -> 1.4 | AA23: =IF(I23="",((TODAY()-A23)*G23)/365.24,((I23-A23)*G23)/365.24) -> 1690.9429 | AB23: 台股
A24: 45737 | C24: 2634 | D24: =VLOOKUP(C24,每日行情!A:B,2,FALSE) -> 漢翔 | E24: 1000 | F24: 51.7 | G24: =E24*F24 -> 51700 | H24: 44 | I24: 45743 | J24: 52.5 | K24: =E24*J24 -> 52500 | L24: 44 | M24: 157 | N24: 0 | O24: =IF(I24="",E24*Y24,0) -> 0 | P24: =IF(I24="",R24-H24,(K24-H24-SUM(L24:N24)+R24-S24-T24)-G24)+(ROUND(R24*V24,0)-ROUND(R24*(1+V24),0)*W24) -> 545 | Q24: =IF(I24="",(O24-G24-(O24*0.1425%*0.65)-(O24*0.3%)-S24-T24),0) -> 0 | S24: 10 | U24: =(V24*50%)/(1+50%*V24) -> 0 | W24: 0.11 | X24: =(P24+Q24)/G24 -> 0.010541586 | Y24: =VLOOKUP(C24,每日行情!A:D,4,FALSE) -> 62.1 | Z24: =VLOOKUP(C24,每日行情!A:E,5,FALSE) -> 1.4 | AA24: =IF(I24="",((TODAY()-A24)*G24)/365.24,((I24-A24)*G24)/365.24) -> 849.30457 | AB24: 台股
A25: 45740 | C25: 3035 | D25: =VLOOKUP(C25,每日行情!A:B,2,FALSE) -> 智原 | E25: 1000 | F25: 249 | G25: =E25*F25 -> 249000 | H25: 212 | I25: 45743 | J25: 242 | K25: =E25*J25 -> 242000 | L25: 206 | M25: 726 | N25: 0 | O25: =IF(I25="",E25*Y25,0) -> 0 | P25: =IF(I25="",R25-H25,(K25-H25-SUM(L25:N25)+R25-S25-T25)-G25)+(ROUND(R25*V25,0)-ROUND(R25*(1+V25),0)*W25) -> -8154 | Q25: =IF(I25="",(O25-G25-(O25*0.1425%*0.65)-(O25*0.3%)-S25-T25),0) -> 0 | S25: 10 | U25: =(V25*50%)/(1+50%*V25) -> 0 | W25: 0.11 | X25: =(P25+Q25)/G25 -> -0.032746988 | Y25: =VLOOKUP(C25,每日行情!A:D,4,FALSE) -> 197.5 | Z25: =VLOOKUP(C25,每日行情!A:E,5,FALSE) -> 0 | AA25: =IF(I25="",((TODAY()-A25)*G25)/365.24,((I25-A25)*G25)/365.24) -> 2045.2305 | AB25: 台股
A26: 45740 | C26: 5534 | D26: =VLOOKUP(C26,每日行情!A:B,2,FALSE) -> 長虹 | E26: 1000 | F26: 108 | G26: =E26*F26 -> 108000 | H26: 92 | I26: 45743 | J26: 105.5 | K26: =E26*J26 -> 105500 | L26: 90 | M26: 316 | N26: 0 | O26: =IF(I26="",E26*Y26,0) -> 0 | P26: =IF(I26="",R26-H26,(K26-H26-SUM(L26:N26)+R26-S26-T26)-G26)+(ROUND(R26*V26,0)-ROUND(R26*(1+V26),0)*W26) -> -3008 | Q26: =IF(I26="",(O26-G26-(O26*0.1425%*0.65)-(O26*0.3%)-S26-T26),0) -> 0 | S26: 10 | U26: =(V26*50%)/(1+50%*V26) -> 0 | W26: 0.11 | X26: =(P26+Q26)/G26 -> -0.027851852 | Y26: =VLOOKUP(C26,每日行情!A:D,4,FALSE) -> 70.3 | Z26: =VLOOKUP(C26,每日行情!A:E,5,FALSE) -> -0.5 | AA26: =IF(I26="",((TODAY()-A26)*G26)/365.24,((I26-A26)*G26)/365.24) -> 887.08794 | AB26: 台股
A27: 45910 | C27: 1711 | D27: =VLOOKUP(C27,每日行情!A:B,2,FALSE) -> 永光 | E27: 3000 | F27: 20.3 | G27: =E27*F27 -> 60900 | H27: 52 | I27: 45924 | J27: 19.65 | K27: =E27*J27 -> 58950 | L27: 50 | M27: 176 | N27: 0 | O27: =IF(I27="",E27*Y27,0) -> 0 | P27: =IF(I27="",R27-H27,(K27-H27-SUM(L27:N27)+R27-S27-T27)-G27)+(ROUND(R27*V27,0)-ROUND(R27*(1+V27),0)*W27) -> -2228 | Q27: =IF(I27="",(O27-G27-(O27*0.1425%*0.65)-(O27*0.3%)-S27-T27),0) -> 0 | U27: =(V27*50%)/(1+50%*V27) -> 0 | W27: 0.11 | X27: =(P27+Q27)/G27 -> -0.036584565 | Y27: =VLOOKUP(C27,每日行情!A:D,4,FALSE) -> 44.45 | Z27: =VLOOKUP(C27,每日行情!A:E,5,FALSE) -> 1.35 | AA27: =IF(I27="",((TODAY()-A27)*G27)/365.24,((I27-A27)*G27)/365.24) -> 2334.3555 | AB27: 台股
A28: 45917 | C28: 3006 | D28: =VLOOKUP(C28,每日行情!A:B,2,FALSE) -> 晶豪科 | E28: 1000 | F28: 65.4 | G28: =E28*F28 -> 65400 | H28: 55 | I28: 45925 | J28: 72.5 | K28: =E28*J28 -> 72500 | L28: 61 | M28: 217 | N28: 0 | O28: =IF(I28="",E28*Y28,0) -> 0 | P28: =IF(I28="",R28-H28,(K28-H28-SUM(L28:N28)+R28-S28-T28)-G28)+(ROUND(R28*V28,0)-ROUND(R28*(1+V28),0)*W28) -> 6767 | Q28: =IF(I28="",(O28-G28-(O28*0.1425%*0.65)-(O28*0.3%)-S28-T28),0) -> 0 | U28: =(V28*50%)/(1+50%*V28) -> 0 | W28: 0.11 | X28: =(P28+Q28)/G28 -> 0.10347095 | Y28: =VLOOKUP(C28,每日行情!A:D,4,FALSE) -> 244.5 | Z28: =VLOOKUP(C28,每日行情!A:E,5,FALSE) -> 15.5 | AA28: =IF(I28="",((TODAY()-A28)*G28)/365.24,((I28-A28)*G28)/365.24) -> 1432.4828 | AB28: 台股
A29: 45917 | C29: 3042 | D29: =VLOOKUP(C29,每日行情!A:B,2,FALSE) -> 晶技 | E29: 1000 | F29: 92.8 | G29: =E29*F29 -> 92800 | H29: 79 | I29: 45925 | J29: 91.4 | K29: =E29*J29 -> 91400 | L29: 78 | M29: 274 | N29: 0 | O29: =IF(I29="",E29*Y29,0) -> 0 | P29: =IF(I29="",R29-H29,(K29-H29-SUM(L29:N29)+R29-S29-T29)-G29)+(ROUND(R29*V29,0)-ROUND(R29*(1+V29),0)*W29) -> -1831 | Q29: =IF(I29="",(O29-G29-(O29*0.1425%*0.65)-(O29*0.3%)-S29-T29),0) -> 0 | U29: =(V29*50%)/(1+50%*V29) -> 0 | W29: 0.11 | X29: =(P29+Q29)/G29 -> -0.019730603 | Y29: =VLOOKUP(C29,每日行情!A:D,4,FALSE) -> 188 | Z29: =VLOOKUP(C29,每日行情!A:E,5,FALSE) -> -1.5 | AA29: =IF(I29="",((TODAY()-A29)*G29)/365.24,((I29-A29)*G29)/365.24) -> 2032.6361 | AB29: 台股
A30: 45917 | C30: 3532 | D30: =VLOOKUP(C30,每日行情!A:B,2,FALSE) -> 台勝科 | E30: 1000 | F30: 95 | G30: =E30*F30 -> 95000 | H30: 81 | I30: 45925 | J30: 106.5 | K30: =E30*J30 -> 106500 | L30: 91 | M30: 319 | N30: 0 | O30: =IF(I30="",E30*Y30,0) -> 0 | P30: =IF(I30="",R30-H30,(K30-H30-SUM(L30:N30)+R30-S30-T30)-G30)+(ROUND(R30*V30,0)-ROUND(R30*(1+V30),0)*W30) -> 11009 | Q30: =IF(I30="",(O30-G30-(O30*0.1425%*0.65)-(O30*0.3%)-S30-T30),0) -> 0 | U30: =(V30*50%)/(1+50%*V30) -> 0 | W30: 0.11 | X30: =(P30+Q30)/G30 -> 0.11588421 | Y30: =VLOOKUP(C30,每日行情!A:D,4,FALSE) -> 417.5 | Z30: =VLOOKUP(C30,每日行情!A:E,5,FALSE) -> 17.5 | AA30: =IF(I30="",((TODAY()-A30)*G30)/365.24,((I30-A30)*G30)/365.24) -> 2080.8236 | AB30: 台股
A31: 45925 | C31: 2324 | D31: =VLOOKUP(C31,每日行情!A:B,2,FALSE) -> 仁寶 | E31: 2000 | F31: 37.1 | G31: =E31*F31 -> 74200 | H31: 63 | I31: 45930 | J31: 32.4 | K31: =E31*J31 -> 64800 | L31: 55 | M31: 194 | N31: 0 | O31: =IF(I31="",E31*Y31,0) -> 0 | P31: =IF(I31="",R31-H31,(K31-H31-SUM(L31:N31)+R31-S31-T31)-G31)+(ROUND(R31*V31,0)-ROUND(R31*(1+V31),0)*W31) -> -9712 | Q31: =IF(I31="",(O31-G31-(O31*0.1425%*0.65)-(O31*0.3%)-S31-T31),0) -> 0 | U31: =(V31*50%)/(1+50%*V31) -> 0 | W31: 0.11 | X31: =(P31+Q31)/G31 -> -0.13088949 | Y31: =VLOOKUP(C31,每日行情!A:D,4,FALSE) -> 36.7 | Z31: =VLOOKUP(C31,每日行情!A:E,5,FALSE) -> 0.7 | AA31: =IF(I31="",((TODAY()-A31)*G31)/365.24,((I31-A31)*G31)/365.24) -> 1015.7705 | AB31: 台股
A32: 45925 | C32: 6548 | D32: =VLOOKUP(C32,每日行情!A:B,2,FALSE) -> 長科* | E32: 2000 | F32: 35.35 | G32: =E32*F32 -> 70700 | H32: 60 | I32: 45933 | J32: 36 | K32: =E32*J32 -> 72000 | L32: 61 | M32: 216 | N32: 0 | O32: =IF(I32="",E32*Y32,0) -> 0 | P32: =IF(I32="",R32-H32,(K32-H32-SUM(L32:N32)+R32-S32-T32)-G32)+(ROUND(R32*V32,0)-ROUND(R32*(1+V32),0)*W32) -> 963 | Q32: =IF(I32="",(O32-G32-(O32*0.1425%*0.65)-(O32*0.3%)-S32-T32),0) -> 0 | U32: =(V32*50%)/(1+50%*V32) -> 0 | W32: 0.11 | X32: =(P32+Q32)/G32 -> 0.013620934 | Y32: =VLOOKUP(C32,每日行情!A:D,4,FALSE) -> 83.4 | Z32: =VLOOKUP(C32,每日行情!A:E,5,FALSE) -> 1.2 | AA32: =IF(I32="",((TODAY()-A32)*G32)/365.24,((I32-A32)*G32)/365.24) -> 1548.5708 | AB32: 台股
A33: 45925 | C33: 2375 | D33: =VLOOKUP(C33,每日行情!A:B,2,FALSE) -> 凱美 | E33: 1000 | F33: 78.8 | G33: =E33*F33 -> 78800 | H33: 67 | I33: 45944 | J33: 76.8 | K33: =E33*J33 -> 76800 | L33: 65 | M33: 230 | N33: 0 | O33: =IF(I33="",E33*Y33,0) -> 0 | P33: =IF(I33="",R33-H33,(K33-H33-SUM(L33:N33)+R33-S33-T33)-G33)+(ROUND(R33*V33,0)-ROUND(R33*(1+V33),0)*W33) -> -2362 | Q33: =IF(I33="",(O33-G33-(O33*0.1425%*0.65)-(O33*0.3%)-S33-T33),0) -> 0 | U33: =(V33*50%)/(1+50%*V33) -> 0 | W33: 0.11 | X33: =(P33+Q33)/G33 -> -0.029974619 | Y33: =VLOOKUP(C33,每日行情!A:D,4,FALSE) -> 125.5 | Z33: =VLOOKUP(C33,每日行情!A:E,5,FALSE) -> -5.5 | AA33: =IF(I33="",((TODAY()-A33)*G33)/365.24,((I33-A33)*G33)/365.24) -> 4099.2224 | AB33: 台股
A34: 45925 | C34: 3628 | D34: =VLOOKUP(C34,每日行情!A:B,2,FALSE) -> 盈正 | E34: 1000 | F34: 59.1 | G34: =E34*F34 -> 59100 | H34: 50 | I34: 45939 | J34: 73.5 | K34: =E34*J34 -> 73500 | L34: 62 | M34: 220 | N34: 0 | O34: =IF(I34="",E34*Y34,0) -> 0 | P34: =IF(I34="",R34-H34,(K34-H34-SUM(L34:N34)+R34-S34-T34)-G34)+(ROUND(R34*V34,0)-ROUND(R34*(1+V34),0)*W34) -> 14068 | Q34: =IF(I34="",(O34-G34-(O34*0.1425%*0.65)-(O34*0.3%)-S34-T34),0) -> 0 | U34: =(V34*50%)/(1+50%*V34) -> 0 | W34: 0.11 | X34: =(P34+Q34)/G34 -> 0.23803723 | Y34: =VLOOKUP(C34,每日行情!A:D,4,FALSE) -> 71.5 | Z34: =VLOOKUP(C34,每日行情!A:E,5,FALSE) -> 1.4 | AA34: =IF(I34="",((TODAY()-A34)*G34)/365.24,((I34-A34)*G34)/365.24) -> 2265.3598 | AB34: 台股
A35: 45889 | C35: 3661 | D35: =VLOOKUP(C35,每日行情!A:B,2,FALSE) -> 世芯-KY | E35: 10 | F35: 3760 | G35: =E35*F35 -> 37600 | H35: 32 | I35: 45964 | J35: 3460 | K35: =E35*J35 -> 34600 | L35: 30 | M35: 104 | N35: 0 | O35: =IF(I35="",E35*Y35,0) -> 0 | P35: =IF(I35="",R35-H35,(K35-H35-SUM(L35:N35)+R35-S35-T35)-G35)+(ROUND(R35*V35,0)-ROUND(R35*(1+V35),0)*W35) -> -2852.04 | Q35: =IF(I35="",(O35-G35-(O35*0.1425%*0.65)-(O35*0.3%)-S35-T35),0) -> 0 | R35: 364 | S35: 10 | U35: =(V35*50%)/(1+50%*V35) -> 0 | W35: 0.11 | X35: =(P35+Q35)/G35 -> -0.075852128 | Y35: =VLOOKUP(C35,每日行情!A:D,4,FALSE) -> 3685 | Z35: =VLOOKUP(C35,每日行情!A:E,5,FALSE) -> -20 | AA35: =IF(I35="",((TODAY()-A35)*G35)/365.24,((I35-A35)*G35)/365.24) -> 7720.9506 | AB35: 台股
A36: 45924 | C36: 3661 | D36: =VLOOKUP(C36,每日行情!A:B,2,FALSE) -> 世芯-KY | E36: 10 | F36: 3420 | G36: =E36*F36 -> 34200 | H36: 29 | I36: 45964 | J36: 3460 | K36: =E36*J36 -> 34600 | L36: 30 | M36: 104 | N36: 0 | O36: =IF(I36="",E36*Y36,0) -> 0 | P36: =IF(I36="",R36-H36,(K36-H36-SUM(L36:N36)+R36-S36-T36)-G36)+(ROUND(R36*V36,0)-ROUND(R36*(1+V36),0)*W36) -> 237 | Q36: =IF(I36="",(O36-G36-(O36*0.1425%*0.65)-(O36*0.3%)-S36-T36),0) -> 0 | U36: =(V36*50%)/(1+50%*V36) -> 0 | W36: 0.11 | X36: =(P36+Q36)/G36 -> 0.0069298246 | Y36: =VLOOKUP(C36,每日行情!A:D,4,FALSE) -> 3685 | Z36: =VLOOKUP(C36,每日行情!A:E,5,FALSE) -> -20 | AA36: =IF(I36="",((TODAY()-A36)*G36)/365.24,((I36-A36)*G36)/365.24) -> 3745.4824 | AB36: 台股
A37: 45926 | C37: 3661 | D37: =VLOOKUP(C37,每日行情!A:B,2,FALSE) -> 世芯-KY | E37: 10 | F37: 3260 | G37: =E37*F37 -> 32600 | H37: 27 | I37: 45964 | J37: 3460 | K37: =E37*J37 -> 34600 | L37: 29 | M37: 104 | N37: 0 | O37: =IF(I37="",E37*Y37,0) -> 0 | P37: =IF(I37="",R37-H37,(K37-H37-SUM(L37:N37)+R37-S37-T37)-G37)+(ROUND(R37*V37,0)-ROUND(R37*(1+V37),0)*W37) -> 1840 | Q37: =IF(I37="",(O37-G37-(O37*0.1425%*0.65)-(O37*0.3%)-S37-T37),0) -> 0 | U37: =(V37*50%)/(1+50%*V37) -> 0 | W37: 0.11 | X37: =(P37+Q37)/G37 -> 0.056441718 | Y37: =VLOOKUP(C37,每日行情!A:D,4,FALSE) -> 3685 | Z37: =VLOOKUP(C37,每日行情!A:E,5,FALSE) -> -20 | AA37: =IF(I37="",((TODAY()-A37)*G37)/365.24,((I37-A37)*G37)/365.24) -> 3391.7424 | AB37: 台股
A38: 45944 | C38: 3661 | D38: =VLOOKUP(C38,每日行情!A:B,2,FALSE) -> 世芯-KY | E38: 10 | F38: 3170 | G38: =E38*F38 -> 31700 | H38: 27 | I38: 45964 | J38: 3460 | K38: =E38*J38 -> 34600 | L38: 29 | M38: 103 | N38: 0 | O38: =IF(I38="",E38*Y38,0) -> 0 | P38: =IF(I38="",R38-H38,(K38-H38-SUM(L38:N38)+R38-S38-T38)-G38)+(ROUND(R38*V38,0)-ROUND(R38*(1+V38),0)*W38) -> 2741 | Q38: =IF(I38="",(O38-G38-(O38*0.1425%*0.65)-(O38*0.3%)-S38-T38),0) -> 0 | U38: =(V38*50%)/(1+50%*V38) -> 0 | W38: 0.11 | X38: =(P38+Q38)/G38 -> 0.086466877 | Y38: =VLOOKUP(C38,每日行情!A:D,4,FALSE) -> 3685 | Z38: =VLOOKUP(C38,每日行情!A:E,5,FALSE) -> -20 | AA38: =IF(I38="",((TODAY()-A38)*G38)/365.24,((I38-A38)*G38)/365.24) -> 1735.8449 | AB38: 台股
A39: 46043 | C39: 50 | D39: =VLOOKUP(C39,每日行情!A:B,2,FALSE) -> 元大台灣50 | E39: 2000 | F39: 72.45 | G39: =E39*F39 -> 144900 | H39: 123 | I39: 46050 | J39: 74 | K39: =E39*J39 -> 148000 | L39: 126 | M39: 148 | N39: 0 | O39: =IF(I39="",E39*Y39,0) -> 0 | P39: =IF(I39="",R39-H39,(K39-H39-SUM(L39:N39)+R39-S39-T39)-G39)+(ROUND(R39*V39,0)-ROUND(R39*(1+V39),0)*W39) -> 4473 | Q39: =IF(I39="",(O39-G39-(O39*0.1425%*0.65)-(O39*0.3%)-S39-T39),0) -> 0 | R39: 2000 | S39: 10 | U39: =(V39*50%)/(1+50%*V39) -> 0 | W39: 0.11 | X39: =(P39+Q39)/G39 -> 0.030869565 | Y39: =VLOOKUP(C39,每日行情!A:D,4,FALSE) -> 109 | Z39: =VLOOKUP(C39,每日行情!A:E,5,FALSE) -> 0.1 | AA39: =IF(I39="",((TODAY()-A39)*G39)/365.24,((I39-A39)*G39)/365.24) -> 2777.0781 | AB39: 台股 ETF
A40: 45901 | C40: 56 | D40: =VLOOKUP(C40,每日行情!A:B,2,FALSE) -> 元大高股息 | E40: 285 | F40: 34.69 | G40: 9886 | H40: 1 | I40: 46051 | J40: 38.23 | K40: =E40*J40 -> 10895.55 | L40: 32 | M40: 38 | N40: 0 | O40: =IF(I40="",E40*Y40,0) -> 0 | P40: =IF(I40="",R40-H40,(K40-H40-SUM(L40:N40)+R40-S40-T40)-G40)+(ROUND(R40*V40,0)-ROUND(R40*(1+V40),0)*W40) -> 1223.14 | Q40: =IF(I40="",(O40-G40-(O40*0.1425%*0.65)-(O40*0.3%)-S40-T40),0) -> 0 | R40: 331 | S40: 10 | U40: =(V40*50%)/(1+50%*V40) -> 0 | W40: 0.11 | X40: =(P40+Q40)/G40 -> 0.12372446 | Y40: =VLOOKUP(C40,每日行情!A:D,4,FALSE) -> 58.75 | Z40: =VLOOKUP(C40,每日行情!A:E,5,FALSE) -> 0.5 | AA40: =IF(I40="",((TODAY()-A40)*G40)/365.24,((I40-A40)*G40)/365.24) -> 4060.0701 | AB40: 台股 ETF
A41: 45931 | C41: 56 | D41: =VLOOKUP(C41,每日行情!A:B,2,FALSE) -> 元大高股息 | E41: 268 | F41: 36.89 | G41: 9886 | H41: 1 | I41: 46051 | J41: 38.23 | K41: =E41*J41 -> 10245.64 | L41: 11 | M41: 13 | N41: 0 | O41: =IF(I41="",E41*Y41,0) -> 0 | P41: =IF(I41="",R41-H41,(K41-H41-SUM(L41:N41)+R41-S41-T41)-G41)+(ROUND(R41*V41,0)-ROUND(R41*(1+V41),0)*W41) -> 618.34 | Q41: =IF(I41="",(O41-G41-(O41*0.1425%*0.65)-(O41*0.3%)-S41-T41),0) -> 0 | R41: 330 | S41: 10 | U41: =(V41*50%)/(1+50%*V41) -> 0 | W41: 0.11 | X41: =(P41+Q41)/G41 -> 0.062547036 | Y41: =VLOOKUP(C41,每日行情!A:D,4,FALSE) -> 58.75 | Z41: =VLOOKUP(C41,每日行情!A:E,5,FALSE) -> 0.5 | AA41: =IF(I41="",((TODAY()-A41)*G41)/365.24,((I41-A41)*G41)/365.24) -> 3248.0561 | AB41: 台股 ETF
A42: 45964 | C42: 56 | D42: =VLOOKUP(C42,每日行情!A:B,2,FALSE) -> 元大高股息 | E42: 264 | F42: 37.35 | G42: 9860 | H42: 1 | I42: 46051 | J42: 38.23 | K42: =E42*J42 -> 10092.72 | N42: 0 | O42: =IF(I42="",E42*Y42,0) -> 0 | P42: =IF(I42="",R42-H42,(K42-H42-SUM(L42:N42)+R42-S42-T42)-G42)+(ROUND(R42*V42,0)-ROUND(R42*(1+V42),0)*W42) -> 515.42 | Q42: =IF(I42="",(O42-G42-(O42*0.1425%*0.65)-(O42*0.3%)-S42-T42),0) -> 0 | R42: 330 | S42: 10 | U42: =(V42*50%)/(1+50%*V42) -> 0 | W42: 0.11 | X42: =(P42+Q42)/G42 -> 0.052273834 | Y42: =VLOOKUP(C42,每日行情!A:D,4,FALSE) -> 58.75 | Z42: =VLOOKUP(C42,每日行情!A:E,5,FALSE) -> 0.5 | AA42: =IF(I42="",((TODAY()-A42)*G42)/365.24,((I42-A42)*G42)/365.24) -> 2348.6475 | AB42: 台股 ETF
A43: 45992 | C43: 56 | D43: =VLOOKUP(C43,每日行情!A:B,2,FALSE) -> 元大高股息 | E43: 275 | F43: 36.03 | G43: 9908 | H43: 1 | I43: 46051 | J43: 38.23 | K43: =E43*J43 -> 10513.25 | N43: 0 | O43: =IF(I43="",E43*Y43,0) -> 0 | P43: =IF(I43="",R43-H43,(K43-H43-SUM(L43:N43)+R43-S43-T43)-G43)+(ROUND(R43*V43,0)-ROUND(R43*(1+V43),0)*W43) -> 887.95 | Q43: =IF(I43="",(O43-G43-(O43*0.1425%*0.65)-(O43*0.3%)-S43-T43),0) -> 0 | R43: 330 | S43: 10 | U43: =(V43*50%)/(1+50%*V43) -> 0 | W43: 0.11 | X43: =(P43+Q43)/G43 -> 0.089619499 | Y43: =VLOOKUP(C43,每日行情!A:D,4,FALSE) -> 58.75 | Z43: =VLOOKUP(C43,每日行情!A:E,5,FALSE) -> 0.5 | AA43: =IF(I43="",((TODAY()-A43)*G43)/365.24,((I43-A43)*G43)/365.24) -> 1600.5147 | AB43: 台股 ETF
A44: 46024 | C44: 56 | D44: =VLOOKUP(C44,每日行情!A:B,2,FALSE) -> 元大高股息 | E44: 267 | F44: 37.02 | G44: 9884 | H44: 1 | I44: 46051 | J44: 38.23 | K44: =E44*J44 -> 10207.41 | N44: 0 | O44: =IF(I44="",E44*Y44,0) -> 0 | P44: =IF(I44="",R44-H44,(K44-H44-SUM(L44:N44)+R44-S44-T44)-G44)+(ROUND(R44*V44,0)-ROUND(R44*(1+V44),0)*W44) -> 606.11 | Q44: =IF(I44="",(O44-G44-(O44*0.1425%*0.65)-(O44*0.3%)-S44-T44),0) -> 0 | R44: 330 | S44: 10 | U44: =(V44*50%)/(1+50%*V44) -> 0 | W44: 0.11 | X44: =(P44+Q44)/G44 -> 0.061322339 | Y44: =VLOOKUP(C44,每日行情!A:D,4,FALSE) -> 58.75 | Z44: =VLOOKUP(C44,每日行情!A:E,5,FALSE) -> 0.5 | AA44: =IF(I44="",((TODAY()-A44)*G44)/365.24,((I44-A44)*G44)/365.24) -> 730.66477 | AB44: 台股 ETF
A45: 45908 | C45: 770 | D45: =VLOOKUP(C45,每日行情!A:B,2,FALSE) -> 國泰北美科技 | E45: 192 | F45: 51.02 | G45: 9795 | H45: 1 | I45: 46090 | J45: 50.05 | K45: =E45*J45 -> 9609.6 | L45: 8 | M45: 10 | N45: 0 | O45: =IF(I45="",E45*Y45,0) -> 0 | P45: =IF(I45="",R45-H45,(K45-H45-SUM(L45:N45)+R45-S45-T45)-G45)+(ROUND(R45*V45,0)-ROUND(R45*(1+V45),0)*W45) -> 446.87 | Q45: =IF(I45="",(O45-G45-(O45*0.1425%*0.65)-(O45*0.3%)-S45-T45),0) -> 0 | R45: 743 | S45: 10 | U45: =(V45*50%)/(1+50%*V45) -> 0 | W45: 0.11 | X45: =(P45+Q45)/G45 -> 0.045622256 | Y45: =VLOOKUP(C45,每日行情!A:D,4,FALSE) -> 64.95 | Z45: =VLOOKUP(C45,每日行情!A:E,5,FALSE) -> 0.6 | AA45: =IF(I45="",((TODAY()-A45)*G45)/365.24,((I45-A45)*G45)/365.24) -> 4880.8729 | AB45: 台股 ETF
A46: 45937 | C46: 770 | D46: =VLOOKUP(C46,每日行情!A:B,2,FALSE) -> 國泰北美科技 | E46: 179 | F46: 54.96 | G46: 9837 | H46: 1 | I46: 46090 | J46: 50.05 | K46: =E46*J46 -> 8958.95 | L46: 8 | M46: 10 | N46: 0 | O46: =IF(I46="",E46*Y46,0) -> 0 | P46: =IF(I46="",R46-H46,(K46-H46-SUM(L46:N46)+R46-S46-T46)-G46)+(ROUND(R46*V46,0)-ROUND(R46*(1+V46),0)*W46) -> -246.67 | Q46: =IF(I46="",(O46-G46-(O46*0.1425%*0.65)-(O46*0.3%)-S46-T46),0) -> 0 | R46: 742 | S46: 10 | U46: =(V46*50%)/(1+50%*V46) -> 0 | W46: 0.11 | X46: =(P46+Q46)/G46 -> -0.025075734 | Y46: =VLOOKUP(C46,每日行情!A:D,4,FALSE) -> 64.95 | Z46: =VLOOKUP(C46,每日行情!A:E,5,FALSE) -> 0.6 | AA46: =IF(I46="",((TODAY()-A46)*G46)/365.24,((I46-A46)*G46)/365.24) -> 4120.7453 | AB46: 台股 ETF
A47: 45967 | C47: 770 | D47: =VLOOKUP(C47,每日行情!A:B,2,FALSE) -> 國泰北美科技 | E47: 173 | F47: 57.55 | G47: 9956 | H47: 1 | I47: 46090 | J47: 50.05 | K47: =E47*J47 -> 8658.65 | L47: 8 | M47: 10 | N47: 0 | O47: =IF(I47="",E47*Y47,0) -> 0 | P47: =IF(I47="",R47-H47,(K47-H47-SUM(L47:N47)+R47-S47-T47)-G47)+(ROUND(R47*V47,0)-ROUND(R47*(1+V47),0)*W47) -> -665.97 | Q47: =IF(I47="",(O47-G47-(O47*0.1425%*0.65)-(O47*0.3%)-S47-T47),0) -> 0 | R47: 742 | S47: 10 | U47: =(V47*50%)/(1+50%*V47) -> 0 | W47: 0.11 | X47: =(P47+Q47)/G47 -> -0.066891322 | Y47: =VLOOKUP(C47,每日行情!A:D,4,FALSE) -> 64.95 | Z47: =VLOOKUP(C47,每日行情!A:E,5,FALSE) -> 0.6 | AA47: =IF(I47="",((TODAY()-A47)*G47)/365.24,((I47-A47)*G47)/365.24) -> 3352.831 | AB47: 台股 ETF
A48: 45999 | C48: 770 | D48: =VLOOKUP(C48,每日行情!A:B,2,FALSE) -> 國泰北美科技 | E48: 170 | F48: 58.65 | G48: 9970 | H48: 1 | I48: 46090 | J48: 50.05 | K48: =E48*J48 -> 8508.5 | L48: 9 | M48: 10 | N48: 0 | O48: =IF(I48="",E48*Y48,0) -> 0 | P48: =IF(I48="",R48-H48,(K48-H48-SUM(L48:N48)+R48-S48-T48)-G48)+(ROUND(R48*V48,0)-ROUND(R48*(1+V48),0)*W48) -> -831.12 | Q48: =IF(I48="",(O48-G48-(O48*0.1425%*0.65)-(O48*0.3%)-S48-T48),0) -> 0 | R48: 742 | S48: 10 | U48: =(V48*50%)/(1+50%*V48) -> 0 | W48: 0.11 | X48: =(P48+Q48)/G48 -> -0.083362086 | Y48: =VLOOKUP(C48,每日行情!A:D,4,FALSE) -> 64.95 | Z48: =VLOOKUP(C48,每日行情!A:E,5,FALSE) -> 0.6 | AA48: =IF(I48="",((TODAY()-A48)*G48)/365.24,((I48-A48)*G48)/365.24) -> 2484.0379 | AB48: 台股 ETF
A49: 46028 | C49: 770 | D49: =VLOOKUP(C49,每日行情!A:B,2,FALSE) -> 國泰北美科技 | E49: 170 | F49: 58.18 | G49: 9890 | H49: 1 | I49: 46090 | J49: 50.05 | K49: =E49*J49 -> 8508.5 | L49: 9 | M49: 10 | N49: 0 | O49: =IF(I49="",E49*Y49,0) -> 0 | P49: =IF(I49="",R49-H49,(K49-H49-SUM(L49:N49)+R49-S49-T49)-G49)+(ROUND(R49*V49,0)-ROUND(R49*(1+V49),0)*W49) -> -751.12 | Q49: =IF(I49="",(O49-G49-(O49*0.1425%*0.65)-(O49*0.3%)-S49-T49),0) -> 0 | R49: 742 | S49: 10 | U49: =(V49*50%)/(1+50%*V49) -> 0 | W49: 0.11 | X49: =(P49+Q49)/G49 -> -0.075947422 | Y49: =VLOOKUP(C49,每日行情!A:D,4,FALSE) -> 64.95 | Z49: =VLOOKUP(C49,每日行情!A:E,5,FALSE) -> 0.6 | AA49: =IF(I49="",((TODAY()-A49)*G49)/365.24,((I49-A49)*G49)/365.24) -> 1678.8413 | AB49: 台股 ETF
A50: 46059 | C50: 770 | D50: =VLOOKUP(C50,每日行情!A:B,2,FALSE) -> 國泰北美科技 | E50: 194 | F50: 50.71 | G50: 9837 | H50: 1 | I50: 46090 | J50: 50.2 | K50: =E50*J50 -> 9738.8 | L50: 3 | M50: 3 | N50: 0 | O50: =IF(I50="",E50*Y50,0) -> 0 | P50: =IF(I50="",R50-H50,(K50-H50-SUM(L50:N50)+R50-S50-T50)-G50)+(ROUND(R50*V50,0)-ROUND(R50*(1+V50),0)*W50) -> -105.2 | Q50: =IF(I50="",(O50-G50-(O50*0.1425%*0.65)-(O50*0.3%)-S50-T50),0) -> 0 | U50: =(V50*50%)/(1+50%*V50) -> 0 | W50: 0.11 | X50: =(P50+Q50)/G50 -> -0.010694317 | Y50: =VLOOKUP(C50,每日行情!A:D,4,FALSE) -> 64.95 | Z50: =VLOOKUP(C50,每日行情!A:E,5,FALSE) -> 0.6 | AA50: =IF(I50="",((TODAY()-A50)*G50)/365.24,((I50-A50)*G50)/365.24) -> 834.92224 | AB50: 台股 ETF
A51: 46051 | C51: 3163 | D51: =VLOOKUP(C51,每日行情!A:B,2,FALSE) -> 波若威 | E51: 1000 | F51: 486 | G51: =E51*F51 -> 486000 | H51: 415 | I51: 46090 | J51: 654 | K51: =E51*J51 -> 654000 | L51: 559 | M51: 1962 | N51: 0 | O51: =IF(I51="",E51*Y51,0) -> 0 | P51: =IF(I51="",R51-H51,(K51-H51-SUM(L51:N51)+R51-S51-T51)-G51)+(ROUND(R51*V51,0)-ROUND(R51*(1+V51),0)*W51) -> 165064 | Q51: =IF(I51="",(O51-G51-(O51*0.1425%*0.65)-(O51*0.3%)-S51-T51),0) -> 0 | U51: =(V51*50%)/(1+50%*V51) -> 0 | W51: 0.11 | X51: =(P51+Q51)/G51 -> 0.33963786 | Y51: =VLOOKUP(C51,每日行情!A:D,4,FALSE) -> 589 | Z51: =VLOOKUP(C51,每日行情!A:E,5,FALSE) -> -15 | AA51: =IF(I51="",((TODAY()-A51)*G51)/365.24,((I51-A51)*G51)/365.24) -> 51894.645 | AB51: 台股
A52: 46051 | C52: 8299 | D52: =VLOOKUP(C52,每日行情!A:B,2,FALSE) -> 群聯 | E52: 50 | F52: 2270 | G52: =E52*F52 -> 113500 | H52: 97 | I52: 46090 | J52: 1600 | K52: =E52*J52 -> 80000 | L52: 81 | M52: 300 | N52: 0 | O52: =IF(I52="",E52*Y52,0) -> 0 | P52: =IF(I52="",R52-H52,(K52-H52-SUM(L52:N52)+R52-S52-T52)-G52)+(ROUND(R52*V52,0)-ROUND(R52*(1+V52),0)*W52) -> -33978 | Q52: =IF(I52="",(O52-G52-(O52*0.1425%*0.65)-(O52*0.3%)-S52-T52),0) -> 0 | U52: =(V52*50%)/(1+50%*V52) -> 0 | W52: 0.11 | X52: =(P52+Q52)/G52 -> -0.29936564 | Y52: =VLOOKUP(C52,每日行情!A:D,4,FALSE) -> 1890 | Z52: =VLOOKUP(C52,每日行情!A:E,5,FALSE) -> 60 | AA52: =IF(I52="",((TODAY()-A52)*G52)/365.24,((I52-A52)*G52)/365.24) -> 12119.428 | AB52: 台股
A53: 46064 | C53: 8299 | D53: =VLOOKUP(C53,每日行情!A:B,2,FALSE) -> 群聯 | E53: 20 | F53: 1860 | G53: =E53*F53 -> 37200 | H53: 31 | I53: 46090 | J53: 1600 | K53: =E53*J53 -> 32000 | L53: 14 | M53: 36 | N53: 0 | O53: =IF(I53="",E53*Y53,0) -> 0 | P53: =IF(I53="",R53-H53,(K53-H53-SUM(L53:N53)+R53-S53-T53)-G53)+(ROUND(R53*V53,0)-ROUND(R53*(1+V53),0)*W53) -> -5281 | Q53: =IF(I53="",(O53-G53-(O53*0.1425%*0.65)-(O53*0.3%)-S53-T53),0) -> 0 | U53: =(V53*50%)/(1+50%*V53) -> 0 | W53: 0.11 | X53: =(P53+Q53)/G53 -> -0.14196237 | Y53: =VLOOKUP(C53,每日行情!A:D,4,FALSE) -> 1890 | Z53: =VLOOKUP(C53,每日行情!A:E,5,FALSE) -> 60 | AA53: =IF(I53="",((TODAY()-A53)*G53)/365.24,((I53-A53)*G53)/365.24) -> 2648.1218 | AB53: 台股
A54: 46126 | C54: 56 | D54: =VLOOKUP(C54,每日行情!A:B,2,FALSE) -> 元大高股息 | E54: 2000 | F54: 39.98 | G54: =E54*F54 -> 79960 | H54: 68 | I54: 46134 | J54: 42.3 | K54: =E54*J54 -> 84600 | L54: 72 | M54: 84 | O54: =IF(I54="",E54*Y54,0) -> 0 | P54: =IF(I54="",R54-H54,(K54-H54-SUM(L54:N54)+R54-S54-T54)-G54)+(ROUND(R54*V54,0)-ROUND(R54*(1+V54),0)*W54) -> 4416 | Q54: =IF(I54="",(O54-G54-(O54*0.1425%*0.65)-(O54*0.3%)-S54-T54),0) -> 0 | U54: =(V54*50%)/(1+50%*V54) -> 0 | W54: 0.11 | X54: =(P54+Q54)/G54 -> 0.055227614 | Y54: =VLOOKUP(C54,每日行情!A:D,4,FALSE) -> 58.75 | Z54: =VLOOKUP(C54,每日行情!A:E,5,FALSE) -> 0.5 | AA54: =IF(I54="",((TODAY()-A54)*G54)/365.24,((I54-A54)*G54)/365.24) -> 1751.3963 | AB54: 台股 ETF
A55: 46126 | C55: 900 | D55: =VLOOKUP(C55,每日行情!A:B,2,FALSE) -> 富邦特選高股息30 | E55: 1000 | F55: 14.72 | G55: =E55*F55 -> 14720 | H55: 20 | I55: 46128 | J55: 15.05 | K55: =E55*J55 -> 15050 | L55: 13 | M55: 15 | O55: =IF(I55="",E55*Y55,0) -> 0 | P55: =IF(I55="",R55-H55,(K55-H55-SUM(L55:N55)+R55-S55-T55)-G55)+(ROUND(R55*V55,0)-ROUND(R55*(1+V55),0)*W55) -> 282 | Q55: =IF(I55="",(O55-G55-(O55*0.1425%*0.65)-(O55*0.3%)-S55-T55),0) -> 0 | U55: =(V55*50%)/(1+50%*V55) -> 0 | W55: 0.11 | X55: =(P55+Q55)/G55 -> 0.019157609 | Y55: =VLOOKUP(C55,每日行情!A:D,4,FALSE) -> 19.9 | Z55: =VLOOKUP(C55,每日行情!A:E,5,FALSE) -> 0.06 | AA55: =IF(I55="",((TODAY()-A55)*G55)/365.24,((I55-A55)*G55)/365.24) -> 80.604534 | AB55: 台股 ETF
A56: 46126 | C56: 900 | D56: =VLOOKUP(C56,每日行情!A:B,2,FALSE) -> 富邦特選高股息30 | E56: 1000 | F56: 14.73 | G56: =E56*F56 -> 14730 | H56: 20 | I56: 46128 | J56: 15.05 | K56: =E56*J56 -> 15050 | L56: 13 | M56: 15 | O56: =IF(I56="",E56*Y56,0) -> 0 | P56: =IF(I56="",R56-H56,(K56-H56-SUM(L56:N56)+R56-S56-T56)-G56)+(ROUND(R56*V56,0)-ROUND(R56*(1+V56),0)*W56) -> 272 | Q56: =IF(I56="",(O56-G56-(O56*0.1425%*0.65)-(O56*0.3%)-S56-T56),0) -> 0 | U56: =(V56*50%)/(1+50%*V56) -> 0 | W56: 0.11 | X56: =(P56+Q56)/G56 -> 0.018465716 | Y56: =VLOOKUP(C56,每日行情!A:D,4,FALSE) -> 19.9 | Z56: =VLOOKUP(C56,每日行情!A:E,5,FALSE) -> 0.06 | AA56: =IF(I56="",((TODAY()-A56)*G56)/365.24,((I56-A56)*G56)/365.24) -> 80.659293 | AB56: 台股 ETF
A57: 46126 | C57: 934 | D57: =VLOOKUP(C57,每日行情!A:B,2,FALSE) -> 中信成長高股息 | E57: 1000 | F57: 22.36 | G57: =E57*F57 -> 22360 | H57: 20 | I57: 46128 | J57: 22.92 | K57: =E57*J57 -> 22920 | L57: 20 | M57: 22 | O57: =IF(I57="",E57*Y57,0) -> 0 | P57: =IF(I57="",R57-H57,(K57-H57-SUM(L57:N57)+R57-S57-T57)-G57)+(ROUND(R57*V57,0)-ROUND(R57*(1+V57),0)*W57) -> 498 | Q57: =IF(I57="",(O57-G57-(O57*0.1425%*0.65)-(O57*0.3%)-S57-T57),0) -> 0 | U57: =(V57*50%)/(1+50%*V57) -> 0 | W57: 0.11 | X57: =(P57+Q57)/G57 -> 0.022271914 | Y57: =VLOOKUP(C57,每日行情!A:D,4,FALSE) -> 30.31 | Z57: =VLOOKUP(C57,每日行情!A:E,5,FALSE) -> 0.3 | AA57: =IF(I57="",((TODAY()-A57)*G57)/365.24,((I57-A57)*G57)/365.24) -> 122.44004 | AB57: 台股 ETF
A58: 46126 | C58: 936 | D58: =VLOOKUP(C58,每日行情!A:B,2,FALSE) -> 台新永續高息中小 | E58: 1000 | F58: 18.04 | G58: =E58*F58 -> 18040 | H58: 20 | I58: 46128 | J58: 18.37 | K58: =E58*J58 -> 18370 | L58: 20 | M58: 18 | O58: =IF(I58="",E58*Y58,0) -> 0 | P58: =IF(I58="",R58-H58,(K58-H58-SUM(L58:N58)+R58-S58-T58)-G58)+(ROUND(R58*V58,0)-ROUND(R58*(1+V58),0)*W58) -> 272 | Q58: =IF(I58="",(O58-G58-(O58*0.1425%*0.65)-(O58*0.3%)-S58-T58),0) -> 0 | U58: =(V58*50%)/(1+50%*V58) -> 0 | W58: 0.11 | X58: =(P58+Q58)/G58 -> 0.015077605 | Y58: =VLOOKUP(C58,每日行情!A:D,4,FALSE) -> 21.52 | Z58: =VLOOKUP(C58,每日行情!A:E,5,FALSE) -> 0.17 | AA58: =IF(I58="",((TODAY()-A58)*G58)/365.24,((I58-A58)*G58)/365.24) -> 98.784361 | AB58: 台股 ETF
A59: 46126 | C59: 944 | D59: =VLOOKUP(C59,每日行情!A:B,2,FALSE) -> 野村趨勢動能高息 | E59: 1000 | F59: 16.4 | G59: =E59*F59 -> 16400 | H59: 20 | I59: 46128 | J59: 16.98 | K59: =E59*J59 -> 16980 | L59: 20 | M59: 16 | O59: =IF(I59="",E59*Y59,0) -> 0 | P59: =IF(I59="",R59-H59,(K59-H59-SUM(L59:N59)+R59-S59-T59)-G59)+(ROUND(R59*V59,0)-ROUND(R59*(1+V59),0)*W59) -> 524 | Q59: =IF(I59="",(O59-G59-(O59*0.1425%*0.65)-(O59*0.3%)-S59-T59),0) -> 0 | U59: =(V59*50%)/(1+50%*V59) -> 0 | W59: 0.11 | X59: =(P59+Q59)/G59 -> 0.03195122 | Y59: =VLOOKUP(C59,每日行情!A:D,4,FALSE) -> 22.65 | Z59: =VLOOKUP(C59,每日行情!A:E,5,FALSE) -> 0.13 | AA59: =IF(I59="",((TODAY()-A59)*G59)/365.24,((I59-A59)*G59)/365.24) -> 89.803965 | AB59: 台股 ETF
A60: 46090 | C60: 2609 | D60: =VLOOKUP(C60,每日行情!A:B,2,FALSE) -> 陽明 | E60: 1000 | F60: 61.09 | G60: =E60*F60 -> 61090 | H60: 52 | I60: 46153 | J60: 50.3 | K60: =E60*J60 -> 50300 | L60: 43 | M60: 150 | O60: =IF(I60="",E60*Y60,0) -> 0 | P60: =IF(I60="",R60-H60,(K60-H60-SUM(L60:N60)+R60-S60-T60)-G60)+(ROUND(R60*V60,0)-ROUND(R60*(1+V60),0)*W60) -> -11035 | Q60: =IF(I60="",(O60-G60-(O60*0.1425%*0.65)-(O60*0.3%)-S60-T60),0) -> 0 | U60: =(V60*50%)/(1+50%*V60) -> 0 | W60: 0.11 | X60: =(P60+Q60)/G60 -> -0.18063513 | Y60: =VLOOKUP(C60,每日行情!A:D,4,FALSE) -> 64.7 | Z60: =VLOOKUP(C60,每日行情!A:E,5,FALSE) -> 1.4 | AA60: =IF(I60="",((TODAY()-A60)*G60)/365.24,((I60-A60)*G60)/365.24) -> 10537.373 | AB60: 台股
A61: 46149 | C61: 4938 | D61: =VLOOKUP(C61,每日行情!A:B,2,FALSE) -> 和碩 | E61: 1000 | F61: 83.9 | G61: =E61*F61 -> 83900 | H61: 71 | I61: 46156 | J61: 76.7 | K61: =E61*J61 -> 76700 | L61: 65 | M61: =ROUND(J61*E61*0.3%,0) -> 230 | O61: =IF(I61="",E61*Y61,0) -> 0 | P61: =IF(I61="",R61-H61,(K61-H61-SUM(L61:N61)+R61-S61-T61)-G61)+(ROUND(R61*V61,0)-ROUND(R61*(1+V61),0)*W61) -> -7566 | Q61: =IF(I61="",(O61-G61-(O61*0.1425%*0.65)-(O61*0.3%)-S61-T61),0) -> 0 | U61: =(V61*50%)/(1+50%*V61) -> 0 | W61: 0.11 | X61: =(P61+Q61)/G61 -> -0.090178784 | Y61: =VLOOKUP(C61,每日行情!A:D,4,FALSE) -> 102 | Z61: =VLOOKUP(C61,每日行情!A:E,5,FALSE) -> 3.9 | AA61: =IF(I61="",((TODAY()-A61)*G61)/365.24,((I61-A61)*G61)/365.24) -> 1607.9838 | AB61: 台股
A62: 46157 | C62: 944 | D62: =VLOOKUP(C62,每日行情!A:B,2,FALSE) -> 野村趨勢動能高息 | E62: 1000 | F62: 18.83 | G62: =E62*F62 -> 18830 | H62: 20 | I62: 46169 | J62: 19.57 | K62: =E62*J62 -> 19570 | L62: 20 | M62: 19 | O62: =IF(I62="",E62*Y62,0) -> 0 | P62: =IF(I62="",R62-H62,(K62-H62-SUM(L62:N62)+R62-S62-T62)-G62)+(ROUND(R62*V62,0)-ROUND(R62*(1+V62),0)*W62) -> 1268.4 | Q62: =IF(I62="",(O62-G62-(O62*0.1425%*0.65)-(O62*0.3%)-S62-T62),0) -> 0 | R62: 660 | U62: =(V62*50%)/(1+50%*V62) -> 0 | W62: 0.11 | X62: =(P62+Q62)/G62 -> 0.067360595 | Y62: =VLOOKUP(C62,每日行情!A:D,4,FALSE) -> 22.65 | Z62: =VLOOKUP(C62,每日行情!A:E,5,FALSE) -> 0.13 | AA62: =IF(I62="",((TODAY()-A62)*G62)/365.24,((I62-A62)*G62)/365.24) -> 618.6617 | AB62: 台股 ETF
A63: 46157 | C63: 934 | D63: =VLOOKUP(C63,每日行情!A:B,2,FALSE) -> 中信成長高股息 | E63: 1000 | F63: 25.39 | G63: =E63*F63 -> 25390 | H63: 21 | I63: 46169 | J63: 26.92 | K63: =E63*J63 -> 26920 | L63: 23 | M63: 26 | O63: =IF(I63="",E63*Y63,0) -> 0 | P63: =IF(I63="",R63-H63,(K63-H63-SUM(L63:N63)+R63-S63-T63)-G63)+(ROUND(R63*V63,0)-ROUND(R63*(1+V63),0)*W63) -> 1682.5 | Q63: =IF(I63="",(O63-G63-(O63*0.1425%*0.65)-(O63*0.3%)-S63-T63),0) -> 0 | R63: 250 | U63: =(V63*50%)/(1+50%*V63) -> 0 | W63: 0.11 | X63: =(P63+Q63)/G63 -> 0.066266247 | Y63: =VLOOKUP(C63,每日行情!A:D,4,FALSE) -> 30.31 | Z63: =VLOOKUP(C63,每日行情!A:E,5,FALSE) -> 0.3 | AA63: =IF(I63="",((TODAY()-A63)*G63)/365.24,((I63-A63)*G63)/365.24) -> 834.19122 | AB63: 台股 ETF
A64: 46157 | C64: 878 | D64: =VLOOKUP(C64,每日行情!A:B,2,FALSE) -> 國泰永續高股息 | E64: 1000 | F64: 28.2 | G64: =E64*F64 -> 28200 | H64: 24 | I64: 46169 | J64: 29.7 | K64: =E64*J64 -> 29700 | L64: 25 | M64: 29 | O64: =IF(I64="",E64*Y64,0) -> 0 | P64: =IF(I64="",R64-H64,(K64-H64-SUM(L64:N64)+R64-S64-T64)-G64)+(ROUND(R64*V64,0)-ROUND(R64*(1+V64),0)*W64) -> 1470.06 | Q64: =IF(I64="",(O64-G64-(O64*0.1425%*0.65)-(O64*0.3%)-S64-T64),0) -> 0 | R64: 54 | U64: =(V64*50%)/(1+50%*V64) -> 0 | W64: 0.11 | X64: =(P64+Q64)/G64 -> 0.052129787 | Y64: =VLOOKUP(C64,每日行情!A:D,4,FALSE) -> 35.53 | Z64: =VLOOKUP(C64,每日行情!A:E,5,FALSE) -> 0.44 | AA64: =IF(I64="",((TODAY()-A64)*G64)/365.24,((I64-A64)*G64)/365.24) -> 926.51407 | AB64: 台股 ETF
A65: 46170 | C65: 00631L | D65: =VLOOKUP(C65,每日行情!A:B,2,FALSE) -> 元大台灣50正2 | E65: 1000 | F65: 34.36 | G65: =E65*F65 -> 34360 | H65: 29 | I65: 46189 | J65: 37.6 | K65: =E65*J65 -> 37600 | L65: 32 | M65: 37 | O65: =IF(I65="",E65*Y65,0) -> 0 | P65: =IF(I65="",R65-H65,(K65-H65-SUM(L65:N65)+R65-S65-T65)-G65)+(ROUND(R65*V65,0)-ROUND(R65*(1+V65),0)*W65) -> 3142 | Q65: =IF(I65="",(O65-G65-(O65*0.1425%*0.65)-(O65*0.3%)-S65-T65),0) -> 0 | U65: =(V65*50%)/(1+50%*V65) -> 0 | W65: 0.11 | X65: =(P65+Q65)/G65 -> 0.091443539 | Y65: =VLOOKUP(C65,每日行情!A:D,4,FALSE) -> 37.15 | Z65: =VLOOKUP(C65,每日行情!A:E,5,FALSE) -> 0.01 | AA65: =IF(I65="",((TODAY()-A65)*G65)/365.24,((I65-A65)*G65)/365.24) -> 1787.4274 | AB65: 台股 ETF
A69: 45614 | C69: 895 | D69: =VLOOKUP(C69,每日行情!A:B,2,FALSE) -> 富邦未來車 | E69: 160 | F69: 31.12 | G69: =E69*F69 -> 4979.2 | H69: 1 | K69: =E69*J69 -> 0 | L69: =ROUND(J69*E69*0.1425%,0) -> 0 | M69: =ROUND(J69*E69*0.3%,0) -> 0 | O69: =IF(I69="",E69*Y69,0) -> 8128 | P69: =IF(I69="",R69-H69,(K69-H69-SUM(L69:N69)+R69-S69-T69)-G69)+(ROUND(R69*V69,0)-ROUND(R69*(1+V69),0)*W69) -> -1 | Q69: =IF(I69="",(O69-G69-(O69*0.1425%*0.65)-(O69*0.3%)-S69-T69),0) -> 3116.8874 | U69: =(V69*50%)/(1+50%*V69) -> 0 | W69: 0.11 | X69: =(P69+Q69)/G69 -> 0.62578074 | Y69: =VLOOKUP(C69,每日行情!A:D,4,FALSE) -> 50.8 | Z69: =VLOOKUP(C69,每日行情!A:E,5,FALSE) -> 0.35 | AA69: =IF(I69="",((TODAY()-A69)*G69)/365.24,((I69-A69)*G69)/365.24) -> 9501.9779 | AB69: 台股 ETF
A70: 45642 | C70: 895 | D70: =VLOOKUP(C70,每日行情!A:B,2,FALSE) -> 富邦未來車 | E70: 154 | F70: 32.37 | G70: 4984 | H70: 1 | K70: =E70*J70 -> 0 | L70: =ROUND(J70*E70*0.1425%,0) -> 0 | M70: =ROUND(J70*E70*0.3%,0) -> 0 | O70: =IF(I70="",E70*Y70,0) -> 7823.2 | P70: =IF(I70="",R70-H70,(K70-H70-SUM(L70:N70)+R70-S70-T70)-G70)+(ROUND(R70*V70,0)-ROUND(R70*(1+V70),0)*W70) -> -1 | Q70: =IF(I70="",(O70-G70-(O70*0.1425%*0.65)-(O70*0.3%)-S70-T70),0) -> 2808.4842 | U70: =(V70*50%)/(1+50%*V70) -> 0 | W70: 0.11 | X70: =(P70+Q70)/G70 -> 0.56329939 | Y70: =VLOOKUP(C70,每日行情!A:D,4,FALSE) -> 50.8 | Z70: =VLOOKUP(C70,每日行情!A:E,5,FALSE) -> 0.35 | AA70: =IF(I70="",((TODAY()-A70)*G70)/365.24,((I70-A70)*G70)/365.24) -> 9129.0549 | AB70: 台股 ETF
A71: 45673 | C71: 895 | D71: =VLOOKUP(C71,每日行情!A:B,2,FALSE) -> 富邦未來車 | E71: 155 | F71: 32.2 | G71: 4991 | H71: 1 | K71: =E71*J71 -> 0 | L71: =ROUND(J71*E71*0.1425%,0) -> 0 | M71: =ROUND(J71*E71*0.3%,0) -> 0 | O71: =IF(I71="",E71*Y71,0) -> 7874 | P71: =IF(I71="",R71-H71,(K71-H71-SUM(L71:N71)+R71-S71-T71)-G71)+(ROUND(R71*V71,0)-ROUND(R71*(1+V71),0)*W71) -> -1 | Q71: =IF(I71="",(O71-G71-(O71*0.1425%*0.65)-(O71*0.3%)-S71-T71),0) -> 2852.0847 | U71: =(V71*50%)/(1+50%*V71) -> 0 | W71: 0.11 | X71: =(P71+Q71)/G71 -> 0.57124518 | Y71: =VLOOKUP(C71,每日行情!A:D,4,FALSE) -> 50.8 | Z71: =VLOOKUP(C71,每日行情!A:E,5,FALSE) -> 0.35 | AA71: =IF(I71="",((TODAY()-A71)*G71)/365.24,((I71-A71)*G71)/365.24) -> 8718.262 | AB71: 台股 ETF
A72: 45705 | C72: 895 | D72: =VLOOKUP(C72,每日行情!A:B,2,FALSE) -> 富邦未來車 | E72: 157 | F72: 31.68 | G72: 4973 | H72: 1 | K72: =E72*J72 -> 0 | L72: =ROUND(J72*E72*0.1425%,0) -> 0 | M72: =ROUND(J72*E72*0.3%,0) -> 0 | O72: =IF(I72="",E72*Y72,0) -> 7975.6 | P72: =IF(I72="",R72-H72,(K72-H72-SUM(L72:N72)+R72-S72-T72)-G72)+(ROUND(R72*V72,0)-ROUND(R72*(1+V72),0)*W72) -> -1 | Q72: =IF(I72="",(O72-G72-(O72*0.1425%*0.65)-(O72*0.3%)-S72-T72),0) -> 2971.2858 | U72: =(V72*50%)/(1+50%*V72) -> 0 | W72: 0.11 | X72: =(P72+Q72)/G72 -> 0.59728249 | Y72: =VLOOKUP(C72,每日行情!A:D,4,FALSE) -> 50.8 | Z72: =VLOOKUP(C72,每日行情!A:E,5,FALSE) -> 0.35 | AA72: =IF(I72="",((TODAY()-A72)*G72)/365.24,((I72-A72)*G72)/365.24) -> 8251.1171 | AB72: 台股 ETF
A73: 45733 | C73: 895 | D73: =VLOOKUP(C73,每日行情!A:B,2,FALSE) -> 富邦未來車 | E73: 176 | F73: 28.3 | G73: 4980 | H73: 1 | K73: =E73*J73 -> 0 | L73: =ROUND(J73*E73*0.1425%,0) -> 0 | M73: =ROUND(J73*E73*0.3%,0) -> 0 | O73: =IF(I73="",E73*Y73,0) -> 8940.8 | P73: =IF(I73="",R73-H73,(K73-H73-SUM(L73:N73)+R73-S73-T73)-G73)+(ROUND(R73*V73,0)-ROUND(R73*(1+V73),0)*W73) -> -1 | Q73: =IF(I73="",(O73-G73-(O73*0.1425%*0.65)-(O73*0.3%)-S73-T73),0) -> 3925.6962 | U73: =(V73*50%)/(1+50%*V73) -> 0 | W73: 0.11 | X73: =(P73+Q73)/G73 -> 0.7880916 | Y73: =VLOOKUP(C73,每日行情!A:D,4,FALSE) -> 50.8 | Z73: =VLOOKUP(C73,每日行情!A:E,5,FALSE) -> 0.35 | AA73: =IF(I73="",((TODAY()-A73)*G73)/365.24,((I73-A73)*G73)/365.24) -> 7880.955 | AB73: 台股 ETF
A74: 45763 | C74: 895 | D74: =VLOOKUP(C74,每日行情!A:B,2,FALSE) -> 富邦未來車 | E74: 193 | F74: 25.84 | G74: 4987 | H74: 1 | K74: =E74*J74 -> 0 | L74: =ROUND(J74*E74*0.1425%,0) -> 0 | M74: =ROUND(J74*E74*0.3%,0) -> 0 | O74: =IF(I74="",E74*Y74,0) -> 9804.4 | P74: =IF(I74="",R74-H74,(K74-H74-SUM(L74:N74)+R74-S74-T74)-G74)+(ROUND(R74*V74,0)-ROUND(R74*(1+V74),0)*W74) -> -1 | Q74: =IF(I74="",(O74-G74-(O74*0.1425%*0.65)-(O74*0.3%)-S74-T74),0) -> 4778.9055 | U74: =(V74*50%)/(1+50%*V74) -> 0 | W74: 0.11 | X74: =(P74+Q74)/G74 -> 0.95807208 | Y74: =VLOOKUP(C74,每日行情!A:D,4,FALSE) -> 50.8 | Z74: =VLOOKUP(C74,每日行情!A:E,5,FALSE) -> 0.35 | AA74: =IF(I74="",((TODAY()-A74)*G74)/365.24,((I74-A74)*G74)/365.24) -> 7482.4116 | AB74: 台股 ETF
A75: 45793 | C75: 895 | D75: =VLOOKUP(C75,每日行情!A:B,2,FALSE) -> 富邦未來車 | E75: 171 | F75: 29.12 | G75: 4979 | H75: 1 | K75: =E75*J75 -> 0 | L75: =ROUND(J75*E75*0.1425%,0) -> 0 | M75: =ROUND(J75*E75*0.3%,0) -> 0 | O75: =IF(I75="",E75*Y75,0) -> 8686.8 | P75: =IF(I75="",R75-H75,(K75-H75-SUM(L75:N75)+R75-S75-T75)-G75)+(ROUND(R75*V75,0)-ROUND(R75*(1+V75),0)*W75) -> -1 | Q75: =IF(I75="",(O75-G75-(O75*0.1425%*0.65)-(O75*0.3%)-S75-T75),0) -> 3673.6935 | U75: =(V75*50%)/(1+50%*V75) -> 0 | W75: 0.11 | X75: =(P75+Q75)/G75 -> 0.73763676 | Y75: =VLOOKUP(C75,每日行情!A:D,4,FALSE) -> 50.8 | Z75: =VLOOKUP(C75,每日行情!A:E,5,FALSE) -> 0.35 | AA75: =IF(I75="",((TODAY()-A75)*G75)/365.24,((I75-A75)*G75)/365.24) -> 7061.4445 | AB75: 台股 ETF
A76: 45824 | C76: 895 | D76: =VLOOKUP(C76,每日行情!A:B,2,FALSE) -> 富邦未來車 | E76: 172 | F76: 29 | G76: 4988 | H76: 1 | K76: =E76*J76 -> 0 | L76: =ROUND(J76*E76*0.1425%,0) -> 0 | M76: =ROUND(J76*E76*0.3%,0) -> 0 | O76: =IF(I76="",E76*Y76,0) -> 8737.6 | P76: =IF(I76="",R76-H76,(K76-H76-SUM(L76:N76)+R76-S76-T76)-G76)+(ROUND(R76*V76,0)-ROUND(R76*(1+V76),0)*W76) -> -1 | Q76: =IF(I76="",(O76-G76-(O76*0.1425%*0.65)-(O76*0.3%)-S76-T76),0) -> 3715.294 | U76: =(V76*50%)/(1+50%*V76) -> 0 | W76: 0.11 | X76: =(P76+Q76)/G76 -> 0.74464595 | Y76: =VLOOKUP(C76,每日行情!A:D,4,FALSE) -> 50.8 | Z76: =VLOOKUP(C76,每日行情!A:E,5,FALSE) -> 0.35 | AA76: =IF(I76="",((TODAY()-A76)*G76)/365.24,((I76-A76)*G76)/365.24) -> 6650.8488 | AB76: 台股 ETF
A77: 45854 | C77: 895 | D77: =VLOOKUP(C77,每日行情!A:B,2,FALSE) -> 富邦未來車 | E77: 160 | F77: 31.14 | G77: 4982 | H77: 1 | K77: =E77*J77 -> 0 | L77: =ROUND(J77*E77*0.1425%,0) -> 0 | M77: =ROUND(J77*E77*0.3%,0) -> 0 | O77: =IF(I77="",E77*Y77,0) -> 8128 | P77: =IF(I77="",R77-H77,(K77-H77-SUM(L77:N77)+R77-S77-T77)-G77)+(ROUND(R77*V77,0)-ROUND(R77*(1+V77),0)*W77) -> -1 | Q77: =IF(I77="",(O77-G77-(O77*0.1425%*0.65)-(O77*0.3%)-S77-T77),0) -> 3114.0874 | U77: =(V77*50%)/(1+50%*V77) -> 0 | W77: 0.11 | X77: =(P77+Q77)/G77 -> 0.62486701 | Y77: =VLOOKUP(C77,每日行情!A:D,4,FALSE) -> 50.8 | Z77: =VLOOKUP(C77,每日行情!A:E,5,FALSE) -> 0.35 | AA77: =IF(I77="",((TODAY()-A77)*G77)/365.24,((I77-A77)*G77)/365.24) -> 6233.6382 | AB77: 台股 ETF
A78: 45887 | C78: 895 | D78: =VLOOKUP(C78,每日行情!A:B,2,FALSE) -> 富邦未來車 | E78: 150 | F78: 33.15 | G78: 4972 | H78: 1 | K78: =E78*J78 -> 0 | L78: =ROUND(J78*E78*0.1425%,0) -> 0 | M78: =ROUND(J78*E78*0.3%,0) -> 0 | O78: =IF(I78="",E78*Y78,0) -> 7620 | P78: =IF(I78="",R78-H78,(K78-H78-SUM(L78:N78)+R78-S78-T78)-G78)+(ROUND(R78*V78,0)-ROUND(R78*(1+V78),0)*W78) -> -1 | Q78: =IF(I78="",(O78-G78-(O78*0.1425%*0.65)-(O78*0.3%)-S78-T78),0) -> 2618.082 | U78: =(V78*50%)/(1+50%*V78) -> 0 | W78: 0.11 | X78: =(P78+Q78)/G78 -> 0.52636403 | Y78: =VLOOKUP(C78,每日行情!A:D,4,FALSE) -> 50.8 | Z78: =VLOOKUP(C78,每日行情!A:E,5,FALSE) -> 0.35 | AA78: =IF(I78="",((TODAY()-A78)*G78)/365.24,((I78-A78)*G78)/365.24) -> 5771.8979 | AB78: 台股 ETF
A79: 45916 | C79: 895 | D79: =VLOOKUP(C79,每日行情!A:B,2,FALSE) -> 富邦未來車 | E79: 144 | F79: 34.64 | G79: 4988 | H79: 1 | K79: =E79*J79 -> 0 | L79: =ROUND(J79*E79*0.1425%,0) -> 0 | M79: =ROUND(J79*E79*0.3%,0) -> 0 | O79: =IF(I79="",E79*Y79,0) -> 7315.2 | P79: =IF(I79="",R79-H79,(K79-H79-SUM(L79:N79)+R79-S79-T79)-G79)+(ROUND(R79*V79,0)-ROUND(R79*(1+V79),0)*W79) -> -1 | Q79: =IF(I79="",(O79-G79-(O79*0.1425%*0.65)-(O79*0.3%)-S79-T79),0) -> 2298.4787 | U79: =(V79*50%)/(1+50%*V79) -> 0 | W79: 0.11 | X79: =(P79+Q79)/G79 -> 0.46060118 | Y79: =VLOOKUP(C79,每日行情!A:D,4,FALSE) -> 50.8 | Z79: =VLOOKUP(C79,每日行情!A:E,5,FALSE) -> 0.35 | AA79: =IF(I79="",((TODAY()-A79)*G79)/365.24,((I79-A79)*G79)/365.24) -> 5394.4256 | AB79: 台股 ETF
A80: 45946 | C80: 895 | D80: =VLOOKUP(C80,每日行情!A:B,2,FALSE) -> 富邦未來車 | E80: 133 | F80: 37.43 | G80: 4978 | H80: 1 | K80: =E80*J80 -> 0 | L80: =ROUND(J80*E80*0.1425%,0) -> 0 | M80: =ROUND(J80*E80*0.3%,0) -> 0 | O80: =IF(I80="",E80*Y80,0) -> 6756.4 | P80: =IF(I80="",R80-H80,(K80-H80-SUM(L80:N80)+R80-S80-T80)-G80)+(ROUND(R80*V80,0)-ROUND(R80*(1+V80),0)*W80) -> -1 | Q80: =IF(I80="",(O80-G80-(O80*0.1425%*0.65)-(O80*0.3%)-S80-T80),0) -> 1751.8727 | U80: =(V80*50%)/(1+50%*V80) -> 0 | W80: 0.11 | X80: =(P80+Q80)/G80 -> 0.35172211 | Y80: =VLOOKUP(C80,每日行情!A:D,4,FALSE) -> 50.8 | Z80: =VLOOKUP(C80,每日行情!A:E,5,FALSE) -> 0.35 | AA80: =IF(I80="",((TODAY()-A80)*G80)/365.24,((I80-A80)*G80)/365.24) -> 4974.7289 | AB80: 台股 ETF
A81: 45978 | C81: 895 | D81: =VLOOKUP(C81,每日行情!A:B,2,FALSE) -> 富邦未來車 | E81: 131 | F81: 38.04 | G81: 4983 | H81: 1 | K81: =E81*J81 -> 0 | L81: =ROUND(J81*E81*0.1425%,0) -> 0 | M81: =ROUND(J81*E81*0.3%,0) -> 0 | O81: =IF(I81="",E81*Y81,0) -> 6654.8 | P81: =IF(I81="",R81-H81,(K81-H81-SUM(L81:N81)+R81-S81-T81)-G81)+(ROUND(R81*V81,0)-ROUND(R81*(1+V81),0)*W81) -> -1 | Q81: =IF(I81="",(O81-G81-(O81*0.1425%*0.65)-(O81*0.3%)-S81-T81),0) -> 1645.6716 | U81: =(V81*50%)/(1+50%*V81) -> 0 | W81: 0.11 | X81: =(P81+Q81)/G81 -> 0.33005651 | Y81: =VLOOKUP(C81,每日行情!A:D,4,FALSE) -> 50.8 | Z81: =VLOOKUP(C81,每日行情!A:E,5,FALSE) -> 0.35 | AA81: =IF(I81="",((TODAY()-A81)*G81)/365.24,((I81-A81)*G81)/365.24) -> 4543.147 | AB81: 台股 ETF
... A86: 46160 | C86: 895 | D86: =VLOOKUP(C86,每日行情!A:B,2,FALSE) -> 富邦未來車 | E86: 101 | F86: 49.19 | G86: 4968 | H86: 1 | K86: =E86*J86 -> 0 | L86: =ROUND(J86*E86*0.1425%,0) -> 0 | M86: =ROUND(J86*E86*0.3%,0) -> 0 | O86: =IF(I86="",E86*Y86,0) -> 5130.8 | P86: =IF(I86="",R86-H86,(K86-H86-SUM(L86:N86)+R86-S86-T86)-G86)+(ROUND(R86*V86,0)-ROUND(R86*(1+V86),0)*W86) -> -1 | Q86: =IF(I86="",(O86-G86-(O86*0.1425%*0.65)-(O86*0.3%)-S86-T86),0) -> 142.6552 | U86: =(V86*50%)/(1+50%*V86) -> 0 | W86: 0.11 | X86: =(P86+Q86)/G86 -> 0.028513526 | Y86: =VLOOKUP(C86,每日行情!A:D,4,FALSE) -> 50.8 | Z86: =VLOOKUP(C86,每日行情!A:E,5,FALSE) -> 0.35 | AA86: =IF(I86="",((TODAY()-A86)*G86)/365.24,((I86-A86)*G86)/365.24) -> 2053.9043 | AB86: 台股 ETF
A87: 46090 | C87: 00991A | D87: =VLOOKUP(C87,每日行情!A:B,2,FALSE) -> 主動復華未來50 | E87: 876 | F87: 11.12 | G87: 9741 | H87: 1 | K87: =E87*J87 -> 0 | L87: =ROUND(J87*E87*0.1425%,0) -> 0 | M87: =ROUND(J87*E87*0.3%,0) -> 0 | O87: =IF(I87="",E87*Y87,0) -> 15198.6 | P87: =IF(I87="",R87-H87,(K87-H87-SUM(L87:N87)+R87-S87-T87)-G87)+(ROUND(R87*V87,0)-ROUND(R87*(1+V87),0)*W87) -> -1 | Q87: =IF(I87="",(O87-G87-(O87*0.1425%*0.65)-(O87*0.3%)-S87-T87),0) -> 5397.9265 | U87: =(V87*50%)/(1+50%*V87) -> 0 | W87: 0.11 | X87: =(P87+Q87)/G87 -> 0.55404235 | Y87: =VLOOKUP(C87,每日行情!A:D,4,FALSE) -> 17.35 | Z87: =VLOOKUP(C87,每日行情!A:E,5,FALSE) -> 0.18 | AA87: =IF(I87="",((TODAY()-A87)*G87)/365.24,((I87-A87)*G87)/365.24) -> 5894.0998 | AB87: 台股 ETF
A88: 46120 | C88: 00991A | D88: =VLOOKUP(C88,每日行情!A:B,2,FALSE) -> 主動復華未來50 | E88: 740 | F88: 13.5 | G88: 9858 | H88: 1 | K88: =E88*J88 -> 0 | L88: =ROUND(J88*E88*0.1425%,0) -> 0 | M88: =ROUND(J88*E88*0.3%,0) -> 0 | O88: =IF(I88="",E88*Y88,0) -> 12839 | P88: =IF(I88="",R88-H88,(K88-H88-SUM(L88:N88)+R88-S88-T88)-G88)+(ROUND(R88*V88,0)-ROUND(R88*(1+V88),0)*W88) -> -1 | Q88: =IF(I88="",(O88-G88-(O88*0.1425%*0.65)-(O88*0.3%)-S88-T88),0) -> 2930.5909 | U88: =(V88*50%)/(1+50%*V88) -> 0 | W88: 0.11 | X88: =(P88+Q88)/G88 -> 0.29717903 | Y88: =VLOOKUP(C88,每日行情!A:D,4,FALSE) -> 17.35 | Z88: =VLOOKUP(C88,每日行情!A:E,5,FALSE) -> 0.18 | AA88: =IF(I88="",((TODAY()-A88)*G88)/365.24,((I88-A88)*G88)/365.24) -> 5155.1802 | AB88: 台股 ETF
A89: 46097 | C89: 895 | D89: =VLOOKUP(C89,每日行情!A:B,2,FALSE) -> 富邦未來車 | E89: 125 | F89: 40 | G89: 5000 | H89: 1 | K89: =E89*J89 -> 0 | L89: =ROUND(J89*E89*0.1425%,0) -> 0 | M89: =ROUND(J89*E89*0.3%,0) -> 0 | O89: =IF(I89="",E89*Y89,0) -> 6350 | P89: =IF(I89="",R89-H89,(K89-H89-SUM(L89:N89)+R89-S89-T89)-G89)+(ROUND(R89*V89,0)-ROUND(R89*(1+V89),0)*W89) -> -1 | Q89: =IF(I89="",(O89-G89-(O89*0.1425%*0.65)-(O89*0.3%)-S89-T89),0) -> 1325.0683 | U89: =(V89*50%)/(1+50%*V89) -> 0 | W89: 0.11 | X89: =(P89+Q89)/G89 -> 0.26481366 | Y89: =VLOOKUP(C89,每日行情!A:D,4,FALSE) -> 50.8 | Z89: =VLOOKUP(C89,每日行情!A:E,5,FALSE) -> 0.35 | AA89: =IF(I89="",((TODAY()-A89)*G89)/365.24,((I89-A89)*G89)/365.24) -> 2929.5805 | AB89: 台股 ETF
A90: 46132 | C90: 2330 | D90: =VLOOKUP(C90,每日行情!A:B,2,FALSE) -> 台積電 | E90: 100 | F90: 2050 | G90: =E90*F90 -> 205000 | H90: 175 | K90: =E90*J90 -> 0 | L90: =ROUND(J90*E90*0.1425%,0) -> 0 | M90: =ROUND(J90*E90*0.3%,0) -> 0 | O90: =IF(I90="",E90*Y90,0) -> 242000 | P90: =IF(I90="",R90-H90,(K90-H90-SUM(L90:N90)+R90-S90-T90)-G90)+(ROUND(R90*V90,0)-ROUND(R90*(1+V90),0)*W90) -> -175 | Q90: =IF(I90="",(O90-G90-(O90*0.1425%*0.65)-(O90*0.3%)-S90-T90),0) -> 36049.848 | U90: =(V90*50%)/(1+50%*V90) -> 0 | W90: 0.11 | X90: =(P90+Q90)/G90 -> 0.17499926 | Y90: =VLOOKUP(C90,每日行情!A:D,4,FALSE) -> 2420 | Z90: =VLOOKUP(C90,每日行情!A:E,5,FALSE) -> -20 | AA90: =IF(I90="",((TODAY()-A90)*G90)/365.24,((I90-A90)*G90)/365.24) -> 100468.19 | AB90: 台股
A91: 46146 | C91: 00981A | D91: =VLOOKUP(C91,每日行情!A:B,2,FALSE) -> 主動統一台股增長 | E91: 2000 | F91: 29.4 | G91: =E91*F91 -> 58800 | H91: 50 | K91: =E91*J91 -> 0 | L91: =ROUND(J91*E91*0.1425%,0) -> 0 | M91: =ROUND(J91*E91*0.3%,0) -> 0 | O91: =IF(I91="",E91*Y91,0) -> 59060 | P91: =IF(I91="",R91-H91,(K91-H91-SUM(L91:N91)+R91-S91-T91)-G91)+(ROUND(R91*V91,0)-ROUND(R91*(1+V91),0)*W91) -> -50 | Q91: =IF(I91="",(O91-G91-(O91*0.1425%*0.65)-(O91*0.3%)-S91-T91),0) -> 28.115675 | U91: =(V91*50%)/(1+50%*V91) -> 0 | W91: 0.11 | X91: =(P91+Q91)/G91 -> -0.0003721824 | Y91: =VLOOKUP(C91,每日行情!A:D,4,FALSE) -> 29.53 | Z91: =VLOOKUP(C91,每日行情!A:E,5,FALSE) -> 0.13 | AA91: =IF(I91="",((TODAY()-A91)*G91)/365.24,((I91-A91)*G91)/365.24) -> 26563.356 | AB91: 台股 ETF
A92: 46148 | C92: 6525 | D92: =VLOOKUP(C92,每日行情!A:B,2,FALSE) -> 捷敏-KY | E92: 1000 | F92: 103.5 | G92: =E92*F92 -> 103500 | H92: 88 | K92: =E92*J92 -> 0 | L92: =ROUND(J92*E92*0.1425%,0) -> 0 | M92: =ROUND(J92*E92*0.3%,0) -> 0 | O92: =IF(I92="",E92*Y92,0) -> 128500 | P92: =IF(I92="",R92-H92,(K92-H92-SUM(L92:N92)+R92-S92-T92)-G92)+(ROUND(R92*V92,0)-ROUND(R92*(1+V92),0)*W92) -> -88 | Q92: =IF(I92="",(O92-G92-(O92*0.1425%*0.65)-(O92*0.3%)-S92-T92),0) -> 24495.477 | U92: =(V92*50%)/(1+50%*V92) -> 0 | W92: 0.11 | X92: =(P92+Q92)/G92 -> 0.23582103 | Y92: =VLOOKUP(C92,每日行情!A:D,4,FALSE) -> 128.5 | Z92: =VLOOKUP(C92,每日行情!A:E,5,FALSE) -> 0 | AA92: =IF(I92="",((TODAY()-A92)*G92)/365.24,((I92-A92)*G92)/365.24) -> 46190.176 | AB92: 台股
A93: 46150 | C93: 00991A | D93: =VLOOKUP(C93,每日行情!A:B,2,FALSE) -> 主動復華未來50 | E93: 563 | F93: 17.51 | G93: 9858 | H93: 1 | K93: =E93*J93 -> 0 | L93: =ROUND(J93*E93*0.1425%,0) -> 0 | M93: =ROUND(J93*E93*0.3%,0) -> 0 | O93: =IF(I93="",E93*Y93,0) -> 9768.05 | P93: =IF(I93="",R93-H93,(K93-H93-SUM(L93:N93)+R93-S93-T93)-G93)+(ROUND(R93*V93,0)-ROUND(R93*(1+V93),0)*W93) -> -1 | Q93: =IF(I93="",(O93-G93-(O93*0.1425%*0.65)-(O93*0.3%)-S93-T93),0) -> -128.30181 | U93: =(V93*50%)/(1+50%*V93) -> 0 | W93: 0.11 | X93: =(P93+Q93)/G93 -> -0.013116434 | Y93: =VLOOKUP(C93,每日行情!A:D,4,FALSE) -> 17.35 | Z93: =VLOOKUP(C93,每日行情!A:E,5,FALSE) -> 0.18 | AA93: =IF(I93="",((TODAY()-A93)*G93)/365.24,((I93-A93)*G93)/365.24) -> 4345.466 | AB93: 台股 ETF
A94: 46150 | C94: 3430 | D94: =VLOOKUP(C94,每日行情!A:B,2,FALSE) -> 奇鈦科 | E94: 1000 | F94: 148 | G94: =E94*F94 -> 148000 | H94: 126 | K94: =E94*J94 -> 0 | L94: =ROUND(J94*E94*0.1425%,0) -> 0 | M94: =ROUND(J94*E94*0.3%,0) -> 0 | O94: =IF(I94="",E94*Y94,0) -> 92000 | P94: =IF(I94="",R94-H94,(K94-H94-SUM(L94:N94)+R94-S94-T94)-G94)+(ROUND(R94*V94,0)-ROUND(R94*(1+V94),0)*W94) -> -126 | Q94: =IF(I94="",(O94-G94-(O94*0.1425%*0.65)-(O94*0.3%)-S94-T94),0) -> -56361.215 | U94: =(V94*50%)/(1+50%*V94) -> 0 | W94: 0.11 | X94: =(P94+Q94)/G94 -> -0.38167037 | Y94: =VLOOKUP(C94,每日行情!A:D,4,FALSE) -> 92 | Z94: =VLOOKUP(C94,每日行情!A:E,5,FALSE) -> 0.9 | AA94: =IF(I94="",((TODAY()-A94)*G94)/365.24,((I94-A94)*G94)/365.24) -> 65239.295 | AB94: 台股
A95: 46150 | C95: 6788 | D95: =VLOOKUP(C95,每日行情!A:B,2,FALSE) -> 華景電 | E95: 200 | F95: 449.5 | G95: =E95*F95 -> 89900 | H95: 76 | K95: =E95*J95 -> 0 | L95: =ROUND(J95*E95*0.1425%,0) -> 0 | M95: =ROUND(J95*E95*0.3%,0) -> 0 | O95: =IF(I95="",E95*Y95,0) -> 72300 | P95: =IF(I95="",R95-H95,(K95-H95-SUM(L95:N95)+R95-S95-T95)-G95)+(ROUND(R95*V95,0)-ROUND(R95*(1+V95),0)*W95) -> -76 | Q95: =IF(I95="",(O95-G95-(O95*0.1425%*0.65)-(O95*0.3%)-S95-T95),0) -> -17883.868 | U95: =(V95*50%)/(1+50%*V95) -> 0 | W95: 0.11 | X95: =(P95+Q95)/G95 -> -0.19977606 | Y95: =VLOOKUP(C95,每日行情!A:D,4,FALSE) -> 361.5 | Z95: =VLOOKUP(C95,每日行情!A:E,5,FALSE) -> 3 | AA95: =IF(I95="",((TODAY()-A95)*G95)/365.24,((I95-A95)*G95)/365.24) -> 39628.463 | AB95: 台股
A96: 46153 | C96: 2330 | D96: =VLOOKUP(C96,每日行情!A:B,2,FALSE) -> 台積電 | E96: 10 | F96: 2265 | G96: =E96*F96 -> 22650 | H96: 19 | K96: =E96*J96 -> 0 | L96: =ROUND(J96*E96*0.1425%,0) -> 0 | M96: =ROUND(J96*E96*0.3%,0) -> 0 | O96: =IF(I96="",E96*Y96,0) -> 24200 | P96: =IF(I96="",R96-H96,(K96-H96-SUM(L96:N96)+R96-S96-T96)-G96)+(ROUND(R96*V96,0)-ROUND(R96*(1+V96),0)*W96) -> -19 | Q96: =IF(I96="",(O96-G96-(O96*0.1425%*0.65)-(O96*0.3%)-S96-T96),0) -> 1454.9848 | U96: =(V96*50%)/(1+50%*V96) -> 0 | W96: 0.11 | X96: =(P96+Q96)/G96 -> 0.063398885 | Y96: =VLOOKUP(C96,每日行情!A:D,4,FALSE) -> 2420 | Z96: =VLOOKUP(C96,每日行情!A:E,5,FALSE) -> -20 | AA96: =IF(I96="",((TODAY()-A96)*G96)/365.24,((I96-A96)*G96)/365.24) -> 9798.2149 | AB96: 台股
A97: 46153 | C97: 3430 | D97: =VLOOKUP(C97,每日行情!A:B,2,FALSE) -> 奇鈦科 | E97: 1000 | F97: 164 | G97: =E97*F97 -> 164000 | H97: 140 | K97: =E97*J97 -> 0 | L97: =ROUND(J97*E97*0.1425%,0) -> 0 | M97: =ROUND(J97*E97*0.3%,0) -> 0 | O97: =IF(I97="",E97*Y97,0) -> 92000 | P97: =IF(I97="",R97-H97,(K97-H97-SUM(L97:N97)+R97-S97-T97)-G97)+(ROUND(R97*V97,0)-ROUND(R97*(1+V97),0)*W97) -> -140 | Q97: =IF(I97="",(O97-G97-(O97*0.1425%*0.65)-(O97*0.3%)-S97-T97),0) -> -72361.215 | U97: =(V97*50%)/(1+50%*V97) -> 0 | W97: 0.11 | X97: =(P97+Q97)/G97 -> -0.44208058 | Y97: =VLOOKUP(C97,每日行情!A:D,4,FALSE) -> 92 | Z97: =VLOOKUP(C97,每日行情!A:E,5,FALSE) -> 0.9 | AA97: =IF(I97="",((TODAY()-A97)*G97)/365.24,((I97-A97)*G97)/365.24) -> 70945.132 | AB97: 台股
A98: 46155 | C98: 00631L | D98: =VLOOKUP(C98,每日行情!A:B,2,FALSE) -> 元大台灣50正2 | E98: 2000 | F98: 31.88 | G98: =E98*F98 -> 63760 | H98: 54 | K98: =E98*J98 -> 0 | L98: =ROUND(J98*E98*0.1425%,0) -> 0 | M98: =ROUND(J98*E98*0.3%,0) -> 0 | O98: =IF(I98="",E98*Y98,0) -> 74300 | P98: =IF(I98="",R98-H98,(K98-H98-SUM(L98:N98)+R98-S98-T98)-G98)+(ROUND(R98*V98,0)-ROUND(R98*(1+V98),0)*W98) -> -54 | Q98: =IF(I98="",(O98-G98-(O98*0.1425%*0.65)-(O98*0.3%)-S98-T98),0) -> 10248.28 | U98: =(V98*50%)/(1+50%*V98) -> 0 | W98: 0.11 | X98: =(P98+Q98)/G98 -> 0.15988519 | Y98: =VLOOKUP(C98,每日行情!A:D,4,FALSE) -> 37.15 | Z98: =VLOOKUP(C98,每日行情!A:E,5,FALSE) -> 0.01 | AA98: =IF(I98="",((TODAY()-A98)*G98)/365.24,((I98-A98)*G98)/365.24) -> 27232.943 | AB98: 台股 ETF
A99: 46157 | C99: 6788 | D99: =VLOOKUP(C99,每日行情!A:B,2,FALSE) -> 華景電 | E99: 100 | F99: 411 | G99: =E99*F99 -> 41100 | H99: 35 | K99: =E99*J99 -> 0 | L99: =ROUND(J99*E99*0.1425%,0) -> 0 | M99: =ROUND(J99*E99*0.3%,0) -> 0 | O99: =IF(I99="",E99*Y99,0) -> 36150 | P99: =IF(I99="",R99-H99,(K99-H99-SUM(L99:N99)+R99-S99-T99)-G99)+(ROUND(R99*V99,0)-ROUND(R99*(1+V99),0)*W99) -> -35 | Q99: =IF(I99="",(O99-G99-(O99*0.1425%*0.65)-(O99*0.3%)-S99-T99),0) -> -5091.9339 | U99: =(V99*50%)/(1+50%*V99) -> 0 | W99: 0.11 | X99: =(P99+Q99)/G99 -> -0.12474292 | Y99: =VLOOKUP(C99,每日行情!A:D,4,FALSE) -> 361.5 | Z99: =VLOOKUP(C99,每日行情!A:E,5,FALSE) -> 3 | AA99: =IF(I99="",((TODAY()-A99)*G99)/365.24,((I99-A99)*G99)/365.24) -> 17329.427 | AB99: 台股
A100: 46160 | C100: 7818 | D100: =VLOOKUP(C100,每日行情!A:B,2,FALSE) -> 溢泰實業 | E100: 1000 | F100: 70 | G100: =E100*F100 -> 70000 | H100: 20 | K100: =E100*J100 -> 0 | L100: =ROUND(J100*E100*0.1425%,0) -> 0 | M100: =ROUND(J100*E100*0.3%,0) -> 0 | O100: =IF(I100="",E100*Y100,0) -> 59400 | P100: =IF(I100="",R100-H100,(K100-H100-SUM(L100:N100)+R100-S100-T100)-G100)+(ROUND(R100*V100,0)-ROUND(R100*(1+V100),0)*W100) -> -20 | Q100: =IF(I100="",(O100-G100-(O100*0.1425%*0.65)-(O100*0.3%)-S100-T100),0) -> -10833.219 | U100: =(V100*50%)/(1+50%*V100) -> 0 | W100: 0.11 | X100: =(P100+Q100)/G100 -> -0.15504599 | Y100: =VLOOKUP(C100,每日行情!A:D,4,FALSE) -> 59.4 | Z100: =VLOOKUP(C100,每日行情!A:E,5,FALSE) -> -0.4 | AA100: =IF(I100="",((TODAY()-A100)*G100)/365.24,((I100-A100)*G100)/365.24) -> 28939.875 | AB100: 台股
A101: 46160 | C101: 910 | D101: =VLOOKUP(C101,每日行情!A:B,2,FALSE) -> 第一金太空衛星 | E101: 66 | F101: 75.5 | G101: 4983 | H101: 1 | K101: =E101*J101 -> 0 | L101: =ROUND(J101*E101*0.1425%,0) -> 0 | M101: =ROUND(J101*E101*0.3%,0) -> 0 | O101: =IF(I101="",E101*Y101,0) -> 3408.9 | P101: =IF(I101="",R101-H101,(K101-H101-SUM(L101:N101)+R101-S101-T101)-G101)+(ROUND(R101*V101,0)-ROUND(R101*(1+V101),0)*W101) -> -1 | Q101: =IF(I101="",(O101-G101-(O101*0.1425%*0.65)-(O101*0.3%)-S101-T101),0) -> -1587.4842 | U101: =(V101*50%)/(1+50%*V101) -> 0 | W101: 0.11 | X101: =(P101+Q101)/G101 -> -0.31878069 | Y101: =VLOOKUP(C101,每日行情!A:D,4,FALSE) -> 51.65 | Z101: =VLOOKUP(C101,每日行情!A:E,5,FALSE) -> 1.75 | AA101: =IF(I101="",((TODAY()-A101)*G101)/365.24,((I101-A101)*G101)/365.24) -> 2060.1057 | AB101: 台股
A102: 46170 | C102: 1802 | D102: =VLOOKUP(C102,每日行情!A:B,2,FALSE) -> 台玻 | E102: 1000 | F102: 70.6 | G102: =E102*F102 -> 70600 | H102: 60 | K102: =E102*J102 -> 0 | L102: =ROUND(J102*E102*0.1425%,0) -> 0 | M102: =ROUND(J102*E102*0.3%,0) -> 0 | O102: =IF(I102="",E102*Y102,0) -> 66900 | P102: =IF(I102="",R102-H102,(K102-H102-SUM(L102:N102)+R102-S102-T102)-G102)+(ROUND(R102*V102,0)-ROUND(R102*(1+V102),0)*W102) -> -60 | Q102: =IF(I102="",(O102-G102-(O102*0.1425%*0.65)-(O102*0.3%)-S102-T102),0) -> -3962.6661 | U102: =(V102*50%)/(1+50%*V102) -> 0 | W102: 0.11 | X102: =(P102+Q102)/G102 -> -0.056978274 | Y102: =VLOOKUP(C102,每日行情!A:D,4,FALSE) -> 66.9 | Z102: =VLOOKUP(C102,每日行情!A:E,5,FALSE) -> 4.2 | AA102: =IF(I102="",((TODAY()-A102)*G102)/365.24,((I102-A102)*G102)/365.24) -> 27254.956 | AB102: 台股
A103: 46174 | C103: 4906 | D103: =VLOOKUP(C103,每日行情!A:B,2,FALSE) -> 正文 | E103: 1000 | F103: 53.3 | G103: =E103*F103 -> 53300 | H103: 45 | K103: =E103*J103 -> 0 | L103: =ROUND(J103*E103*0.1425%,0) -> 0 | M103: =ROUND(J103*E103*0.3%,0) -> 0 | O103: =IF(I103="",E103*Y103,0) -> 44850 | P103: =IF(I103="",R103-H103,(K103-H103-SUM(L103:N103)+R103-S103-T103)-G103)+(ROUND(R103*V103,0)-ROUND(R103*(1+V103),0)*W103) -> -45 | Q103: =IF(I103="",(O103-G103-(O103*0.1425%*0.65)-(O103*0.3%)-S103-T103),0) -> -8626.0923 | U103: =(V103*50%)/(1+50%*V103) -> 0 | W103: 0.11 | X103: =(P103+Q103)/G103 -> -0.16268466 | Y103: =VLOOKUP(C103,每日行情!A:D,4,FALSE) -> 44.85 | Z103: =VLOOKUP(C103,每日行情!A:E,5,FALSE) -> 4.05 | AA103: =IF(I103="",((TODAY()-A103)*G103)/365.24,((I103-A103)*G103)/365.24) -> 19992.608 | AB103: 台股
A104: 46178 | C104: 00631L | D104: =VLOOKUP(C104,每日行情!A:B,2,FALSE) -> 元大台灣50正2 | E104: 1000 | F104: 37.37 | G104: =E104*F104 -> 37370 | H104: 31 | K104: =E104*J104 -> 0 | L104: =ROUND(J104*E104*0.1425%,0) -> 0 | M104: =ROUND(J104*E104*0.3%,0) -> 0 | O104: =IF(I104="",E104*Y104,0) -> 37150 | P104: =IF(I104="",R104-H104,(K104-H104-SUM(L104:N104)+R104-S104-T104)-G104)+(ROUND(R104*V104,0)-ROUND(R104*(1+V104),0)*W104) -> -31 | Q104: =IF(I104="",(O104-G104-(O104*0.1425%*0.65)-(O104*0.3%)-S104-T104),0) -> -365.86019 | U104: =(V104*50%)/(1+50%*V104) -> 0 | W104: 0.11 | X104: =(P104+Q104)/G104 -> -0.010619753 | Y104: =VLOOKUP(C104,每日行情!A:D,4,FALSE) -> 37.15 | Z104: =VLOOKUP(C104,每日行情!A:E,5,FALSE) -> 0.01 | AA104: =IF(I104="",((TODAY()-A104)*G104)/365.24,((I104-A104)*G104)/365.24) -> 13608.066 | AB104: 台股 ETF
A105: 46181 | C105: 00631L | D105: 元大台灣50正2 | E105: 1000 | F105: 33.99 | G105: 33990 | H105: 29 | K105: 0 | L105: 0 | M105: 0 | O105: 33800 | P105: -29 | Q105: -322.70725 | U105: 0 | W105: 0.11 | X105: -0.010347374 | Y105: 33.8 | Z105: -2.87 | AA105: =IF(I105="",((TODAY()-A105)*G105)/365.24,((I105-A105)*G105)/365.24) -> 12098.073 | AB105: 台股
A106: 46181 | C106: 00991A | D106: 主動復華未來50 | E106: 531 | F106: 18.54 | G106: 9844 | H106: 1 | K106: 0 | L106: 0 | M106: 0 | O106: 9924.39 | P106: -1 | Q106: 41.424364 | U106: 0 | W106: 0.11 | X106: 0.0041064977 | Y106: 18.69 | Z106: -0.53 | AA106: =IF(I106="",((TODAY()-A106)*G106)/365.24,((I106-A106)*G106)/365.24) -> 3503.7783 | AB106: 台股 ETF
A108: 45923 | B108: 普通買進 | C108: QQQ | D108: =VLOOKUP(C108,美股行情!A:B,2,FALSE) -> 景順QQQ ETF | E108: 0.4981 | F108: 602.29 | G108: 300 | H108: 0.6 | I108: 46092 | J108: 594.17 | K108: =E108*J108 -> 295.95608 | L108: 0.73 | N108: 0 | O108: =IF(I108="",E108*Y108,0) -> 0 | P108: =IF(I108="",R108-H108,(K108-H108-SUM(L108:N108)+R108-S108-T108)-G108)+(ROUND(R108*V108,0)-ROUND(R108*(1+V108),0)*W108) -> -5.373923 | Q108: =IF(I108="",(O108-G108-(O108*0.1425%*0.65)-(O108*0.3%)-S108-T108),0) -> 0 | S108: 0 | T108: =IF(ROUND(R108*(1+V108),0)>20000,ROUND(ROUND(R108*(1+V108),0)*2%,0),0) -> 0 | U108: =(V108*50%)/(1+50%*V108) -> 0 | W108: 0.11 | X108: =(P108+Q108)/G108 -> -0.017913077 | Y108: =VLOOKUP(C108,美股行情!A:C,3,FALSE) -> 716.31 | Z108: =VLOOKUP(C108,美股行情!A:G,7,FALSE) -> -2.05 | AA108: =IF(I108="",((TODAY()-A108)*G108)/365.24,((I108-A108)*G108)/365.24) -> 138.81284 | AB108: 美股
...

Sheet YuHui-帳戶紀錄
A1: 日期 | B1: 台幣提出 | C1: 台幣存入 | D1: 台幣結餘 | E1: 美金提出 | F1: 美金存入 | G1: 美金結餘 | J1: 類別 | K1: 台幣本金 | L1: 美金本金
A2: 45698 | C2: 429 | D2: =C2-B2 -> 429 | G2: 0 | J2: 本金 | K2: =C2 -> 429 | L2: =G2 -> 0
A3: 45698 | C3: 50000 | D3: =D2+C3-B3 -> 50429 | G3: =G2+F3-E3 -> 0 | H3: 老木金援 | J3: 本金 | K3: =IF(J3="本金",C3-B3+K2,K2) -> 50429 | L3: =IF(J3="本金",F3+L2,L2) -> 0
A4: 45698 | C4: 500000 | D4: =D3+C4-B4 -> 550429 | G4: =G3+F4-E4 -> 0 | H4: 老木金援 | J4: 本金 | K4: =IF(J4="本金",C4-B4+K3,K3) -> 550429 | L4: =IF(J4="本金",F4+L3,L3) -> 0
A5: 45700 | B5: 113597 | D5: =D4+C5-B5 -> 436832 | G5: =G4+F5-E5 -> 0 | H5: 立端 | J5: 投資 | K5: =IF(J5="本金",C5-B5+K4,K4) -> 550429 | L5: =IF(J5="本金",F5+L4,L4) -> 0
A6: 45700 | B6: 118601 | D6: =D5+C6-B6 -> 318231 | G6: =G5+F6-E6 -> 0 | H6: 飛捷 | J6: 投資 | K6: =IF(J6="本金",C6-B6+K5,K5) -> 550429 | L6: =IF(J6="本金",F6+L5,L5) -> 0
A7: 45701 | B7: 92579 | D7: =D6+C7-B7 -> 225652 | G7: =G6+F7-E7 -> 0 | H7: 寬宏藝術 | J7: 投資 | K7: =IF(J7="本金",C7-B7+K6,K6) -> 550429 | L7: =IF(J7="本金",F7+L6,L6) -> 0
A8: 45705 | C8: 450000 | D8: =D7+C8-B8 -> 675652 | G8: =G7+F8-E8 -> 0 | H8: 老木金援 | J8: 本金 | K8: =IF(J8="本金",C8-B8+K7,K7) -> 1000429 | L8: =IF(J8="本金",F8+L7,L7) -> 0
A9: 45706 | B9: 29124 | D9: =D8+C9-B9 -> 646528 | G9: =G8+F9-E9 -> 0 | H9: 玉山金 | J9: 投資 | K9: =IF(J9="本金",C9-B9+K8,K8) -> 1000429 | L9: =IF(J9="本金",F9+L8,L8) -> 0
A10: 45706 | B10: 53345 | D10: =D9+C10-B10 -> 593183 | G10: =G9+F10-E10 -> 0 | H10: 華新 | J10: 投資 | K10: =IF(J10="本金",C10-B10+K9,K9) -> 1000429 | L10: =IF(J10="本金",F10+L9,L9) -> 0
A11: 45706 | B11: 69359 | D11: =D10+C11-B11 -> 523824 | G11: =G10+F11-E11 -> 0 | H11: 裕民 | J11: 投資 | K11: =IF(J11="本金",C11-B11+K10,K10) -> 1000429 | L11: =IF(J11="本金",F11+L10,L10) -> 0
A12: 45706 | B12: 110594 | D12: =D11+C12-B12 -> 413230 | G12: =G11+F12-E12 -> 0 | H12: 光寶科 | J12: 投資 | K12: =IF(J12="本金",C12-B12+K11,K11) -> 1000429 | L12: =IF(J12="本金",F12+L11,L11) -> 0
A13: 45708 | B13: 17920 | D13: =D12+C13-B13 -> 395310 | G13: =G12+F13-E13 -> 0 | H13: 凱基金 | J13: 投資 | K13: =IF(J13="本金",C13-B13+K12,K12) -> 1000429 | L13: =IF(J13="本金",F13+L12,L12) -> 0
A14: 45709 | B14: 87975 | D14: =D13+C14-B14 -> 307335 | G14: =G13+F14-E14 -> 0 | H14: 僑威 | J14: 投資 | K14: =IF(J14="本金",C14-B14+K13,K13) -> 1000429 | L14: =IF(J14="本金",F14+L13,L13) -> 0
A15: 45713 | C15: 84973 | D15: =D14+C15-B15 -> 392308 | G15: =G14+F15-E15 -> 0 | H15: 僑威 | J15: 投資 | K15: =IF(J15="本金",C15-B15+K14,K14) -> 1000429 | L15: =IF(J15="本金",F15+L14,L14) -> 0
A16: 45713 | B16: 70059 | D16: =D15+C16-B16 -> 322249 | G16: =G15+F16-E16 -> 0 | H16: 華碩 | J16: 投資 | K16: =IF(J16="本金",C16-B16+K15,K15) -> 1000429 | L16: =IF(J16="本金",F16+L15,L15) -> 0
A17: 45713 | C17: 500000 | D17: =D16+C17-B17 -> 822249 | G17: =G16+F17-E17 -> 0 | H17: 老木金援 | J17: 本金 | K17: =IF(J17="本金",C17-B17+K16,K16) -> 1500429 | L17: =IF(J17="本金",F17+L16,L16) -> 0
A18: 45715 | C18: 115056 | D18: =D17+C18-B18 -> 937305 | G18: =G17+F18-E18 -> 0 | H18: 立端 | J18: 投資 | K18: =IF(J18="本金",C18-B18+K17,K17) -> 1500429 | L18: =IF(J18="本金",F18+L17,L17) -> 0
A19: 45715 | C19: 500000 | D19: =D18+C19-B19 -> 1437305 | G19: =G18+F19-E19 -> 0 | H19: 老木金援 | J19: 本金 | K19: =IF(J19="本金",C19-B19+K18,K18) -> 2000429 | L19: =IF(J19="本金",F19+L18,L18) -> 0
A20: 45715 | B20: 654559 | D20: =D19+C20-B20 -> 782746 | G20: =G19+F20-E20 -> 0 | H20: 華城 | J20: 投資 | K20: =IF(J20="本金",C20-B20+K19,K19) -> 2000429 | L20: =IF(J20="本金",F20+L19,L19) -> 0
A21: 45715 | B21: 100 | D21: =D20+C21-B21 -> 782646 | G21: =G20+F21-E21 -> 0 | H21: 承銷申購 | J21: 投資 | K21: =IF(J21="本金",C21-B21+K20,K20) -> 2000429 | L21: =IF(J21="本金",F21+L20,L20) -> 0
A22: 45719 | C22: 91547 | D22: =D21+C22-B22 -> 874193 | G22: =G21+F22-E22 -> 0 | H22: 寬宏藝術 | J22: 投資 | K22: =IF(J22="本金",C22-B22+K21,K21) -> 2000429 | L22: =IF(J22="本金",F22+L21,L21) -> 0
A23: 45719 | B23: 564482 | D23: =D22+C23-B23 -> 309711 | G23: =G22+F23-E23 -> 0 | H23: 群聯 | J23: 投資 | K23: =IF(J23="本金",C23-B23+K22,K22) -> 2000429 | L23: =IF(J23="本金",F23+L22,L22) -> 0
A24: 45720 | C24: 18076 | D24: =D23+C24-B24 -> 327787 | G24: =G23+F24-E24 -> 0 | H24: 凱基金 | J24: 投資 | K24: =IF(J24="本金",C24-B24+K23,K23) -> 2000429 | L24: =IF(J24="本金",F24+L23,L23) -> 0
A25: 45720 | C25: 29387 | D25: =D24+C25-B25 -> 357174 | G25: =G24+F25-E25 -> 0 | H25: 玉山金 | J25: 投資 | K25: =IF(J25="本金",C25-B25+K24,K24) -> 2000429 | L25: =IF(J25="本金",F25+L24,L24) -> 0
A26: 45720 | C26: 109576 | D26: =D25+C26-B26 -> 466750 | G26: =G25+F26-E26 -> 0 | H26: 光寶科 | J26: 投資 | K26: =IF(J26="本金",C26-B26+K25,K25) -> 2000429 | L26: =IF(J26="本金",F26+L25,L25) -> 0
A27: 45720 | C27: 161875 | D27: =D26+C27-B27 -> 628625 | G27: =G26+F27-E27 -> 0 | H27: 飛捷 | J27: 投資 | K27: =IF(J27="本金",C27-B27+K26,K26) -> 2000429 | L27: =IF(J27="本金",F27+L26,L26) -> 0
A28: 45722 | C28: 55139 | D28: =D27+C28-B28 -> 683764 | G28: =G27+F28-E28 -> 0 | H28: 華新 | J28: 投資 | K28: =IF(J28="本金",C28-B28+K27,K27) -> 2000429 | L28: =IF(J28="本金",F28+L27,L27) -> 0 | N28: 683764 | O28: =D28-N28 -> 0
A29: 45723 | B29: 172147 | D29: =D28+C29-B29 -> 511617 | G29: =G28+F29-E29 -> 0 | H29: 帆宣 | J29: 投資 | K29: =IF(J29="本金",C29-B29+K28,K28) -> 2000429 | L29: =IF(J29="本金",F29+L28,L28) -> 0
A30: 45726 | B30: 81769 | D30: =D29+C30-B30 -> 429848 | G30: =G29+F30-E30 -> 0 | H30: 矽格 | J30: 投資 | K30: =IF(J30="本金",C30-B30+K29,K29) -> 2000429 | L30: =IF(J30="本金",F30+L29,L29) -> 0
A31: 45726 | B31: 49242 | D31: =D30+C31-B31 -> 380606 | G31: =G30+F31-E31 -> 0 | H31: 大成鋼 | J31: 投資 | K31: =IF(J31="本金",C31-B31+K30,K30) -> 2000429 | L31: =IF(J31="本金",F31+L30,L30) -> 0
A32: 45729 | C32: 64352 | D32: =D31+C32-B32 -> 444958 | G32: =G31+F32-E32 -> 0 | H32: 華碩 | J32: 投資 | K32: =IF(J32="本金",C32-B32+K31,K31) -> 2000429 | L32: =IF(J32="本金",F32+L31,L31) -> 0
A33: 45729 | C33: 75210 | D33: =D32+C33-B33 -> 520168 | G33: =G32+F33-E33 -> 0 | H33: 矽格 | J33: 投資 | K33: =IF(J33="本金",C33-B33+K32,K32) -> 2000429 | L33: =IF(J33="本金",F33+L32,L32) -> 0
A34: 45729 | C34: 587726 | D34: =D33+C34-B34 -> 1107894 | G34: =G33+F34-E34 -> 0 | H34: 華城 | J34: 投資 | K34: =IF(J34="本金",C34-B34+K33,K33) -> 2000429 | L34: =IF(J34="本金",F34+L33,L33) -> 0
A35: 45730 | C35: 48663 | D35: =D34+C35-B35 -> 1156557 | G35: =G34+F35-E35 -> 0 | H35: 大成鋼 | J35: 投資 | K35: =IF(J35="本金",C35-B35+K34,K34) -> 2000429 | L35: =IF(J35="本金",F35+L34,L34) -> 0
A36: 45730 | C36: 70329 | D36: =D35+C36-B36 -> 1226886 | G36: =G35+F36-E36 -> 0 | H36: 裕民 | J36: 投資 | K36: =IF(J36="本金",C36-B36+K35,K35) -> 2000429 | L36: =IF(J36="本金",F36+L35,L35) -> 0
A37: 45730 | B37: 86874 | D37: =D36+C37-B37 -> 1140012 | G37: =G36+F37-E37 -> 0 | H37: 新盛力 | J37: 投資 | K37: =IF(J37="本金",C37-B37+K36,K36) -> 2000429 | L37: =IF(J37="本金",F37+L36,L36) -> 0
A38: 45733 | C38: 2319 | D38: =D37+C38-B38 -> 1142331 | G38: =G37+F38-E38 -> 0 | H38: 順達 | J38: 投資 | K38: =IF(J38="本金",C38-B38+K37,K37) -> 2000429 | L38: =IF(J38="本金",F38+L37,L37) -> 0
A39: 45733 | C39: 161376 | D39: =D38+C39-B39 -> 1303707 | G39: =G38+F39-E39 -> 0 | H39: 帆宣 | J39: 投資 | K39: =IF(J39="本金",C39-B39+K38,K38) -> 2000429 | L39: =IF(J39="本金",F39+L38,L38) -> 0
A40: 45734 | C40: 2449 | D40: =D39+C40-B40 -> 1306156 | G40: =G39+F40-E40 -> 0 | H40: 波若威 | J40: 投資 | K40: =IF(J40="本金",C40-B40+K39,K39) -> 2000429 | L40: =IF(J40="本金",F40+L39,L39) -> 0 | N40: 1306016 | O40: =D40-N40 -> 140
A41: 45734 | C41: 87264 | D41: =D40+C41-B41 -> 1393420 | G41: =G40+F41-E41 -> 0 | H41: 新盛力 | J41: 投資 | K41: =IF(J41="本金",C41-B41+K40,K40) -> 2000429 | L41: =IF(J41="本金",F41+L40,L40) -> 0
A42: 45737 | B42: 77266 | D42: =D41+C42-B42 -> 1316154 | G42: =G41+F42-E42 -> 0 | H42: 陽明 | J42: 投資 | K42: =IF(J42="本金",C42-B42+K41,K41) -> 2000429 | L42: =IF(J42="本金",F42+L41,L41) -> 0
A43: 45741 | B43: 1964 | D43: =D42+C43-B43 -> 1314190 | G43: =G42+F43-E43 -> 0 | H43: 漢翔 | J43: 投資 | K43: =IF(J43="本金",C43-B43+K42,K42) -> 2000429 | L43: =IF(J43="本金",F43+L42,L42) -> 0
A44: 45741 | B44: 51744 | D44: =D43+C44-B44 -> 1262446 | G44: =G43+F44-E44 -> 0 | H44: 漢翔 | J44: 投資 | K44: =IF(J44="本金",C44-B44+K43,K43) -> 2000429 | L44: =IF(J44="本金",F44+L43,L43) -> 0
A45: 45741 | B45: 138117 | D45: =D44+C45-B45 -> 1124329 | G45: =G44+F45-E45 -> 0 | H45: 東陽 | J45: 投資 | K45: =IF(J45="本金",C45-B45+K44,K44) -> 2000429 | L45: =IF(J45="本金",F45+L44,L44) -> 0
A46: 45742 | B46: 249212 | D46: =D45+C46-B46 -> 875117 | G46: =G45+F46-E46 -> 0 | H46: 智原 | J46: 投資 | K46: =IF(J46="本金",C46-B46+K45,K45) -> 2000429 | L46: =IF(J46="本金",F46+L45,L45) -> 0
A47: 45743 | B47: 108092 | D47: =D46+C47-B47 -> 767025 | G47: =G46+F47-E47 -> 0 | H47: 長虹 | J47: 投資 | K47: =IF(J47="本金",C47-B47+K46,K46) -> 2000429 | L47: =IF(J47="本金",F47+L46,L46) -> 0
A48: 45743 | C48: 570792 | D48: =D47+C48-B48 -> 1337817 | G48: =G47+F48-E48 -> 0 | H48: 群聯 | J48: 投資 | K48: =IF(J48="本金",C48-B48+K47,K47) -> 2000429 | L48: =IF(J48="本金",F48+L47,L47) -> 0
A49: 45744 | C49: 132488 | D49: =D48+C49-B49 -> 1470305 | G49: =G48+F49-E49 -> 0 | H49: 東陽 | J49: 投資 | K49: =IF(J49="本金",C49-B49+K48,K48) -> 2000429 | L49: =IF(J49="本金",F49+L48,L48) -> 0
A50: 45747 | C50: 52299 | D50: =D49+C50-B50 -> 1522604 | G50: =G49+F50-E50 -> 0 | H50: 漢翔 | J50: 投資 | K50: =IF(J50="本金",C50-B50+K49,K49) -> 2000429 | L50: =IF(J50="本金",F50+L49,L49) -> 0 | N50: 1926603 | O50: =D50-N50 -> -403999
A51: 45747 | C51: 75907 | D51: =D50+C51-B51 -> 1598511 | G51: =G50+F51-E51 -> 0 | H51: 陽明 | J51: 投資 | K51: =IF(J51="本金",C51-B51+K50,K50) -> 2000429 | L51: =IF(J51="本金",F51+L50,L50) -> 0
A52: 45747 | C52: 105094 | D52: =D51+C52-B52 -> 1703605 | G52: =G51+F52-E52 -> 0 | H52: 長虹 | J52: 投資 | K52: =IF(J52="本金",C52-B52+K51,K51) -> 2000429 | L52: =IF(J52="本金",F52+L51,L51) -> 0
A53: 45747 | C53: 241068 | D53: =D52+C53-B53 -> 1944673 | G53: =G52+F53-E53 -> 0 | H53: 智原 | J53: 投資 | K53: =IF(J53="本金",C53-B53+K52,K52) -> 2000429 | L53: =IF(J53="本金",F53+L52,L52) -> 0 | N53: 1944453 | O53: =D53-N53 -> 220
A54: 45747 | B54: 220 | D54: =D53+C54-B54 -> 1944453 | G54: =G53+F54-E54 -> 0 | H54: 承銷申購 | J54: 投資 | K54: =IF(J54="本金",C54-B54+K53,K53) -> 2000429 | L54: =IF(J54="本金",F54+L53,L53) -> 0
A55: 45762 | B55: 200000 | D55: =D54+C55-B55 -> 1744453 | G55: =G54+F55-E55 -> 0 | J55: 本金 | K55: =IF(J55="本金",C55-B55+K54,K54) -> 1800429 | L55: =IF(J55="本金",F55+L54,L54) -> 0
A56: 45782 | B56: 200000 | D56: =D55+C56-B56 -> 1544453 | G56: =G55+F56-E56 -> 0 | J56: 本金 | K56: =IF(J56="本金",C56-B56+K55,K55) -> 1600429 | L56: =IF(J56="本金",F56+L55,L55) -> 0
A57: 45829 | C57: 23 | D57: =D56+C57-B57 -> 1544476 | G57: =G56+F57-E57 -> 0 | J57: 投資 | K57: =IF(J57="本金",C57-B57+K56,K56) -> 1600429 | L57: =IF(J57="本金",F57+L56,L56) -> 0
A58: 45891 | B58: 37632 | D58: =D57+C58-B58 -> 1506844 | G58: =G57+F58-E58 -> 0 | H58: 世芯-KY | J58: 投資 | K58: =IF(J58="本金",C58-B58+K57,K57) -> 1600429 | L58: =IF(J58="本金",F58+L57,L57) -> 0
A59: 45901 | B59: 10001 | C59: 114 | D59: =D58+C59-B59 -> 1496957 | G59: =G58+F59-E59 -> 0 | H59: 台股定期定額 | J59: 投資 | K59: =IF(J59="本金",C59-B59+K58,K58) -> 1600429 | L59: =IF(J59="本金",F59+L58,L58) -> 0
A60: 45908 | B60: 10001 | C60: 205 | D60: =D59+C60-B60 -> 1487161 | G60: =G59+F60-E60 -> 0 | H60: 台股定期定額 | J60: 投資 | K60: =IF(J60="本金",C60-B60+K59,K59) -> 1600429 | L60: =IF(J60="本金",F60+L59,L59) -> 0
A61: 45912 | B61: 60952 | D61: =D60+C61-B61 -> 1426209 | G61: =G60+F61-E61 -> 0 | H61: 永光 | J61: 投資 | K61: =IF(J61="本金",C61-B61+K60,K60) -> 1600429 | L61: =IF(J61="本金",F61+L60,L60) -> 0
A62: 45915 | D62: =D61+C62-B62 -> 1426209 | F62: 136.51 | G62: =G61+F62-E62 -> 136.51 | J62: 本金 | K62: =IF(J62="本金",C62-B62+K61,K61) -> 1600429 | L62: =IF(J62="本金",F62+L61,L61) -> 136.51
A63: 45915 | D63: =D62+C63-B63 -> 1426209 | F63: 3298.48 | G63: =G62+F63-E63 -> 3434.99 | H63: 行動換匯 | J63: 本金 | K63: =IF(J63="本金",C63-B63+K62,K62) -> 1600429 | L63: =IF(J63="本金",F63+L62,L62) -> 3434.99
A64: 45919 | B64: 65455 | D64: =D63+C64-B64 -> 1360754 | G64: =G63+F64-E64 -> 3434.99 | H64: 晶豪科 | J64: 投資 | K64: =IF(J64="本金",C64-B64+K63,K63) -> 1600429 | L64: =IF(J64="本金",F64+L63,L63) -> 3434.99
A65: 45919 | B65: 92879 | D65: =D64+C65-B65 -> 1267875 | G65: =G64+F65-E65 -> 3434.99 | H65: 晶技 | J65: 投資 | K65: =IF(J65="本金",C65-B65+K64,K64) -> 1600429 | L65: =IF(J65="本金",F65+L64,L64) -> 3434.99
A66: 45919 | B66: 95081 | D66: =D65+C66-B66 -> 1172794 | G66: =G65+F66-E66 -> 3434.99 | H66: 台勝科 | J66: 投資 | K66: =IF(J66="本金",C66-B66+K65,K65) -> 1600429 | L66: =IF(J66="本金",F66+L65,L65) -> 3434.99
A67: 45924 | D67: =D66+C67-B67 -> 1172794 | E67: =300+0.6 -> 300.6 | G67: =G66+F67-E67 -> 3134.39 | H67: 景順QQQ ETF | J67: 投資 | K67: =IF(J67="本金",C67-B67+K66,K66) -> 1600429 | L67: =IF(J67="本金",F67+L66,L66) -> 3434.99
A68: 45924 | D68: =D67+C68-B68 -> 1172794 | E68: =300+0.6 -> 300.6 | G68: =G67+F68-E68 -> 2833.79 | H68: 特斯拉 | J68: 投資 | K68: =IF(J68="本金",C68-B68+K67,K67) -> 1600429 | L68: =IF(J68="本金",F68+L67,L67) -> 3434.99
A69: 45925 | C69: 58724 | D69: =D68+C69-B69 -> 1231518 | G69: =G68+F69-E69 -> 2833.79 | H69: 永光 | J69: 投資 | K69: =IF(J69="本金",C69-B69+K68,K68) -> 1600429 | L69: =IF(J69="本金",F69+L68,L68) -> 3434.99
A70: 45926 | B70: 34229 | D70: =D69+C70-B70 -> 1197289 | G70: =G69+F70-E70 -> 2833.79 | H70: 世芯-KY | J70: 投資 | K70: =IF(J70="本金",C70-B70+K69,K69) -> 1600429 | L70: =IF(J70="本金",F70+L69,L69) -> 3434.99
A71: 45930 | C71: 72222 | D71: =D70+C71-B71 -> 1269511 | G71: =G70+F71-E71 -> 2833.79 | H71: 晶豪科 | J71: 投資 | K71: =IF(J71="本金",C71-B71+K70,K70) -> 1600429 | L71: =IF(J71="本金",F71+L70,L70) -> 3434.99
A72: 45930 | C72: 91048 | D72: =D71+C72-B72 -> 1360559 | G72: =G71+F72-E72 -> 2833.79 | H72: 晶技 | J72: 投資 | K72: =IF(J72="本金",C72-B72+K71,K71) -> 1600429 | L72: =IF(J72="本金",F72+L71,L71) -> 3434.99
A73: 45930 | C73: 106090 | D73: =D72+C73-B73 -> 1466649 | G73: =G72+F73-E73 -> 2833.79 | H73: 台勝科 | J73: 投資 | K73: =IF(J73="本金",C73-B73+K72,K72) -> 1600429 | L73: =IF(J73="本金",F73+L72,L72) -> 3434.99
A74: 45930 | B74: 74263 | D74: =D73+C74-B74 -> 1392386 | G74: =G73+F74-E74 -> 2833.79 | H74: 仁寶 | J74: 投資 | K74: =IF(J74="本金",C74-B74+K73,K73) -> 1600429 | L74: =IF(J74="本金",F74+L73,L73) -> 3434.99
A75: 45930 | B75: 78867 | D75: =D74+C75-B75 -> 1313519 | G75: =G74+F75-E75 -> 2833.79 | H75: 凱美 | J75: 投資 | K75: =IF(J75="本金",C75-B75+K74,K74) -> 1600429 | L75: =IF(J75="本金",F75+L74,L74) -> 3434.99
A76: 45930 | B76: 59150 | D76: =D75+C76-B76 -> 1254369 | G76: =G75+F76-E76 -> 2833.79 | H76: 盈正 | J76: 投資 | K76: =IF(J76="本金",C76-B76+K75,K75) -> 1600429 | L76: =IF(J76="本金",F76+L75,L75) -> 3434.99
A77: 45930 | B77: 70760 | D77: =D76+C77-B77 -> 1183609 | G77: =G76+F77-E77 -> 2833.79 | H77: 長科* | J77: 投資 | K77: =IF(J77="本金",C77-B77+K76,K76) -> 1600429 | L77: =IF(J77="本金",F77+L76,L76) -> 3434.99
A78: 45931 | B78: 32627 | D78: =D77+C78-B78 -> 1150982 | G78: =G77+F78-E78 -> 2833.79 | H78: 世芯-KY | J78: 投資 | K78: =IF(J78="本金",C78-B78+K77,K77) -> 1600429 | L78: =IF(J78="本金",F78+L77,L77) -> 3434.99
A79: 45931 | B79: 10001 | C79: 114 | D79: =D78+C79-B79 -> 1141095 | G79: =G78+F79-E79 -> 2833.79 | H79: 台股定期定額 | J79: 投資 | K79: =IF(J79="本金",C79-B79+K78,K78) -> 1600429 | L79: =IF(J79="本金",F79+L78,L78) -> 3434.99
A80: 45932 | C80: 64551 | D80: =D79+C80-B80 -> 1205646 | G80: =G79+F80-E80 -> 2833.79 | H80: 仁寶 | J80: 投資 | K80: =IF(J80="本金",C80-B80+K79,K79) -> 1600429 | L80: =IF(J80="本金",F80+L79,L79) -> 3434.99
A81: 45937 | C81: 357 | D81: =D80+C81-B81 -> 1206003 | G81: =G80+F81-E81 -> 2833.79 | H81: 世芯-KY | J81: 投資 | K81: =IF(J81="本金",C81-B81+K80,K80) -> 1600429 | L81: =IF(J81="本金",F81+L80,L80) -> 3434.99
A82: 45937 | B82: 10001 | C82: 163 | D82: =D81+C82-B82 -> 1196165 | G82: =G81+F82-E82 -> 2833.79 | H82: 台股定期定額 | J82: 投資 | K82: =IF(J82="本金",C82-B82+K81,K81) -> 1600429 | L82: =IF(J82="本金",F82+L81,L81) -> 3434.99
A83: 45938 | C83: 71723 | D83: =D82+C83-B83 -> 1267888 | G83: =G82+F83-E83 -> 2833.79 | H83: 長科* | J83: 投資 | K83: =IF(J83="本金",C83-B83+K82,K82) -> 1600429 | L83: =IF(J83="本金",F83+L82,L82) -> 3434.99
A84: 45944 | C84: 73218 | D84: =D83+C84-B84 -> 1341106 | G84: =G83+F84-E84 -> 2833.79 | H84: 盈正 | J84: 投資 | K84: =IF(J84="本金",C84-B84+K83,K83) -> 1600429 | L84: =IF(J84="本金",F84+L83,L83) -> 3434.99
A85: 45946 | C85: 76505 | D85: =D84+C85-B85 -> 1417611 | G85: =G84+F85-E85 -> 2833.79 | H85: 凱美 | J85: 投資 | K85: =IF(J85="本金",C85-B85+K84,K84) -> 1600429 | L85: =IF(J85="本金",F85+L84,L84) -> 3434.99
A86: 45946 | B86: 31727 | D86: =D85+C86-B86 -> 1385884 | G86: =G85+F86-E86 -> 2833.79 | H86: 世芯-KY | J86: 投資 | K86: =IF(J86="本金",C86-B86+K85,K85) -> 1600429 | L86: =IF(J86="本金",F86+L85,L85) -> 3434.99
A87: 45957 | D87: =D86+C87-B87 -> 1385884 | E87: =300+0.6 -> 300.6 | G87: =G86+F87-E87 -> 2533.19 | H87: 景順QQQ ETF | J87: 投資 | K87: =IF(J87="本金",C87-B87+K86,K86) -> 1600429 | L87: =IF(J87="本金",F87+L86,L86) -> 3434.99
A88: 45957 | D88: =D87+C88-B88 -> 1385884 | E88: =299.36+0.6 -> 299.96 | G88: =G87+F88-E88 -> 2233.23 | H88: 特斯拉 | J88: 投資 | K88: =IF(J88="本金",C88-B88+K87,K87) -> 1600429 | L88: =IF(J88="本金",F88+L87,L87) -> 3434.99
A89: 45964 | B89: 10001 | C89: 140 | D89: =D88+C89-B89 -> 1376023 | G89: =G88+F89-E89 -> 2233.23 | H89: 台股定期定額 | J89: 投資 | K89: =IF(J89="本金",C89-B89+K88,K88) -> 1600429 | L89: =IF(J89="本金",F89+L88,L88) -> 3434.99
A90: 45966 | C90: 137867 | D90: =D89+C90-B90 -> 1513890 | G90: =G89+F90-E90 -> 2233.23 | H90: 世芯-KY | J90: 投資 | K90: =IF(J90="本金",C90-B90+K89,K89) -> 1600429 | L90: =IF(J90="本金",F90+L89,L89) -> 3434.99
A91: 45967 | B91: 10001 | C91: 44 | D91: =D90+C91-B91 -> 1503933 | G91: =G90+F91-E91 -> 2233.23 | H91: 台股定期定額 | J91: 投資 | K91: =IF(J91="本金",C91-B91+K90,K90) -> 1600429 | L91: =IF(J91="本金",F91+L90,L90) -> 3434.99
A92: 45975 | C92: 468 | D92: =D91+C92-B92 -> 1504401 | G92: =G91+F92-E92 -> 2233.23 | H92: 元大高股息 | J92: 投資 | K92: =IF(J92="本金",C92-B92+K91,K91) -> 1600429 | L92: =IF(J92="本金",F92+L91,L91) -> 3434.99
A93: 45986 | D93: =D92+C93-B93 -> 1504401 | E93: =300+0.3 -> 300.3 | G93: =G92+F93-E93 -> 1932.93 | H93: 景順QQQ ETF | J93: 投資 | K93: =IF(J93="本金",C93-B93+K92,K92) -> 1600429 | L93: =IF(J93="本金",F93+L92,L92) -> 3434.99
A94: 45986 | D94: =D93+C94-B94 -> 1504401 | E94: =300+0.3 -> 300.3 | G94: =G93+F94-E94 -> 1632.63 | H94: 特斯拉 | J94: 投資 | K94: =IF(J94="本金",C94-B94+K93,K93) -> 1600429 | L94: =IF(J94="本金",F94+L93,L93) -> 3434.99
A95: 45964 | B95: 10001 | C95: 140 | D95: =D94+C95-B95 -> 1494540 | G95: =G94+F95-E95 -> 1632.63 | H95: 台股定期定額 | J95: 投資 | K95: =IF(J95="本金",C95-B95+K94,K94) -> 1600429 | L95: =IF(J95="本金",F95+L94,L94) -> 3434.99
A96: 45992 | B96: 10001 | C96: 92 | D96: =D95+C96-B96 -> 1484631 | G96: =G95+F96-E96 -> 1632.63 | H96: 台股定期定額 | J96: 投資 | K96: =IF(J96="本金",C96-B96+K95,K95) -> 1600429 | L96: =IF(J96="本金",F96+L95,L95) -> 3434.99
A97: 45999 | B97: 10001 | C97: 30 | D97: =D96+C97-B97 -> 1474660 | G97: =G96+F97-E97 -> 1632.63 | H97: 台股定期定額 | J97: 投資 | K97: =IF(J97="本金",C97-B97+K96,K96) -> 1600429 | L97: =IF(J97="本金",F97+L96,L96) -> 3434.99
A98: 46006 | D98: =D97+C98-B98 -> 1474660 | F98: 958.56 | G98: =G97+F98-E98 -> 2591.19 | H98: 特斯拉 | J98: 投資 | K98: =IF(J98="本金",C98-B98+K97,K97) -> 1600429 | L98: =IF(J98="本金",F98+L97,L97) -> 3434.99
A99: 46006 | D99: =D98+C99-B99 -> 1474660 | F99: 6078.85 | G99: =G98+F99-E99 -> 8670.04 | J99: 本金 | K99: =IF(J99="本金",C99-B99+K98,K98) -> 1600429 | L99: =IF(J99="本金",F99+L98,L98) -> 9513.84
A100: 46013 | C100: 49 | D100: =D99+C100-B100 -> 1474709 | G100: =G99+F100-E100 -> 8670.04 | H100: 半年息 | J100: 投資 | K100: =IF(J100="本金",C100-B100+K99,K99) -> 1600429 | L100: =IF(J100="本金",F100+L99,L99) -> 9513.84
...

Sheet 2025
A1: 買進日期 | B1: 種類 | C1: 股票代號 | D1: 股票名稱 | E1: 股數 | F1: 買進價 | G1: 成交金額 | H1: 手續費 | I1: 賣出日期 | J1: 賣出價 | K1: 成交金額 | L1: 手續費 | M1: 交易稅 | N1: 證所稅 | O1: 參考現值 | P1: 已實現損益 | Q1: 未實現損益 | R1: 除息 | S1: 手續費 | T1: 健保補充保費 | U1: 實質扣抵稅率 | V1: 扣抵稅率 | W1: 所得稅率 | X1: 投資報酬率 | Y1: 今日股價 | Z1: 漲跌 | AB1: 買進理由 | AC1: 賣出理由
A2: 45707 | C2: 3078 | D2: 僑威 | E2: 1000 | F2: 87.9 | G2: =E2*F2 -> 87900 | H2: 75 | I2: 45709 | J2: 85.3 | K2: =E2*J2 -> 85300 | L2: 72 | M2: 255 | N2: 0 | O2: =IF(I2="",E2*Y2,0) -> 0 | P2: =IF(I2="",R2-H2,(K2-H2-SUM(L2:N2)+R2-S2-T2)-G2)+(ROUND(R2*V2,0)-ROUND(R2*(1+V2),0)*W2) -> -3012 | Q2: =IF(I2="",(O2-G2-(O2*0.1425%*0.65)-(O2*0.3%)-S2-T2),0) -> 0 | S2: 10 | U2: =(V2*50%)/(1+50%*V2) -> 0 | W2: 0.11 | X2: =(P2+Q2)/G2 -> -0.034266212 | Y2: =VLOOKUP(C2,每日行情!A:D,4,FALSE) -> 47.3 | Z2: =VLOOKUP(C2,每日行情!A:E,5,FALSE) -> -0.1 | AA2: =IF(I2="",((TODAY()-A2)*G2)/365.24,((I2-A2)*G2)/365.24) -> 481.32735 | AB2: 強勢股 | AC2: 破10日線，認賠出場
A3: 45698 | C3: 6245 | D3: 立端 | E3: 1000 | F3: 113.5 | G3: =E3*F3 -> 113500 | H3: 97 | I3: 45713 | J3: 115.5 | K3: =E3*J3 -> 115500 | L3: 98 | M3: 346 | N3: 0 | O3: =IF(I3="",E3*Y3,0) -> 0 | P3: =IF(I3="",R3-H3,(K3-H3-SUM(L3:N3)+R3-S3-T3)-G3)+(ROUND(R3*V3,0)-ROUND(R3*(1+V3),0)*W3) -> 1449 | Q3: =IF(I3="",(O3-G3-(O3*0.1425%*0.65)-(O3*0.3%)-S3-T3),0) -> 0 | S3: 10 | U3: =(V3*50%)/(1+50%*V3) -> 0 | W3: 0.11 | X3: =(P3+Q3)/G3 -> 0.01276652 | Y3: =VLOOKUP(C3,每日行情!A:D,4,FALSE) -> 89.3 | Z3: =VLOOKUP(C3,每日行情!A:E,5,FALSE) -> 1.6 | AA3: =IF(I3="",((TODAY()-A3)*G3)/365.24,((I3-A3)*G3)/365.24) -> 4661.3186 | AB3: 強勢股 | AC3: 破5日線，獲利了結
A4: 45699 | C4: 6596 | D4: 寬宏藝術 | E4: 1000 | F4: 92.5 | G4: =E4*F4 -> 92500 | H4: 79 | I4: 45714 | J4: 91.9 | K4: =E4*J4 -> 91900 | L4: 78 | M4: 275 | N4: 0 | O4: =IF(I4="",E4*Y4,0) -> 0 | P4: =IF(I4="",R4-H4,(K4-H4-SUM(L4:N4)+R4-S4-T4)-G4)+(ROUND(R4*V4,0)-ROUND(R4*(1+V4),0)*W4) -> -1042 | Q4: =IF(I4="",(O4-G4-(O4*0.1425%*0.65)-(O4*0.3%)-S4-T4),0) -> 0 | S4: 10 | U4: =(V4*50%)/(1+50%*V4) -> 0 | W4: 0.11 | X4: =(P4+Q4)/G4 -> -0.011264865 | Y4: =VLOOKUP(C4,每日行情!A:D,4,FALSE) -> 96.1 | Z4: =VLOOKUP(C4,每日行情!A:E,5,FALSE) -> 0.8 | AA4: =IF(I4="",((TODAY()-A4)*G4)/365.24,((I4-A4)*G4)/365.24) -> 3798.872 | AB4: 強勢股 | AC4: 破10日線，認賠出場
A5: 45702 | C5: 2301 | D5: 光寶科 | E5: 1000 | F5: 110.5 | G5: =E5*F5 -> 110500 | H5: 94 | I5: 45715 | J5: 110 | K5: =E5*J5 -> 110000 | L5: 94 | M5: 330 | N5: 0 | O5: =IF(I5="",E5*Y5,0) -> 0 | P5: =IF(I5="",R5-H5,(K5-H5-SUM(L5:N5)+R5-S5-T5)-G5)+(ROUND(R5*V5,0)-ROUND(R5*(1+V5),0)*W5) -> -1028 | Q5: =IF(I5="",(O5-G5-(O5*0.1425%*0.65)-(O5*0.3%)-S5-T5),0) -> 0 | S5: 10 | U5: =(V5*50%)/(1+50%*V5) -> 0 | W5: 0.11 | X5: =(P5+Q5)/G5 -> -0.0093031674 | Y5: =VLOOKUP(C5,每日行情!A:D,4,FALSE) -> 264.5 | Z5: =VLOOKUP(C5,每日行情!A:E,5,FALSE) -> -3.5 | AA5: =IF(I5="",((TODAY()-A5)*G5)/365.24,((I5-A5)*G5)/365.24) -> 3933.0303 | AB5: 強勢股 | AC5: 破10日線，認賠出場
A6: 45706 | C6: 2883 | D6: 凱基金 | E6: 1000 | F6: 17.9 | G6: =E6*F6 -> 17900 | H6: 20 | I6: 45715 | J6: 18.15 | K6: =E6*J6 -> 18150 | L6: 20 | M6: 54 | N6: 0 | O6: =IF(I6="",E6*Y6,0) -> 0 | P6: =IF(I6="",R6-H6,(K6-H6-SUM(L6:N6)+R6-S6-T6)-G6)+(ROUND(R6*V6,0)-ROUND(R6*(1+V6),0)*W6) -> 146 | Q6: =IF(I6="",(O6-G6-(O6*0.1425%*0.65)-(O6*0.3%)-S6-T6),0) -> 0 | S6: 10 | U6: =(V6*50%)/(1+50%*V6) -> 0 | W6: 0.11 | X6: =(P6+Q6)/G6 -> 0.0081564246 | Y6: =VLOOKUP(C6,每日行情!A:D,4,FALSE) -> 39.1 | Z6: =VLOOKUP(C6,每日行情!A:E,5,FALSE) -> 0.7 | AA6: =IF(I6="",((TODAY()-A6)*G6)/365.24,((I6-A6)*G6)/365.24) -> 441.07984 | AB6: 強勢股 | AC6: 破10日線，獲利了結
A7: 45702 | C7: 2884 | D7: 玉山金 | E7: 1000 | F7: 29.1 | G7: =E7*F7 -> 29100 | H7: 24 | I7: 45715 | J7: 29.5 | K7: =E7*J7 -> 29500 | L7: 25 | M7: 88 | N7: 0 | O7: =IF(I7="",E7*Y7,0) -> 0 | P7: =IF(I7="",R7-H7,(K7-H7-SUM(L7:N7)+R7-S7-T7)-G7)+(ROUND(R7*V7,0)-ROUND(R7*(1+V7),0)*W7) -> 253 | Q7: =IF(I7="",(O7-G7-(O7*0.1425%*0.65)-(O7*0.3%)-S7-T7),0) -> 0 | S7: 10 | U7: =(V7*50%)/(1+50%*V7) -> 0 | W7: 0.11 | X7: =(P7+Q7)/G7 -> 0.0086941581 | Y7: =VLOOKUP(C7,每日行情!A:D,4,FALSE) -> 49.15 | Z7: =VLOOKUP(C7,每日行情!A:E,5,FALSE) -> 0.35 | AA7: =IF(I7="",((TODAY()-A7)*G7)/365.24,((I7-A7)*G7)/365.24) -> 1035.7573 | AB7: 強勢股 | AC7: 破10日線，獲利了結
A8: 45698 | C8: 6206 | D8: 飛捷 | E8: 1000 | F8: 118.5 | G8: =E8*F8 -> 118500 | H8: 101 | I8: 45715 | J8: 162.5 | K8: =E8*J8 -> 162500 | L8: 138 | M8: 487 | N8: 0 | O8: =IF(I8="",E8*Y8,0) -> 0 | P8: =IF(I8="",R8-H8,(K8-H8-SUM(L8:N8)+R8-S8-T8)-G8)+(ROUND(R8*V8,0)-ROUND(R8*(1+V8),0)*W8) -> 43264 | Q8: =IF(I8="",(O8-G8-(O8*0.1425%*0.65)-(O8*0.3%)-S8-T8),0) -> 0 | S8: 10 | U8: =(V8*50%)/(1+50%*V8) -> 0 | W8: 0.11 | X8: =(P8+Q8)/G8 -> 0.36509705 | Y8: =VLOOKUP(C8,每日行情!A:D,4,FALSE) -> 36.56 | Z8: =VLOOKUP(C8,每日行情!A:E,5,FALSE) -> 0.4 | AA8: =IF(I8="",((TODAY()-A8)*G8)/365.24,((I8-A8)*G8)/365.24) -> 5515.5514 | AB8: 強勢股 | AC8: 破10日線，獲利了結
A9: 45702 | C9: 1605 | D9: 華新 | E9: 1000 | F9: 26.65 | G9: =E9*F9 -> 26650 | H9: 23 | I9: 45720 | J9: 27.6 | K9: =E9*J9 -> 27600 | L9: 23 | M9: 82 | N9: 0 | O9: =IF(I9="",E9*Y9,0) -> 0 | P9: =IF(I9="",R9-H9,(K9-H9-SUM(L9:N9)+R9-S9-T9)-G9)+(ROUND(R9*V9,0)-ROUND(R9*(1+V9),0)*W9) -> 812 | Q9: =IF(I9="",(O9-G9-(O9*0.1425%*0.65)-(O9*0.3%)-S9-T9),0) -> 0 | S9: 10 | U9: =(V9*50%)/(1+50%*V9) -> 0 | W9: 0.11 | X9: =(P9+Q9)/G9 -> 0.030469043 | Y9: =VLOOKUP(C9,每日行情!A:D,4,FALSE) -> 38.5 | Z9: =VLOOKUP(C9,每日行情!A:E,5,FALSE) -> 0.8 | AA9: =IF(I9="",((TODAY()-A9)*G9)/365.24,((I9-A9)*G9)/365.24) -> 1313.383 | AB9: 強勢股 | AC9: 破10日線，獲利了結
A10: 45702 | C10: 1605 | D10: 華新 | E10: 1000 | F10: 26.65 | G10: =E10*F10 -> 26650 | H10: 22 | I10: 45721 | J10: 27.75 | K10: =E10*J10 -> 27750 | L10: 23 | M10: 83 | N10: 0 | O10: =IF(I10="",E10*Y10,0) -> 0 | P10: =IF(I10="",R10-H10,(K10-H10-SUM(L10:N10)+R10-S10-T10)-G10)+(ROUND(R10*V10,0)-ROUND(R10*(1+V10),0)*W10) -> 962 | Q10: =IF(I10="",(O10-G10-(O10*0.1425%*0.65)-(O10*0.3%)-S10-T10),0) -> 0 | S10: 10 | U10: =(V10*50%)/(1+50%*V10) -> 0 | W10: 0.11 | X10: =(P10+Q10)/G10 -> 0.036097561 | Y10: =VLOOKUP(C10,每日行情!A:D,4,FALSE) -> 38.5 | Z10: =VLOOKUP(C10,每日行情!A:E,5,FALSE) -> 0.8 | AA10: =IF(I10="",((TODAY()-A10)*G10)/365.24,((I10-A10)*G10)/365.24) -> 1386.3487 | AB10: 強勢股 | AC10: 破10日線，獲利了結
A11: 45709 | C11: 2357 | D11: 華碩 | E11: 100 | F11: 700 | G11: =E11*F11 -> 70000 | H11: 59 | I11: 45727 | J11: 646 | K11: =E11*J11 -> 64600 | L11: 55 | M11: 193 | N11: 0 | O11: =IF(I11="",E11*Y11,0) -> 0 | P11: =IF(I11="",R11-H11,(K11-H11-SUM(L11:N11)+R11-S11-T11)-G11)+(ROUND(R11*V11,0)-ROUND(R11*(1+V11),0)*W11) -> -5717 | Q11: =IF(I11="",(O11-G11-(O11*0.1425%*0.65)-(O11*0.3%)-S11-T11),0) -> 0 | S11: 10 | U11: =(V11*50%)/(1+50%*V11) -> 0 | W11: 0.11 | X11: =(P11+Q11)/G11 -> -0.081671429 | Y11: =VLOOKUP(C11,每日行情!A:D,4,FALSE) -> 994 | Z11: =VLOOKUP(C11,每日行情!A:E,5,FALSE) -> 19 | AA11: =IF(I11="",((TODAY()-A11)*G11)/365.24,((I11-A11)*G11)/365.24) -> 3449.7864 | AB11: 強勢股 | AC11: 破10日線，認賠出場
A12: 45713 | C12: 1519 | D12: 華城 | E12: 1000 | F12: 654 | G12: =E12*F12 -> 654000 | H12: 559 | I12: 45727 | J12: 590 | K12: =E12*J12 -> 590000 | L12: 504 | M12: 1770 | N12: 0 | O12: =IF(I12="",E12*Y12,0) -> 0 | P12: =IF(I12="",R12-H12,(K12-H12-SUM(L12:N12)+R12-S12-T12)-G12)+(ROUND(R12*V12,0)-ROUND(R12*(1+V12),0)*W12) -> -66843 | Q12: =IF(I12="",(O12-G12-(O12*0.1425%*0.65)-(O12*0.3%)-S12-T12),0) -> 0 | S12: 10 | U12: =(V12*50%)/(1+50%*V12) -> 0 | W12: 0.11 | X12: =(P12+Q12)/G12 -> -0.10220642 | Y12: =VLOOKUP(C12,每日行情!A:D,4,FALSE) -> 656 | Z12: =VLOOKUP(C12,每日行情!A:E,5,FALSE) -> 7 | AA12: =IF(I12="",((TODAY()-A12)*G12)/365.24,((I12-A12)*G12)/365.24) -> 25068.448 | AB12: 強勢股 | AC12: 破10日線，認賠出場
A13: 45723 | C13: 6257 | D13: 矽格 | E13: 1000 | F13: 81.7 | G13: =E13*F13 -> 81700 | H13: 69 | I13: 45727 | J13: 75.5 | K13: =E13*J13 -> 75500 | L13: 64 | M13: 226 | N13: 0 | O13: =IF(I13="",E13*Y13,0) -> 0 | P13: =IF(I13="",R13-H13,(K13-H13-SUM(L13:N13)+R13-S13-T13)-G13)+(ROUND(R13*V13,0)-ROUND(R13*(1+V13),0)*W13) -> -6569 | Q13: =IF(I13="",(O13-G13-(O13*0.1425%*0.65)-(O13*0.3%)-S13-T13),0) -> 0 | S13: 10 | U13: =(V13*50%)/(1+50%*V13) -> 0 | W13: 0.11 | X13: =(P13+Q13)/G13 -> -0.080403917 | Y13: =VLOOKUP(C13,每日行情!A:D,4,FALSE) -> 252 | Z13: =VLOOKUP(C13,每日行情!A:E,5,FALSE) -> -6 | AA13: =IF(I13="",((TODAY()-A13)*G13)/365.24,((I13-A13)*G13)/365.24) -> 894.75413 | AB13: 強勢股 | AC13: 破10日線，認賠出場
A14: 45723 | C14: 2027 | D14: =VLOOKUP(C14,每日行情!A:B,2,FALSE) -> 大成鋼 | E14: 1000 | F14: 49.2 | G14: =E14*F14 -> 49200 | H14: 42 | I14: 45728 | J14: 48.85 | K14: =E14*J14 -> 48850 | L14: 41 | M14: 146 | N14: 0 | O14: =IF(I14="",E14*Y14,0) -> 0 | P14: =IF(I14="",R14-H14,(K14-H14-SUM(L14:N14)+R14-S14-T14)-G14)+(ROUND(R14*V14,0)-ROUND(R14*(1+V14),0)*W14) -> -589 | Q14: =IF(I14="",(O14-G14-(O14*0.1425%*0.65)-(O14*0.3%)-S14-T14),0) -> 0 | S14: 10 | U14: =(V14*50%)/(1+50%*V14) -> 0 | W14: 0.11 | X14: =(P14+Q14)/G14 -> -0.011971545 | Y14: =VLOOKUP(C14,每日行情!A:D,4,FALSE) -> 50.9 | Z14: =VLOOKUP(C14,每日行情!A:E,5,FALSE) -> 1.6 | AA14: =IF(I14="",((TODAY()-A14)*G14)/365.24,((I14-A14)*G14)/365.24) -> 673.52973 | AB14: 強勢股 | AC14: 破10日線，認賠出場
A15: 45702 | C15: 2606 | D15: =VLOOKUP(C15,每日行情!A:B,2,FALSE) -> 裕民 | E15: 1000 | F15: 69.3 | G15: =E15*F15 -> 69300 | H15: 59 | I15: 45728 | J15: 70.6 | K15: =E15*J15 -> 70600 | L15: 60 | M15: 211 | N15: 0 | O15: =IF(I15="",E15*Y15,0) -> 0 | P15: =IF(I15="",R15-H15,(K15-H15-SUM(L15:N15)+R15-S15-T15)-G15)+(ROUND(R15*V15,0)-ROUND(R15*(1+V15),0)*W15) -> 960 | Q15: =IF(I15="",(O15-G15-(O15*0.1425%*0.65)-(O15*0.3%)-S15-T15),0) -> 0 | S15: 10 | U15: =(V15*50%)/(1+50%*V15) -> 0 | W15: 0.11 | X15: =(P15+Q15)/G15 -> 0.013852814 | Y15: =VLOOKUP(C15,每日行情!A:D,4,FALSE) -> 75.2 | Z15: =VLOOKUP(C15,每日行情!A:E,5,FALSE) -> -0.8 | AA15: =IF(I15="",((TODAY()-A15)*G15)/365.24,((I15-A15)*G15)/365.24) -> 4933.1946 | AB15: 強勢股 | AC15: 破10日線，獲利了結
A16: 45729 | C16: 3211 | D16: =VLOOKUP(C16,每日行情!A:B,2,FALSE) -> 順達 | E16: 1000 | F16: 210.5 | G16: =E16*F16 -> 210500 | H16: 179 | I16: 45729 | J16: 213.5 | K16: =E16*J16 -> 213500 | L16: 182 | M16: 320 | N16: 0 | O16: =IF(I16="",E16*Y16,0) -> 0 | P16: =IF(I16="",R16-H16,(K16-H16-SUM(L16:N16)+R16-S16-T16)-G16)+(ROUND(R16*V16,0)-ROUND(R16*(1+V16),0)*W16) -> 2309 | Q16: =IF(I16="",(O16-G16-(O16*0.1425%*0.65)-(O16*0.3%)-S16-T16),0) -> 0 | S16: 10 | U16: =(V16*50%)/(1+50%*V16) -> 0 | W16: 0.11 | X16: =(P16+Q16)/G16 -> 0.010969121 | Y16: =VLOOKUP(C16,每日行情!A:D,4,FALSE) -> 346 | Z16: =VLOOKUP(C16,每日行情!A:E,5,FALSE) -> -3 | AA16: =IF(I16="",((TODAY()-A16)*G16)/365.24,((I16-A16)*G16)/365.24) -> 0 | AB16: 強勢股 | AC16: 當沖
A17: 45721 | C17: 6196 | D17: =VLOOKUP(C17,每日行情!A:B,2,FALSE) -> 帆宣 | E17: 1000 | F17: 172 | G17: =E17*F17 -> 172000 | H17: 147 | I17: 45729 | J17: 162 | K17: =E17*J17 -> 162000 | L17: 138 | M17: 486 | N17: 0 | O17: =IF(I17="",E17*Y17,0) -> 0 | P17: =IF(I17="",R17-H17,(K17-H17-SUM(L17:N17)+R17-S17-T17)-G17)+(ROUND(R17*V17,0)-ROUND(R17*(1+V17),0)*W17) -> -10781 | Q17: =IF(I17="",(O17-G17-(O17*0.1425%*0.65)-(O17*0.3%)-S17-T17),0) -> 0 | S17: 10 | U17: =(V17*50%)/(1+50%*V17) -> 0 | W17: 0.11 | X17: =(P17+Q17)/G17 -> -0.062680233 | Y17: =VLOOKUP(C17,每日行情!A:D,4,FALSE) -> 609 | Z17: =VLOOKUP(C17,每日行情!A:E,5,FALSE) -> -4 | AA17: =IF(I17="",((TODAY()-A17)*G17)/365.24,((I17-A17)*G17)/365.24) -> 3767.3858 | AB17: 強勢股 | AC17: 破10日線，認賠出場
A18: 45728 | C18: 4931 | D18: =VLOOKUP(C18,每日行情!A:B,2,FALSE) -> 新盛力 | E18: 1000 | F18: 86.8 | G18: =E18*F18 -> 86800 | H18: 74 | I18: 45730 | J18: 87.6 | K18: =E18*J18 -> 87600 | L18: 74 | M18: 262 | N18: 0 | O18: =IF(I18="",E18*Y18,0) -> 0 | P18: =IF(I18="",R18-H18,(K18-H18-SUM(L18:N18)+R18-S18-T18)-G18)+(ROUND(R18*V18,0)-ROUND(R18*(1+V18),0)*W18) -> 380 | Q18: =IF(I18="",(O18-G18-(O18*0.1425%*0.65)-(O18*0.3%)-S18-T18),0) -> 0 | S18: 10 | U18: =(V18*50%)/(1+50%*V18) -> 0 | W18: 0.11 | X18: =(P18+Q18)/G18 -> 0.0043778802 | Y18: =VLOOKUP(C18,每日行情!A:D,4,FALSE) -> 217 | Z18: =VLOOKUP(C18,每日行情!A:E,5,FALSE) -> 4 | AA18: =IF(I18="",((TODAY()-A18)*G18)/365.24,((I18-A18)*G18)/365.24) -> 475.30391 | AB18: 強勢股 | AC18: 大盤籌碼軍空頭，股價下跌即賣出，收盤時未破5日線
A19: 45730 | C19: 3163 | D19: =VLOOKUP(C19,每日行情!A:B,2,FALSE) -> 波若威 | E19: 1000 | F19: 170 | G19: =E19*F19 -> 170000 | H19: 145 | I19: 45730 | J19: 173 | K19: =E19*J19 -> 173000 | L19: 147 | M19: 259 | N19: 0 | O19: =IF(I19="",E19*Y19,0) -> 0 | P19: =IF(I19="",R19-H19,(K19-H19-SUM(L19:N19)+R19-S19-T19)-G19)+(ROUND(R19*V19,0)-ROUND(R19*(1+V19),0)*W19) -> 2439 | Q19: =IF(I19="",(O19-G19-(O19*0.1425%*0.65)-(O19*0.3%)-S19-T19),0) -> 0 | S19: 10 | U19: =(V19*50%)/(1+50%*V19) -> 0 | W19: 0.11 | X19: =(P19+Q19)/G19 -> 0.014347059 | Y19: =VLOOKUP(C19,每日行情!A:D,4,FALSE) -> 589 | Z19: =VLOOKUP(C19,每日行情!A:E,5,FALSE) -> -15 | AA19: =IF(I19="",((TODAY()-A19)*G19)/365.24,((I19-A19)*G19)/365.24) -> 0 | AB19: 強勢股 | AC19: 當沖
A20: 45736 | C20: 2634 | D20: =VLOOKUP(C20,每日行情!A:B,2,FALSE) -> 漢翔 | E20: 1000 | F20: 52.9 | G20: =E20*F20 -> 52900 | H20: 45 | I20: 45736 | J20: 51.1 | K20: =E20*J20 -> 51100 | L20: 43 | M20: 76 | N20: 0 | O20: =IF(I20="",E20*Y20,0) -> 0 | P20: =IF(I20="",R20-H20,(K20-H20-SUM(L20:N20)+R20-S20-T20)-G20)+(ROUND(R20*V20,0)-ROUND(R20*(1+V20),0)*W20) -> -1974 | Q20: =IF(I20="",(O20-G20-(O20*0.1425%*0.65)-(O20*0.3%)-S20-T20),0) -> 0 | S20: 10 | U20: =(V20*50%)/(1+50%*V20) -> 0 | W20: 0.11 | X20: =(P20+Q20)/G20 -> -0.03731569 | Y20: =VLOOKUP(C20,每日行情!A:D,4,FALSE) -> 62.1 | Z20: =VLOOKUP(C20,每日行情!A:E,5,FALSE) -> 1.4 | AA20: =IF(I20="",((TODAY()-A20)*G20)/365.24,((I20-A20)*G20)/365.24) -> 0 | AB20: 強勢股 | AC20: 當沖
A21: 45714 | C21: 8299 | D21: =VLOOKUP(C21,每日行情!A:B,2,FALSE) -> 群聯 | E21: 1000 | F21: 564 | G21: =E21*F21 -> 564000 | H21: 482 | I21: 45741 | J21: 573 | K21: =E21*J21 -> 573000 | L21: 489 | M21: 1719 | N21: 0 | O21: =IF(I21="",E21*Y21,0) -> 0 | P21: =IF(I21="",R21-H21,(K21-H21-SUM(L21:N21)+R21-S21-T21)-G21)+(ROUND(R21*V21,0)-ROUND(R21*(1+V21),0)*W21) -> 6300 | Q21: =IF(I21="",(O21-G21-(O21*0.1425%*0.65)-(O21*0.3%)-S21-T21),0) -> 0 | S21: 10 | U21: =(V21*50%)/(1+50%*V21) -> 0 | W21: 0.11 | X21: =(P21+Q21)/G21 -> 0.011170213 | Y21: =VLOOKUP(C21,每日行情!A:D,4,FALSE) -> 1890 | Z21: =VLOOKUP(C21,每日行情!A:E,5,FALSE) -> 60 | AA21: =IF(I21="",((TODAY()-A21)*G21)/365.24,((I21-A21)*G21)/365.24) -> 41693.133 | AB21: 強勢股 | AC21: 破20MA，獲利了結
A22: 45737 | C22: 1319 | D22: =VLOOKUP(C22,每日行情!A:B,2,FALSE) -> 東陽 | E22: 1000 | F22: 138 | G22: =E22*F22 -> 138000 | H22: 117 | I22: 45742 | J22: 133 | K22: =E22*J22 -> 133000 | L22: 113 | M22: 399 | N22: 0 | O22: =IF(I22="",E22*Y22,0) -> 0 | P22: =IF(I22="",R22-H22,(K22-H22-SUM(L22:N22)+R22-S22-T22)-G22)+(ROUND(R22*V22,0)-ROUND(R22*(1+V22),0)*W22) -> -5639 | Q22: =IF(I22="",(O22-G22-(O22*0.1425%*0.65)-(O22*0.3%)-S22-T22),0) -> 0 | S22: 10 | U22: =(V22*50%)/(1+50%*V22) -> 0 | W22: 0.11 | X22: =(P22+Q22)/G22 -> -0.040862319 | Y22: =VLOOKUP(C22,每日行情!A:D,4,FALSE) -> 83.5 | Z22: =VLOOKUP(C22,每日行情!A:E,5,FALSE) -> 0.2 | AA22: =IF(I22="",((TODAY()-A22)*G22)/365.24,((I22-A22)*G22)/365.24) -> 1889.1688 | AB22: 強勢股 | AC22: 破10日線，認賠出場
A23: 45735 | C23: 2609 | D23: =VLOOKUP(C23,每日行情!A:B,2,FALSE) -> 陽明 | E23: 1000 | F23: 77.2 | G23: =E23*F23 -> 77200 | H23: 45 | I23: 45743 | J23: 76.2 | K23: =E23*J23 -> 76200 | L23: 65 | M23: 228 | N23: 0 | O23: =IF(I23="",E23*Y23,0) -> 0 | P23: =IF(I23="",R23-H23,(K23-H23-SUM(L23:N23)+R23-S23-T23)-G23)+(ROUND(R23*V23,0)-ROUND(R23*(1+V23),0)*W23) -> -1348 | Q23: =IF(I23="",(O23-G23-(O23*0.1425%*0.65)-(O23*0.3%)-S23-T23),0) -> 0 | S23: 10 | U23: =(V23*50%)/(1+50%*V23) -> 0 | W23: 0.11 | X23: =(P23+Q23)/G23 -> -0.01746114 | Y23: =VLOOKUP(C23,每日行情!A:D,4,FALSE) -> 64.7 | Z23: =VLOOKUP(C23,每日行情!A:E,5,FALSE) -> 1.4 | AA23: =IF(I23="",((TODAY()-A23)*G23)/365.24,((I23-A23)*G23)/365.24) -> 1690.9429 | AB23: 強勢股 | AC23: 破10日線，認賠出場
A24: 45737 | C24: 2634 | D24: =VLOOKUP(C24,每日行情!A:B,2,FALSE) -> 漢翔 | E24: 1000 | F24: 51.7 | G24: =E24*F24 -> 51700 | H24: 44 | I24: 45743 | J24: 52.5 | K24: =E24*J24 -> 52500 | L24: 44 | M24: 157 | N24: 0 | O24: =IF(I24="",E24*Y24,0) -> 0 | P24: =IF(I24="",R24-H24,(K24-H24-SUM(L24:N24)+R24-S24-T24)-G24)+(ROUND(R24*V24,0)-ROUND(R24*(1+V24),0)*W24) -> 545 | Q24: =IF(I24="",(O24-G24-(O24*0.1425%*0.65)-(O24*0.3%)-S24-T24),0) -> 0 | S24: 10 | U24: =(V24*50%)/(1+50%*V24) -> 0 | W24: 0.11 | X24: =(P24+Q24)/G24 -> 0.010541586 | Y24: =VLOOKUP(C24,每日行情!A:D,4,FALSE) -> 62.1 | Z24: =VLOOKUP(C24,每日行情!A:E,5,FALSE) -> 1.4 | AA24: =IF(I24="",((TODAY()-A24)*G24)/365.24,((I24-A24)*G24)/365.24) -> 849.30457 | AB24: 強勢股 | AC24: 破10日線，獲利了結
A25: 45740 | C25: 3035 | D25: =VLOOKUP(C25,每日行情!A:B,2,FALSE) -> 智原 | E25: 1000 | F25: 249 | G25: =E25*F25 -> 249000 | H25: 212 | I25: 45743 | J25: 242 | K25: =E25*J25 -> 242000 | L25: 206 | M25: 726 | N25: 0 | O25: =IF(I25="",E25*Y25,0) -> 0 | P25: =IF(I25="",R25-H25,(K25-H25-SUM(L25:N25)+R25-S25-T25)-G25)+(ROUND(R25*V25,0)-ROUND(R25*(1+V25),0)*W25) -> -8154 | Q25: =IF(I25="",(O25-G25-(O25*0.1425%*0.65)-(O25*0.3%)-S25-T25),0) -> 0 | S25: 10 | U25: =(V25*50%)/(1+50%*V25) -> 0 | W25: 0.11 | X25: =(P25+Q25)/G25 -> -0.032746988 | Y25: =VLOOKUP(C25,每日行情!A:D,4,FALSE) -> 197.5 | Z25: =VLOOKUP(C25,每日行情!A:E,5,FALSE) -> 0 | AA25: =IF(I25="",((TODAY()-A25)*G25)/365.24,((I25-A25)*G25)/365.24) -> 2045.2305 | AB25: 強勢股 | AC25: 破10日線，認賠出場
A26: 45740 | C26: 5534 | D26: =VLOOKUP(C26,每日行情!A:B,2,FALSE) -> 長虹 | E26: 1000 | F26: 108 | G26: =E26*F26 -> 108000 | H26: 92 | I26: 45743 | J26: 105.5 | K26: =E26*J26 -> 105500 | L26: 90 | M26: 316 | N26: 0 | O26: =IF(I26="",E26*Y26,0) -> 0 | P26: =IF(I26="",R26-H26,(K26-H26-SUM(L26:N26)+R26-S26-T26)-G26)+(ROUND(R26*V26,0)-ROUND(R26*(1+V26),0)*W26) -> -3008 | Q26: =IF(I26="",(O26-G26-(O26*0.1425%*0.65)-(O26*0.3%)-S26-T26),0) -> 0 | S26: 10 | U26: =(V26*50%)/(1+50%*V26) -> 0 | W26: 0.11 | X26: =(P26+Q26)/G26 -> -0.027851852 | Y26: =VLOOKUP(C26,每日行情!A:D,4,FALSE) -> 70.3 | Z26: =VLOOKUP(C26,每日行情!A:E,5,FALSE) -> -0.5 | AA26: =IF(I26="",((TODAY()-A26)*G26)/365.24,((I26-A26)*G26)/365.24) -> 887.08794 | AB26: 強勢股 | AC26: 破10日線，認賠出場
A27: 45910 | C27: 1711 | D27: =VLOOKUP(C27,每日行情!A:B,2,FALSE) -> 永光 | E27: 3000 | F27: 20.3 | G27: =E27*F27 -> 60900 | H27: 52 | I27: 45924 | J27: 19.65 | K27: =E27*J27 -> 58950 | L27: 50 | M27: 176 | N27: 0 | O27: =IF(I27="",E27*Y27,0) -> 0 | P27: =IF(I27="",R27-H27,(K27-H27-SUM(L27:N27)+R27-S27-T27)-G27)+(ROUND(R27*V27,0)-ROUND(R27*(1+V27),0)*W27) -> -2228 | Q27: =IF(I27="",(O27-G27-(O27*0.1425%*0.65)-(O27*0.3%)-S27-T27),0) -> 0 | U27: =(V27*50%)/(1+50%*V27) -> 0 | W27: 0.11 | X27: =(P27+Q27)/G27 -> -0.036584565 | Y27: =VLOOKUP(C27,每日行情!A:D,4,FALSE) -> 44.45 | Z27: =VLOOKUP(C27,每日行情!A:E,5,FALSE) -> 1.35 | AA27: =IF(I27="",((TODAY()-A27)*G27)/365.24,((I27-A27)*G27)/365.24) -> 2334.3555 | AB27: 阿水一式 | AC27: 破5日線，認賠出場
A28: 45917 | C28: 3006 | D28: =VLOOKUP(C28,每日行情!A:B,2,FALSE) -> 晶豪科 | E28: 1000 | F28: 65.4 | G28: =E28*F28 -> 65400 | H28: 55 | I28: 45925 | J28: 72.5 | K28: =E28*J28 -> 72500 | L28: 61 | M28: 217 | N28: 0 | O28: =IF(I28="",E28*Y28,0) -> 0 | P28: =IF(I28="",R28-H28,(K28-H28-SUM(L28:N28)+R28-S28-T28)-G28)+(ROUND(R28*V28,0)-ROUND(R28*(1+V28),0)*W28) -> 6767 | Q28: =IF(I28="",(O28-G28-(O28*0.1425%*0.65)-(O28*0.3%)-S28-T28),0) -> 0 | U28: =(V28*50%)/(1+50%*V28) -> 0 | W28: 0.11 | X28: =(P28+Q28)/G28 -> 0.10347095 | Y28: =VLOOKUP(C28,每日行情!A:D,4,FALSE) -> 244.5 | Z28: =VLOOKUP(C28,每日行情!A:E,5,FALSE) -> 15.5 | AA28: =IF(I28="",((TODAY()-A28)*G28)/365.24,((I28-A28)*G28)/365.24) -> 1432.4828 | AB28: 阿水一式 | AC28: 破5日線，獲利了結
A29: 45917 | C29: 3042 | D29: =VLOOKUP(C29,每日行情!A:B,2,FALSE) -> 晶技 | E29: 1000 | F29: 92.8 | G29: =E29*F29 -> 92800 | H29: 79 | I29: 45925 | J29: 91.4 | K29: =E29*J29 -> 91400 | L29: 78 | M29: 274 | N29: 0 | O29: =IF(I29="",E29*Y29,0) -> 0 | P29: =IF(I29="",R29-H29,(K29-H29-SUM(L29:N29)+R29-S29-T29)-G29)+(ROUND(R29*V29,0)-ROUND(R29*(1+V29),0)*W29) -> -1831 | Q29: =IF(I29="",(O29-G29-(O29*0.1425%*0.65)-(O29*0.3%)-S29-T29),0) -> 0 | U29: =(V29*50%)/(1+50%*V29) -> 0 | W29: 0.11 | X29: =(P29+Q29)/G29 -> -0.019730603 | Y29: =VLOOKUP(C29,每日行情!A:D,4,FALSE) -> 188 | Z29: =VLOOKUP(C29,每日行情!A:E,5,FALSE) -> -1.5 | AA29: =IF(I29="",((TODAY()-A29)*G29)/365.24,((I29-A29)*G29)/365.24) -> 2032.6361 | AB29: 阿水一式 | AC29: 破5日線，認賠出場
A30: 45917 | C30: 3532 | D30: =VLOOKUP(C30,每日行情!A:B,2,FALSE) -> 台勝科 | E30: 1000 | F30: 95 | G30: =E30*F30 -> 95000 | H30: 81 | I30: 45925 | J30: 106.5 | K30: =E30*J30 -> 106500 | L30: 91 | M30: 319 | N30: 0 | O30: =IF(I30="",E30*Y30,0) -> 0 | P30: =IF(I30="",R30-H30,(K30-H30-SUM(L30:N30)+R30-S30-T30)-G30)+(ROUND(R30*V30,0)-ROUND(R30*(1+V30),0)*W30) -> 11009 | Q30: =IF(I30="",(O30-G30-(O30*0.1425%*0.65)-(O30*0.3%)-S30-T30),0) -> 0 | U30: =(V30*50%)/(1+50%*V30) -> 0 | W30: 0.11 | X30: =(P30+Q30)/G30 -> 0.11588421 | Y30: =VLOOKUP(C30,每日行情!A:D,4,FALSE) -> 417.5 | Z30: =VLOOKUP(C30,每日行情!A:E,5,FALSE) -> 17.5 | AA30: =IF(I30="",((TODAY()-A30)*G30)/365.24,((I30-A30)*G30)/365.24) -> 2080.8236 | AB30: 阿水一式 | AC30: 破5日線，獲利了結
A31: 45925 | C31: 2324 | D31: =VLOOKUP(C31,每日行情!A:B,2,FALSE) -> 仁寶 | E31: 2000 | F31: 37.1 | G31: =E31*F31 -> 74200 | H31: 63 | I31: 45930 | J31: 32.4 | K31: =E31*J31 -> 64800 | L31: 55 | M31: 194 | N31: 0 | O31: =IF(I31="",E31*Y31,0) -> 0 | P31: =IF(I31="",R31-H31,(K31-H31-SUM(L31:N31)+R31-S31-T31)-G31)+(ROUND(R31*V31,0)-ROUND(R31*(1+V31),0)*W31) -> -9712 | Q31: =IF(I31="",(O31-G31-(O31*0.1425%*0.65)-(O31*0.3%)-S31-T31),0) -> 0 | U31: =(V31*50%)/(1+50%*V31) -> 0 | W31: 0.11 | X31: =(P31+Q31)/G31 -> -0.13088949 | Y31: =VLOOKUP(C31,每日行情!A:D,4,FALSE) -> 36.7 | Z31: =VLOOKUP(C31,每日行情!A:E,5,FALSE) -> 0.7 | AA31: =IF(I31="",((TODAY()-A31)*G31)/365.24,((I31-A31)*G31)/365.24) -> 1015.7705 | AB31: 阿水一式 | AC31: 破10日線，認賠出場
A32: 45925 | C32: 6548 | D32: =VLOOKUP(C32,每日行情!A:B,2,FALSE) -> 長科* | E32: 2000 | F32: 35.35 | G32: =E32*F32 -> 70700 | H32: 60 | I32: 45933 | J32: 36 | K32: =E32*J32 -> 72000 | L32: 61 | M32: 216 | N32: 0 | O32: =IF(I32="",E32*Y32,0) -> 0 | P32: =IF(I32="",R32-H32,(K32-H32-SUM(L32:N32)+R32-S32-T32)-G32)+(ROUND(R32*V32,0)-ROUND(R32*(1+V32),0)*W32) -> 963 | Q32: =IF(I32="",(O32-G32-(O32*0.1425%*0.65)-(O32*0.3%)-S32-T32),0) -> 0 | U32: =(V32*50%)/(1+50%*V32) -> 0 | W32: 0.11 | X32: =(P32+Q32)/G32 -> 0.013620934 | Y32: =VLOOKUP(C32,每日行情!A:D,4,FALSE) -> 83.4 | Z32: =VLOOKUP(C32,每日行情!A:E,5,FALSE) -> 1.2 | AA32: =IF(I32="",((TODAY()-A32)*G32)/365.24,((I32-A32)*G32)/365.24) -> 1548.5708 | AB32: 阿水一式 | AC32: 破5日線，獲利了結
A33: 45925 | C33: 2375 | D33: =VLOOKUP(C33,每日行情!A:B,2,FALSE) -> 凱美 | E33: 1000 | F33: 78.8 | G33: =E33*F33 -> 78800 | H33: 67 | I33: 45944 | J33: 76.8 | K33: =E33*J33 -> 76800 | L33: 65 | M33: 230 | N33: 0 | O33: =IF(I33="",E33*Y33,0) -> 0 | P33: =IF(I33="",R33-H33,(K33-H33-SUM(L33:N33)+R33-S33-T33)-G33)+(ROUND(R33*V33,0)-ROUND(R33*(1+V33),0)*W33) -> -2362 | Q33: =IF(I33="",(O33-G33-(O33*0.1425%*0.65)-(O33*0.3%)-S33-T33),0) -> 0 | U33: =(V33*50%)/(1+50%*V33) -> 0 | W33: 0.11 | X33: =(P33+Q33)/G33 -> -0.029974619 | Y33: =VLOOKUP(C33,每日行情!A:D,4,FALSE) -> 125.5 | Z33: =VLOOKUP(C33,每日行情!A:E,5,FALSE) -> -5.5 | AA33: =IF(I33="",((TODAY()-A33)*G33)/365.24,((I33-A33)*G33)/365.24) -> 4099.2224 | AB33: 阿水一式 | AC33: 破10日線，認賠出場
A34: 45925 | C34: 3628 | D34: =VLOOKUP(C34,每日行情!A:B,2,FALSE) -> 盈正 | E34: 1000 | F34: 59.1 | G34: =E34*F34 -> 59100 | H34: 50 | I34: 45939 | J34: 73.5 | K34: =E34*J34 -> 73500 | L34: 62 | M34: 220 | N34: 0 | O34: =IF(I34="",E34*Y34,0) -> 0 | P34: =IF(I34="",R34-H34,(K34-H34-SUM(L34:N34)+R34-S34-T34)-G34)+(ROUND(R34*V34,0)-ROUND(R34*(1+V34),0)*W34) -> 14068 | Q34: =IF(I34="",(O34-G34-(O34*0.1425%*0.65)-(O34*0.3%)-S34-T34),0) -> 0 | U34: =(V34*50%)/(1+50%*V34) -> 0 | W34: 0.11 | X34: =(P34+Q34)/G34 -> 0.23803723 | Y34: =VLOOKUP(C34,每日行情!A:D,4,FALSE) -> 71.5 | Z34: =VLOOKUP(C34,每日行情!A:E,5,FALSE) -> 1.4 | AA34: =IF(I34="",((TODAY()-A34)*G34)/365.24,((I34-A34)*G34)/365.24) -> 2265.3598 | AB34: 阿水一式 | AC34: 破5日線，獲利了結
A35: 45889 | C35: 3661 | D35: =VLOOKUP(C35,每日行情!A:B,2,FALSE) -> 世芯-KY | E35: 10 | F35: 3760 | G35: =E35*F35 -> 37600 | H35: 32 | I35: 45964 | J35: 3460 | K35: =E35*J35 -> 34600 | L35: 30 | M35: 104 | N35: 0 | O35: =IF(I35="",E35*Y35,0) -> 0 | P35: =IF(I35="",R35-H35,(K35-H35-SUM(L35:N35)+R35-S35-T35)-G35)+(ROUND(R35*V35,0)-ROUND(R35*(1+V35),0)*W35) -> -2852.04 | Q35: =IF(I35="",(O35-G35-(O35*0.1425%*0.65)-(O35*0.3%)-S35-T35),0) -> 0 | R35: 364 | S35: 10 | U35: =(V35*50%)/(1+50%*V35) -> 0 | W35: 0.11 | X35: =(P35+Q35)/G35 -> -0.075852128 | Y35: =VLOOKUP(C35,每日行情!A:D,4,FALSE) -> 3685 | Z35: =VLOOKUP(C35,每日行情!A:E,5,FALSE) -> -20 | AA35: =IF(I35="",((TODAY()-A35)*G35)/365.24,((I35-A35)*G35)/365.24) -> 7720.9506 | AB35: 存股 | AC35: 破5日線，認賠出場
A36: 45924 | C36: 3661 | D36: =VLOOKUP(C36,每日行情!A:B,2,FALSE) -> 世芯-KY | E36: 10 | F36: 3420 | G36: =E36*F36 -> 34200 | H36: 29 | I36: 45964 | J36: 3460 | K36: =E36*J36 -> 34600 | L36: 30 | M36: 104 | N36: 0 | O36: =IF(I36="",E36*Y36,0) -> 0 | P36: =IF(I36="",R36-H36,(K36-H36-SUM(L36:N36)+R36-S36-T36)-G36)+(ROUND(R36*V36,0)-ROUND(R36*(1+V36),0)*W36) -> 237 | Q36: =IF(I36="",(O36-G36-(O36*0.1425%*0.65)-(O36*0.3%)-S36-T36),0) -> 0 | U36: =(V36*50%)/(1+50%*V36) -> 0 | W36: 0.11 | X36: =(P36+Q36)/G36 -> 0.0069298246 | Y36: =VLOOKUP(C36,每日行情!A:D,4,FALSE) -> 3685 | Z36: =VLOOKUP(C36,每日行情!A:E,5,FALSE) -> -20 | AA36: =IF(I36="",((TODAY()-A36)*G36)/365.24,((I36-A36)*G36)/365.24) -> 3745.4824 | AB36: 存股 | AC36: 破5日線，獲利了結
A37: 45926 | C37: 3661 | D37: =VLOOKUP(C37,每日行情!A:B,2,FALSE) -> 世芯-KY | E37: 10 | F37: 3260 | G37: =E37*F37 -> 32600 | H37: 27 | I37: 45964 | J37: 3460 | K37: =E37*J37 -> 34600 | L37: 29 | M37: 104 | N37: 0 | O37: =IF(I37="",E37*Y37,0) -> 0 | P37: =IF(I37="",R37-H37,(K37-H37-SUM(L37:N37)+R37-S37-T37)-G37)+(ROUND(R37*V37,0)-ROUND(R37*(1+V37),0)*W37) -> 1840 | Q37: =IF(I37="",(O37-G37-(O37*0.1425%*0.65)-(O37*0.3%)-S37-T37),0) -> 0 | U37: =(V37*50%)/(1+50%*V37) -> 0 | W37: 0.11 | X37: =(P37+Q37)/G37 -> 0.056441718 | Y37: =VLOOKUP(C37,每日行情!A:D,4,FALSE) -> 3685 | Z37: =VLOOKUP(C37,每日行情!A:E,5,FALSE) -> -20 | AA37: =IF(I37="",((TODAY()-A37)*G37)/365.24,((I37-A37)*G37)/365.24) -> 3391.7424 | AB37: 存股 | AC37: 破5日線，獲利了結
A38: 45944 | C38: 3661 | D38: =VLOOKUP(C38,每日行情!A:B,2,FALSE) -> 世芯-KY | E38: 10 | F38: 3170 | G38: =E38*F38 -> 31700 | H38: 27 | I38: 45964 | J38: 3460 | K38: =E38*J38 -> 34600 | L38: 29 | M38: 103 | N38: 0 | O38: =IF(I38="",E38*Y38,0) -> 0 | P38: =IF(I38="",R38-H38,(K38-H38-SUM(L38:N38)+R38-S38-T38)-G38)+(ROUND(R38*V38,0)-ROUND(R38*(1+V38),0)*W38) -> 2741 | Q38: =IF(I38="",(O38-G38-(O38*0.1425%*0.65)-(O38*0.3%)-S38-T38),0) -> 0 | U38: =(V38*50%)/(1+50%*V38) -> 0 | W38: 0.11 | X38: =(P38+Q38)/G38 -> 0.086466877 | Y38: =VLOOKUP(C38,每日行情!A:D,4,FALSE) -> 3685 | Z38: =VLOOKUP(C38,每日行情!A:E,5,FALSE) -> -20 | AA38: =IF(I38="",((TODAY()-A38)*G38)/365.24,((I38-A38)*G38)/365.24) -> 1735.8449 | AB38: 存股 | AC38: 破5日線，獲利了結
A39: 46043 | C39: 50 | D39: =VLOOKUP(C39,每日行情!A:B,2,FALSE) -> 元大台灣50 | E39: 2000 | F39: 72.45 | G39: =E39*F39 -> 144900 | H39: 123 | I39: 46050 | J39: 74 | K39: =E39*J39 -> 148000 | L39: 126 | M39: 148 | N39: 0 | O39: =IF(I39="",E39*Y39,0) -> 0 | P39: =IF(I39="",R39-H39,(K39-H39-SUM(L39:N39)+R39-S39-T39)-G39)+(ROUND(R39*V39,0)-ROUND(R39*(1+V39),0)*W39) -> 4473 | Q39: =IF(I39="",(O39-G39-(O39*0.1425%*0.65)-(O39*0.3%)-S39-T39),0) -> 0 | R39: 2000 | S39: 10 | U39: =(V39*50%)/(1+50%*V39) -> 0 | W39: 0.11 | X39: =(P39+Q39)/G39 -> 0.030869565 | Y39: =VLOOKUP(C39,每日行情!A:D,4,FALSE) -> 109 | Z39: =VLOOKUP(C39,每日行情!A:E,5,FALSE) -> 0.1 | AA39: =IF(I39="",((TODAY()-A39)*G39)/365.24,((I39-A39)*G39)/365.24) -> 2777.0781 | AB39: 除權息 | AC39: 已填息
A40: 45901 | C40: 56 | D40: =VLOOKUP(C40,每日行情!A:B,2,FALSE) -> 元大高股息 | E40: 285 | F40: 34.69 | G40: 9886 | H40: 1 | I40: 46051 | J40: 38.23 | K40: =E40*J40 -> 10895.55 | L40: 32 | M40: 38 | N40: 0 | O40: =IF(I40="",E40*Y40,0) -> 0 | P40: =IF(I40="",R40-H40,(K40-H40-SUM(L40:N40)+R40-S40-T40)-G40)+(ROUND(R40*V40,0)-ROUND(R40*(1+V40),0)*W40) -> 1223.14 | Q40: =IF(I40="",(O40-G40-(O40*0.1425%*0.65)-(O40*0.3%)-S40-T40),0) -> 0 | R40: 331 | S40: 10 | U40: =(V40*50%)/(1+50%*V40) -> 0 | W40: 0.11 | X40: =(P40+Q40)/G40 -> 0.12372446 | Y40: =VLOOKUP(C40,每日行情!A:D,4,FALSE) -> 58.75 | Z40: =VLOOKUP(C40,每日行情!A:E,5,FALSE) -> 0.5 | AA40: =IF(I40="",((TODAY()-A40)*G40)/365.24,((I40-A40)*G40)/365.24) -> 4060.0701 | AB40: 存股 | AC40: 獲利了結，轉換標的 | AD40: 元大-台股定期定額
A41: 45931 | C41: 56 | D41: =VLOOKUP(C41,每日行情!A:B,2,FALSE) -> 元大高股息 | E41: 268 | F41: 36.89 | G41: 9886 | H41: 1 | I41: 46051 | J41: 38.23 | K41: =E41*J41 -> 10245.64 | L41: 11 | M41: 13 | N41: 0 | O41: =IF(I41="",E41*Y41,0) -> 0 | P41: =IF(I41="",R41-H41,(K41-H41-SUM(L41:N41)+R41-S41-T41)-G41)+(ROUND(R41*V41,0)-ROUND(R41*(1+V41),0)*W41) -> 618.34 | Q41: =IF(I41="",(O41-G41-(O41*0.1425%*0.65)-(O41*0.3%)-S41-T41),0) -> 0 | R41: 330 | S41: 10 | U41: =(V41*50%)/(1+50%*V41) -> 0 | W41: 0.11 | X41: =(P41+Q41)/G41 -> 0.062547036 | Y41: =VLOOKUP(C41,每日行情!A:D,4,FALSE) -> 58.75 | Z41: =VLOOKUP(C41,每日行情!A:E,5,FALSE) -> 0.5 | AA41: =IF(I41="",((TODAY()-A41)*G41)/365.24,((I41-A41)*G41)/365.24) -> 3248.0561 | AB41: 存股 | AC41: 獲利了結，轉換標的 | AD41: 元大-台股定期定額
A42: 45964 | C42: 56 | D42: =VLOOKUP(C42,每日行情!A:B,2,FALSE) -> 元大高股息 | E42: 264 | F42: 37.35 | G42: 9860 | H42: 1 | I42: 46051 | J42: 38.23 | K42: =E42*J42 -> 10092.72 | N42: 0 | O42: =IF(I42="",E42*Y42,0) -> 0 | P42: =IF(I42="",R42-H42,(K42-H42-SUM(L42:N42)+R42-S42-T42)-G42)+(ROUND(R42*V42,0)-ROUND(R42*(1+V42),0)*W42) -> 515.42 | Q42: =IF(I42="",(O42-G42-(O42*0.1425%*0.65)-(O42*0.3%)-S42-T42),0) -> 0 | R42: 330 | S42: 10 | U42: =(V42*50%)/(1+50%*V42) -> 0 | W42: 0.11 | X42: =(P42+Q42)/G42 -> 0.052273834 | Y42: =VLOOKUP(C42,每日行情!A:D,4,FALSE) -> 58.75 | Z42: =VLOOKUP(C42,每日行情!A:E,5,FALSE) -> 0.5 | AA42: =IF(I42="",((TODAY()-A42)*G42)/365.24,((I42-A42)*G42)/365.24) -> 2348.6475 | AB42: 存股 | AC42: 獲利了結，轉換標的 | AD42: 元大-台股定期定額
A43: 45992 | C43: 56 | D43: =VLOOKUP(C43,每日行情!A:B,2,FALSE) -> 元大高股息 | E43: 275 | F43: 36.03 | G43: 9908 | H43: 1 | I43: 46051 | J43: 38.23 | K43: =E43*J43 -> 10513.25 | N43: 0 | O43: =IF(I43="",E43*Y43,0) -> 0 | P43: =IF(I43="",R43-H43,(K43-H43-SUM(L43:N43)+R43-S43-T43)-G43)+(ROUND(R43*V43,0)-ROUND(R43*(1+V43),0)*W43) -> 887.95 | Q43: =IF(I43="",(O43-G43-(O43*0.1425%*0.65)-(O43*0.3%)-S43-T43),0) -> 0 | R43: 330 | S43: 10 | U43: =(V43*50%)/(1+50%*V43) -> 0 | W43: 0.11 | X43: =(P43+Q43)/G43 -> 0.089619499 | Y43: =VLOOKUP(C43,每日行情!A:D,4,FALSE) -> 58.75 | Z43: =VLOOKUP(C43,每日行情!A:E,5,FALSE) -> 0.5 | AA43: =IF(I43="",((TODAY()-A43)*G43)/365.24,((I43-A43)*G43)/365.24) -> 1600.5147 | AB43: 存股 | AC43: 獲利了結，轉換標的 | AD43: 元大-台股定期定額
A44: 46024 | C44: 56 | D44: =VLOOKUP(C44,每日行情!A:B,2,FALSE) -> 元大高股息 | E44: 267 | F44: 37.02 | G44: 9884 | H44: 1 | I44: 46051 | J44: 38.23 | K44: =E44*J44 -> 10207.41 | N44: 0 | O44: =IF(I44="",E44*Y44,0) -> 0 | P44: =IF(I44="",R44-H44,(K44-H44-SUM(L44:N44)+R44-S44-T44)-G44)+(ROUND(R44*V44,0)-ROUND(R44*(1+V44),0)*W44) -> 606.11 | Q44: =IF(I44="",(O44-G44-(O44*0.1425%*0.65)-(O44*0.3%)-S44-T44),0) -> 0 | R44: 330 | S44: 10 | U44: =(V44*50%)/(1+50%*V44) -> 0 | W44: 0.11 | X44: =(P44+Q44)/G44 -> 0.061322339 | Y44: =VLOOKUP(C44,每日行情!A:D,4,FALSE) -> 58.75 | Z44: =VLOOKUP(C44,每日行情!A:E,5,FALSE) -> 0.5 | AA44: =IF(I44="",((TODAY()-A44)*G44)/365.24,((I44-A44)*G44)/365.24) -> 730.66477 | AB44: 存股 | AC44: 獲利了結，轉換標的 | AD44: 元大-台股定期定額
A45: 45908 | C45: 770 | D45: =VLOOKUP(C45,每日行情!A:B,2,FALSE) -> 國泰北美科技 | E45: 192 | F45: 51.02 | G45: 9795 | H45: 1 | I45: 46090 | J45: 50.05 | K45: =E45*J45 -> 9609.6 | L45: 8 | M45: 10 | N45: 0 | O45: =IF(I45="",E45*Y45,0) -> 0 | P45: =IF(I45="",R45-H45,(K45-H45-SUM(L45:N45)+R45-S45-T45)-G45)+(ROUND(R45*V45,0)-ROUND(R45*(1+V45),0)*W45) -> 446.87 | Q45: =IF(I45="",(O45-G45-(O45*0.1425%*0.65)-(O45*0.3%)-S45-T45),0) -> 0 | R45: 743 | S45: 10 | U45: =(V45*50%)/(1+50%*V45) -> 0 | W45: 0.11 | X45: =(P45+Q45)/G45 -> 0.045622256 | Y45: =VLOOKUP(C45,每日行情!A:D,4,FALSE) -> 64.95 | Z45: =VLOOKUP(C45,每日行情!A:E,5,FALSE) -> 0.6 | AA45: =IF(I45="",((TODAY()-A45)*G45)/365.24,((I45-A45)*G45)/365.24) -> 4880.8729 | AB45: 存股 | AC45: 美伊戰爭，憂心崩跌，獲利了結 | AD45: 元大-台股定期定額
A46: 45937 | C46: 770 | D46: =VLOOKUP(C46,每日行情!A:B,2,FALSE) -> 國泰北美科技 | E46: 179 | F46: 54.96 | G46: 9837 | H46: 1 | I46: 46090 | J46: 50.05 | K46: =E46*J46 -> 8958.95 | L46: 8 | M46: 10 | N46: 0 | O46: =IF(I46="",E46*Y46,0) -> 0 | P46: =IF(I46="",R46-H46,(K46-H46-SUM(L46:N46)+R46-S46-T46)-G46)+(ROUND(R46*V46,0)-ROUND(R46*(1+V46),0)*W46) -> -246.67 | Q46: =IF(I46="",(O46-G46-(O46*0.1425%*0.65)-(O46*0.3%)-S46-T46),0) -> 0 | R46: 742 | S46: 10 | U46: =(V46*50%)/(1+50%*V46) -> 0 | W46: 0.11 | X46: =(P46+Q46)/G46 -> -0.025075734 | Y46: =VLOOKUP(C46,每日行情!A:D,4,FALSE) -> 64.95 | Z46: =VLOOKUP(C46,每日行情!A:E,5,FALSE) -> 0.6 | AA46: =IF(I46="",((TODAY()-A46)*G46)/365.24,((I46-A46)*G46)/365.24) -> 4120.7453 | AB46: 存股 | AC46: 美伊戰爭，憂心崩跌，認賠出場 | AD46: 元大-台股定期定額
A47: 45967 | C47: 770 | D47: =VLOOKUP(C47,每日行情!A:B,2,FALSE) -> 國泰北美科技 | E47: 173 | F47: 57.55 | G47: 9956 | H47: 1 | I47: 46090 | J47: 50.05 | K47: =E47*J47 -> 8658.65 | L47: 8 | M47: 10 | N47: 0 | O47: =IF(I47="",E47*Y47,0) -> 0 | P47: =IF(I47="",R47-H47,(K47-H47-SUM(L47:N47)+R47-S47-T47)-G47)+(ROUND(R47*V47,0)-ROUND(R47*(1+V47),0)*W47) -> -665.97 | Q47: =IF(I47="",(O47-G47-(O47*0.1425%*0.65)-(O47*0.3%)-S47-T47),0) -> 0 | R47: 742 | S47: 10 | U47: =(V47*50%)/(1+50%*V47) -> 0 | W47: 0.11 | X47: =(P47+Q47)/G47 -> -0.066891322 | Y47: =VLOOKUP(C47,每日行情!A:D,4,FALSE) -> 64.95 | Z47: =VLOOKUP(C47,每日行情!A:E,5,FALSE) -> 0.6 | AA47: =IF(I47="",((TODAY()-A47)*G47)/365.24,((I47-A47)*G47)/365.24) -> 3352.831 | AB47: 存股 | AC47: 美伊戰爭，憂心崩跌，認賠出場 | AD47: 元大-台股定期定額
A48: 45999 | C48: 770 | D48: =VLOOKUP(C48,每日行情!A:B,2,FALSE) -> 國泰北美科技 | E48: 170 | F48: 58.65 | G48: 9970 | H48: 1 | I48: 46090 | J48: 50.05 | K48: =E48*J48 -> 8508.5 | L48: 9 | M48: 10 | N48: 0 | O48: =IF(I48="",E48*Y48,0) -> 0 | P48: =IF(I48="",R48-H48,(K48-H48-SUM(L48:N48)+R48-S48-T48)-G48)+(ROUND(R48*V48,0)-ROUND(R48*(1+V48),0)*W48) -> -831.12 | Q48: =IF(I48="",(O48-G48-(O48*0.1425%*0.65)-(O48*0.3%)-S48-T48),0) -> 0 | R48: 742 | S48: 10 | U48: =(V48*50%)/(1+50%*V48) -> 0 | W48: 0.11 | X48: =(P48+Q48)/G48 -> -0.083362086 | Y48: =VLOOKUP(C48,每日行情!A:D,4,FALSE) -> 64.95 | Z48: =VLOOKUP(C48,每日行情!A:E,5,FALSE) -> 0.6 | AA48: =IF(I48="",((TODAY()-A48)*G48)/365.24,((I48-A48)*G48)/365.24) -> 2484.0379 | AB48: 存股 | AC48: 美伊戰爭，憂心崩跌，認賠出場 | AD48: 元大-台股定期定額
A49: 46028 | C49: 770 | D49: =VLOOKUP(C49,每日行情!A:B,2,FALSE) -> 國泰北美科技 | E49: 170 | F49: 58.18 | G49: 9890 | H49: 1 | I49: 46090 | J49: 50.05 | K49: =E49*J49 -> 8508.5 | L49: 9 | M49: 10 | N49: 0 | O49: =IF(I49="",E49*Y49,0) -> 0 | P49: =IF(I49="",R49-H49,(K49-H49-SUM(L49:N49)+R49-S49-T49)-G49)+(ROUND(R49*V49,0)-ROUND(R49*(1+V49),0)*W49) -> -751.12 | Q49: =IF(I49="",(O49-G49-(O49*0.1425%*0.65)-(O49*0.3%)-S49-T49),0) -> 0 | R49: 742 | S49: 10 | U49: =(V49*50%)/(1+50%*V49) -> 0 | W49: 0.11 | X49: =(P49+Q49)/G49 -> -0.075947422 | Y49: =VLOOKUP(C49,每日行情!A:D,4,FALSE) -> 64.95 | Z49: =VLOOKUP(C49,每日行情!A:E,5,FALSE) -> 0.6 | AA49: =IF(I49="",((TODAY()-A49)*G49)/365.24,((I49-A49)*G49)/365.24) -> 1678.8413 | AB49: 存股 | AC49: 美伊戰爭，憂心崩跌，認賠出場 | AD49: 元大-台股定期定額
A50: 46059 | C50: 770 | D50: =VLOOKUP(C50,每日行情!A:B,2,FALSE) -> 國泰北美科技 | E50: 194 | F50: 50.71 | G50: 9837 | H50: 1 | I50: 46090 | J50: 50.2 | K50: =E50*J50 -> 9738.8 | L50: 3 | M50: 3 | N50: 0 | O50: =IF(I50="",E50*Y50,0) -> 0 | P50: =IF(I50="",R50-H50,(K50-H50-SUM(L50:N50)+R50-S50-T50)-G50)+(ROUND(R50*V50,0)-ROUND(R50*(1+V50),0)*W50) -> -105.2 | Q50: =IF(I50="",(O50-G50-(O50*0.1425%*0.65)-(O50*0.3%)-S50-T50),0) -> 0 | U50: =(V50*50%)/(1+50%*V50) -> 0 | W50: 0.11 | X50: =(P50+Q50)/G50 -> -0.010694317 | Y50: =VLOOKUP(C50,每日行情!A:D,4,FALSE) -> 64.95 | Z50: =VLOOKUP(C50,每日行情!A:E,5,FALSE) -> 0.6 | AA50: =IF(I50="",((TODAY()-A50)*G50)/365.24,((I50-A50)*G50)/365.24) -> 834.92224 | AB50: 存股 | AC50: 美伊戰爭，憂心崩跌，認賠出場 | AD50: 元大-台股定期定額
A51: 46051 | C51: 3163 | D51: =VLOOKUP(C51,每日行情!A:B,2,FALSE) -> 波若威 | E51: 1000 | F51: 486 | G51: =E51*F51 -> 486000 | H51: 415 | I51: 46090 | J51: 654 | K51: =E51*J51 -> 654000 | L51: 559 | M51: 1962 | N51: 0 | O51: =IF(I51="",E51*Y51,0) -> 0 | P51: =IF(I51="",R51-H51,(K51-H51-SUM(L51:N51)+R51-S51-T51)-G51)+(ROUND(R51*V51,0)-ROUND(R51*(1+V51),0)*W51) -> 165064 | Q51: =IF(I51="",(O51-G51-(O51*0.1425%*0.65)-(O51*0.3%)-S51-T51),0) -> 0 | U51: =(V51*50%)/(1+50%*V51) -> 0 | W51: 0.11 | X51: =(P51+Q51)/G51 -> 0.33963786 | Y51: =VLOOKUP(C51,每日行情!A:D,4,FALSE) -> 589 | Z51: =VLOOKUP(C51,每日行情!A:E,5,FALSE) -> -15 | AA51: =IF(I51="",((TODAY()-A51)*G51)/365.24,((I51-A51)*G51)/365.24) -> 51894.645 | AB51: 矽光子族群 | AC51: 美伊戰爭，憂心崩跌，獲利了結
A52: 46051 | C52: 8299 | D52: =VLOOKUP(C52,每日行情!A:B,2,FALSE) -> 群聯 | E52: 50 | F52: 2270 | G52: =E52*F52 -> 113500 | H52: 97 | I52: 46090 | J52: 1600 | K52: =E52*J52 -> 80000 | L52: 81 | M52: 300 | N52: 0 | O52: =IF(I52="",E52*Y52,0) -> 0 | P52: =IF(I52="",R52-H52,(K52-H52-SUM(L52:N52)+R52-S52-T52)-G52)+(ROUND(R52*V52,0)-ROUND(R52*(1+V52),0)*W52) -> -33978 | Q52: =IF(I52="",(O52-G52-(O52*0.1425%*0.65)-(O52*0.3%)-S52-T52),0) -> 0 | U52: =(V52*50%)/(1+50%*V52) -> 0 | W52: 0.11 | X52: =(P52+Q52)/G52 -> -0.29936564 | Y52: =VLOOKUP(C52,每日行情!A:D,4,FALSE) -> 1890 | Z52: =VLOOKUP(C52,每日行情!A:E,5,FALSE) -> 60 | AA52: =IF(I52="",((TODAY()-A52)*G52)/365.24,((I52-A52)*G52)/365.24) -> 12119.428 | AB52: 記憶體族群 | AC52: 美伊戰爭，憂心崩跌，認賠出場
A53: 46064 | C53: 8299 | D53: =VLOOKUP(C53,每日行情!A:B,2,FALSE) -> 群聯 | E53: 20 | F53: 1860 | G53: =E53*F53 -> 37200 | H53: 31 | I53: 46090 | J53: 1600 | K53: =E53*J53 -> 32000 | L53: 14 | M53: 36 | N53: 0 | O53: =IF(I53="",E53*Y53,0) -> 0 | P53: =IF(I53="",R53-H53,(K53-H53-SUM(L53:N53)+R53-S53-T53)-G53)+(ROUND(R53*V53,0)-ROUND(R53*(1+V53),0)*W53) -> -5281 | Q53: =IF(I53="",(O53-G53-(O53*0.1425%*0.65)-(O53*0.3%)-S53-T53),0) -> 0 | U53: =(V53*50%)/(1+50%*V53) -> 0 | W53: 0.11 | X53: =(P53+Q53)/G53 -> -0.14196237 | Y53: =VLOOKUP(C53,每日行情!A:D,4,FALSE) -> 1890 | Z53: =VLOOKUP(C53,每日行情!A:E,5,FALSE) -> 60 | AA53: =IF(I53="",((TODAY()-A53)*G53)/365.24,((I53-A53)*G53)/365.24) -> 2648.1218 | AB53: 記憶體族群 | AC53: 美伊戰爭，憂心崩跌，認賠出場
A54: 46126 | C54: 56 | D54: =VLOOKUP(C54,每日行情!A:B,2,FALSE) -> 元大高股息 | E54: 2000 | F54: 39.98 | G54: =E54*F54 -> 79960 | H54: 68 | I54: 46134 | J54: 42.3 | K54: =E54*J54 -> 84600 | L54: 72 | M54: 84 | O54: =IF(I54="",E54*Y54,0) -> 0 | P54: =IF(I54="",R54-H54,(K54-H54-SUM(L54:N54)+R54-S54-T54)-G54)+(ROUND(R54*V54,0)-ROUND(R54*(1+V54),0)*W54) -> 4416 | Q54: =IF(I54="",(O54-G54-(O54*0.1425%*0.65)-(O54*0.3%)-S54-T54),0) -> 0 | U54: =(V54*50%)/(1+50%*V54) -> 0 | W54: 0.11 | X54: =(P54+Q54)/G54 -> 0.055227614 | Y54: =VLOOKUP(C54,每日行情!A:D,4,FALSE) -> 58.75 | Z54: =VLOOKUP(C54,每日行情!A:E,5,FALSE) -> 0.5 | AA54: =IF(I54="",((TODAY()-A54)*G54)/365.24,((I54-A54)*G54)/365.24) -> 1751.3963 | AB54: 除權息 | AC54: 除息前，獲利了結
A55: 46126 | C55: 900 | D55: =VLOOKUP(C55,每日行情!A:B,2,FALSE) -> 富邦特選高股息30 | E55: 1000 | F55: 14.72 | G55: =E55*F55 -> 14720 | H55: 20 | I55: 46128 | J55: 15.05 | K55: =E55*J55 -> 15050 | L55: 13 | M55: 15 | O55: =IF(I55="",E55*Y55,0) -> 0 | P55: =IF(I55="",R55-H55,(K55-H55-SUM(L55:N55)+R55-S55-T55)-G55)+(ROUND(R55*V55,0)-ROUND(R55*(1+V55),0)*W55) -> 282 | Q55: =IF(I55="",(O55-G55-(O55*0.1425%*0.65)-(O55*0.3%)-S55-T55),0) -> 0 | U55: =(V55*50%)/(1+50%*V55) -> 0 | W55: 0.11 | X55: =(P55+Q55)/G55 -> 0.019157609 | Y55: =VLOOKUP(C55,每日行情!A:D,4,FALSE) -> 19.9 | Z55: =VLOOKUP(C55,每日行情!A:E,5,FALSE) -> 0.06 | AA55: =IF(I55="",((TODAY()-A55)*G55)/365.24,((I55-A55)*G55)/365.24) -> 80.604534 | AB55: 除權息 | AC55: 除息前，獲利了結
A56: 46126 | C56: 900 | D56: =VLOOKUP(C56,每日行情!A:B,2,FALSE) -> 富邦特選高股息30 | E56: 1000 | F56: 14.73 | G56: =E56*F56 -> 14730 | H56: 20 | I56: 46128 | J56: 15.05 | K56: =E56*J56 -> 15050 | L56: 13 | M56: 15 | O56: =IF(I56="",E56*Y56,0) -> 0 | P56: =IF(I56="",R56-H56,(K56-H56-SUM(L56:N56)+R56-S56-T56)-G56)+(ROUND(R56*V56,0)-ROUND(R56*(1+V56),0)*W56) -> 272 | Q56: =IF(I56="",(O56-G56-(O56*0.1425%*0.65)-(O56*0.3%)-S56-T56),0) -> 0 | U56: =(V56*50%)/(1+50%*V56) -> 0 | W56: 0.11 | X56: =(P56+Q56)/G56 -> 0.018465716 | Y56: =VLOOKUP(C56,每日行情!A:D,4,FALSE) -> 19.9 | Z56: =VLOOKUP(C56,每日行情!A:E,5,FALSE) -> 0.06 | AA56: =IF(I56="",((TODAY()-A56)*G56)/365.24,((I56-A56)*G56)/365.24) -> 80.659293 | AB56: 除權息 | AC56: 除息前，獲利了結
A57: 46126 | C57: 934 | D57: =VLOOKUP(C57,每日行情!A:B,2,FALSE) -> 中信成長高股息 | E57: 1000 | F57: 22.36 | G57: =E57*F57 -> 22360 | H57: 20 | I57: 46128 | J57: 22.92 | K57: =E57*J57 -> 22920 | L57: 20 | M57: 22 | O57: =IF(I57="",E57*Y57,0) -> 0 | P57: =IF(I57="",R57-H57,(K57-H57-SUM(L57:N57)+R57-S57-T57)-G57)+(ROUND(R57*V57,0)-ROUND(R57*(1+V57),0)*W57) -> 498 | Q57: =IF(I57="",(O57-G57-(O57*0.1425%*0.65)-(O57*0.3%)-S57-T57),0) -> 0 | U57: =(V57*50%)/(1+50%*V57) -> 0 | W57: 0.11 | X57: =(P57+Q57)/G57 -> 0.022271914 | Y57: =VLOOKUP(C57,每日行情!A:D,4,FALSE) -> 30.31 | Z57: =VLOOKUP(C57,每日行情!A:E,5,FALSE) -> 0.3 | AA57: =IF(I57="",((TODAY()-A57)*G57)/365.24,((I57-A57)*G57)/365.24) -> 122.44004 | AB57: 除權息 | AC57: 除息前，獲利了結
A58: 46126 | C58: 936 | D58: =VLOOKUP(C58,每日行情!A:B,2,FALSE) -> 台新永續高息中小 | E58: 1000 | F58: 18.04 | G58: =E58*F58 -> 18040 | H58: 20 | I58: 46128 | J58: 18.37 | K58: =E58*J58 -> 18370 | L58: 20 | M58: 18 | O58: =IF(I58="",E58*Y58,0) -> 0 | P58: =IF(I58="",R58-H58,(K58-H58-SUM(L58:N58)+R58-S58-T58)-G58)+(ROUND(R58*V58,0)-ROUND(R58*(1+V58),0)*W58) -> 272 | Q58: =IF(I58="",(O58-G58-(O58*0.1425%*0.65)-(O58*0.3%)-S58-T58),0) -> 0 | U58: =(V58*50%)/(1+50%*V58) -> 0 | W58: 0.11 | X58: =(P58+Q58)/G58 -> 0.015077605 | Y58: =VLOOKUP(C58,每日行情!A:D,4,FALSE) -> 21.52 | Z58: =VLOOKUP(C58,每日行情!A:E,5,FALSE) -> 0.17 | AA58: =IF(I58="",((TODAY()-A58)*G58)/365.24,((I58-A58)*G58)/365.24) -> 98.784361 | AB58: 除權息 | AC58: 除息前，獲利了結
A59: 46126 | C59: 944 | D59: =VLOOKUP(C59,每日行情!A:B,2,FALSE) -> 野村趨勢動能高息 | E59: 1000 | F59: 16.4 | G59: =E59*F59 -> 16400 | H59: 20 | I59: 46128 | J59: 16.98 | K59: =E59*J59 -> 16980 | L59: 20 | M59: 16 | O59: =IF(I59="",E59*Y59,0) -> 0 | P59: =IF(I59="",R59-H59,(K59-H59-SUM(L59:N59)+R59-S59-T59)-G59)+(ROUND(R59*V59,0)-ROUND(R59*(1+V59),0)*W59) -> 524 | Q59: =IF(I59="",(O59-G59-(O59*0.1425%*0.65)-(O59*0.3%)-S59-T59),0) -> 0 | U59: =(V59*50%)/(1+50%*V59) -> 0 | W59: 0.11 | X59: =(P59+Q59)/G59 -> 0.03195122 | Y59: =VLOOKUP(C59,每日行情!A:D,4,FALSE) -> 22.65 | Z59: =VLOOKUP(C59,每日行情!A:E,5,FALSE) -> 0.13 | AA59: =IF(I59="",((TODAY()-A59)*G59)/365.24,((I59-A59)*G59)/365.24) -> 89.803965 | AB59: 除權息 | AC59: 除息前，獲利了結
A60: 46090 | C60: 2609 | D60: =VLOOKUP(C60,每日行情!A:B,2,FALSE) -> 陽明 | E60: 1000 | F60: 61.09 | G60: =E60*F60 -> 61090 | H60: 52 | I60: 46153 | J60: 50.3 | K60: =E60*J60 -> 50300 | L60: 43 | M60: 150 | O60: =IF(I60="",E60*Y60,0) -> 0 | P60: =IF(I60="",R60-H60,(K60-H60-SUM(L60:N60)+R60-S60-T60)-G60)+(ROUND(R60*V60,0)-ROUND(R60*(1+V60),0)*W60) -> -11035 | Q60: =IF(I60="",(O60-G60-(O60*0.1425%*0.65)-(O60*0.3%)-S60-T60),0) -> 0 | U60: =(V60*50%)/(1+50%*V60) -> 0 | W60: 0.11 | X60: =(P60+Q60)/G60 -> -0.18063513 | Y60: =VLOOKUP(C60,每日行情!A:D,4,FALSE) -> 64.7 | Z60: =VLOOKUP(C60,每日行情!A:E,5,FALSE) -> 1.4 | AA60: =IF(I60="",((TODAY()-A60)*G60)/365.24,((I60-A60)*G60)/365.24) -> 10537.373 | AB60: 美伊戰爭 | AC60: 美伊戰爭
A61: 46149 | C61: 4938 | D61: =VLOOKUP(C61,每日行情!A:B,2,FALSE) -> 和碩 | E61: 1000 | F61: 83.9 | G61: =E61*F61 -> 83900 | H61: 71 | I61: 46156 | J61: 76.7 | K61: =E61*J61 -> 76700 | L61: 65 | M61: =ROUND(J61*E61*0.3%,0) -> 230 | O61: =IF(I61="",E61*Y61,0) -> 0 | P61: =IF(I61="",R61-H61,(K61-H61-SUM(L61:N61)+R61-S61-T61)-G61)+(ROUND(R61*V61,0)-ROUND(R61*(1+V61),0)*W61) -> -7566 | Q61: =IF(I61="",(O61-G61-(O61*0.1425%*0.65)-(O61*0.3%)-S61-T61),0) -> 0 | U61: =(V61*50%)/(1+50%*V61) -> 0 | W61: 0.11 | X61: =(P61+Q61)/G61 -> -0.090178784 | Y61: =VLOOKUP(C61,每日行情!A:D,4,FALSE) -> 102 | Z61: =VLOOKUP(C61,每日行情!A:E,5,FALSE) -> 3.9 | AA61: =IF(I61="",((TODAY()-A61)*G61)/365.24,((I61-A61)*G61)/365.24) -> 1607.9838 | AB61: 賭新聞 | AC61: 新聞沒發生，認賠出場
A62: 46157 | C62: 944 | D62: =VLOOKUP(C62,每日行情!A:B,2,FALSE) -> 野村趨勢動能高息 | E62: 1000 | F62: 18.83 | G62: =E62*F62 -> 18830 | H62: 20 | I62: 46169 | J62: 19.57 | K62: =E62*J62 -> 19570 | L62: 20 | M62: 19 | O62: =IF(I62="",E62*Y62,0) -> 0 | P62: =IF(I62="",R62-H62,(K62-H62-SUM(L62:N62)+R62-S62-T62)-G62)+(ROUND(R62*V62,0)-ROUND(R62*(1+V62),0)*W62) -> 1268.4 | Q62: =IF(I62="",(O62-G62-(O62*0.1425%*0.65)-(O62*0.3%)-S62-T62),0) -> 0 | R62: 660 | U62: =(V62*50%)/(1+50%*V62) -> 0 | W62: 0.11 | X62: =(P62+Q62)/G62 -> 0.067360595 | Y62: =VLOOKUP(C62,每日行情!A:D,4,FALSE) -> 22.65 | Z62: =VLOOKUP(C62,每日行情!A:E,5,FALSE) -> 0.13 | AA62: =IF(I62="",((TODAY()-A62)*G62)/365.24,((I62-A62)*G62)/365.24) -> 618.6617 | AB62: 除權息
A63: 46157 | C63: 934 | D63: =VLOOKUP(C63,每日行情!A:B,2,FALSE) -> 中信成長高股息 | E63: 1000 | F63: 25.39 | G63: =E63*F63 -> 25390 | H63: 21 | I63: 46169 | J63: 26.92 | K63: =E63*J63 -> 26920 | L63: 23 | M63: 26 | O63: =IF(I63="",E63*Y63,0) -> 0 | P63: =IF(I63="",R63-H63,(K63-H63-SUM(L63:N63)+R63-S63-T63)-G63)+(ROUND(R63*V63,0)-ROUND(R63*(1+V63),0)*W63) -> 1682.5 | Q63: =IF(I63="",(O63-G63-(O63*0.1425%*0.65)-(O63*0.3%)-S63-T63),0) -> 0 | R63: 250 | U63: =(V63*50%)/(1+50%*V63) -> 0 | W63: 0.11 | X63: =(P63+Q63)/G63 -> 0.066266247 | Y63: =VLOOKUP(C63,每日行情!A:D,4,FALSE) -> 30.31 | Z63: =VLOOKUP(C63,每日行情!A:E,5,FALSE) -> 0.3 | AA63: =IF(I63="",((TODAY()-A63)*G63)/365.24,((I63-A63)*G63)/365.24) -> 834.19122 | AB63: 除權息
A64: 46157 | C64: 878 | D64: =VLOOKUP(C64,每日行情!A:B,2,FALSE) -> 國泰永續高股息 | E64: 1000 | F64: 28.2 | G64: =E64*F64 -> 28200 | H64: 24 | I64: 46169 | J64: 29.7 | K64: =E64*J64 -> 29700 | L64: 25 | M64: 29 | O64: =IF(I64="",E64*Y64,0) -> 0 | P64: =IF(I64="",R64-H64,(K64-H64-SUM(L64:N64)+R64-S64-T64)-G64)+(ROUND(R64*V64,0)-ROUND(R64*(1+V64),0)*W64) -> 1470.06 | Q64: =IF(I64="",(O64-G64-(O64*0.1425%*0.65)-(O64*0.3%)-S64-T64),0) -> 0 | R64: 54 | U64: =(V64*50%)/(1+50%*V64) -> 0 | W64: 0.11 | X64: =(P64+Q64)/G64 -> 0.052129787 | Y64: =VLOOKUP(C64,每日行情!A:D,4,FALSE) -> 35.53 | Z64: =VLOOKUP(C64,每日行情!A:E,5,FALSE) -> 0.44 | AA64: =IF(I64="",((TODAY()-A64)*G64)/365.24,((I64-A64)*G64)/365.24) -> 926.51407 | AB64: 除權息
A65: 46170 | C65: 00631L | D65: =VLOOKUP(C65,每日行情!A:B,2,FALSE) -> 元大台灣50正2 | E65: 1000 | F65: 34.36 | G65: =E65*F65 -> 34360 | H65: 29 | I65: 46189 | J65: 37.6 | K65: =E65*J65 -> 37600 | L65: 32 | M65: 37 | O65: =IF(I65="",E65*Y65,0) -> 0 | P65: =IF(I65="",R65-H65,(K65-H65-SUM(L65:N65)+R65-S65-T65)-G65)+(ROUND(R65*V65,0)-ROUND(R65*(1+V65),0)*W65) -> 3142 | Q65: =IF(I65="",(O65-G65-(O65*0.1425%*0.65)-(O65*0.3%)-S65-T65),0) -> 0 | U65: =(V65*50%)/(1+50%*V65) -> 0 | W65: 0.11 | X65: =(P65+Q65)/G65 -> 0.091443539 | Y65: =VLOOKUP(C65,每日行情!A:D,4,FALSE) -> 37.15 | Z65: =VLOOKUP(C65,每日行情!A:E,5,FALSE) -> 0.01 | AA65: =IF(I65="",((TODAY()-A65)*G65)/365.24,((I65-A65)*G65)/365.24) -> 1787.4274 | AB65: 存股
A66: 46150 | C66: 3430 | D66: =VLOOKUP(C66,每日行情!A:B,2,FALSE) -> 奇鈦科 | E66: 1000 | F66: 148 | G66: =E66*F66 -> 148000 | H66: 126 | I66: 46309 | J66: 95.5 | K66: =E66*J66 -> 95500 | L66: 81 | M66: 286 | O66: =IF(I66="",E66*Y66,0) -> 0 | P66: =IF(I66="",R66-H66,(K66-H66-SUM(L66:N66)+R66-S66-T66)-G66)+(ROUND(R66*V66,0)-ROUND(R66*(1+V66),0)*W66) -> -51569 | Q66: =IF(I66="",(O66-G66-(O66*0.1425%*0.65)-(O66*0.3%)-S66-T66),0) -> 0 | R66: 1600 | U66: =(V66*50%)/(1+50%*V66) -> 0 | W66: 0.11 | X66: =(P66+Q66)/G66 -> -0.34843919 | Y66: =VLOOKUP(C66,每日行情!A:D,4,FALSE) -> 92 | Z66: =VLOOKUP(C66,每日行情!A:E,5,FALSE) -> 0.9 | AA66: =IF(I66="",((TODAY()-A66)*G66)/365.24,((I66-A66)*G66)/365.24) -> 64428.869 | AB66: 強勢股
A67: 46153 | C67: 3430 | D67: =VLOOKUP(C67,每日行情!A:B,2,FALSE) -> 奇鈦科 | E67: 1000 | F67: 164 | G67: =E67*F67 -> 164000 | H67: 140 | I67: 46309 | J67: 95.9 | K67: =E67*J67 -> 95900 | L67: 81 | M67: 287 | O67: =IF(I67="",E67*Y67,0) -> 0 | P67: =IF(I67="",R67-H67,(K67-H67-SUM(L67:N67)+R67-S67-T67)-G67)+(ROUND(R67*V67,0)-ROUND(R67*(1+V67),0)*W67) -> -67184 | Q67: =IF(I67="",(O67-G67-(O67*0.1425%*0.65)-(O67*0.3%)-S67-T67),0) -> 0 | R67: 1600 | U67: =(V67*50%)/(1+50%*V67) -> 0 | W67: 0.11 | X67: =(P67+Q67)/G67 -> -0.40965854 | Y67: =VLOOKUP(C67,每日行情!A:D,4,FALSE) -> 92 | Z67: =VLOOKUP(C67,每日行情!A:E,5,FALSE) -> 0.9 | AA67: =IF(I67="",((TODAY()-A67)*G67)/365.24,((I67-A67)*G67)/365.24) -> 70047.092 | AB67: 強勢股
A68: 46160 | C68: 7818 | D68: =VLOOKUP(C68,每日行情!A:B,2,FALSE) -> 溢泰實業 | E68: 1000 | F68: 70 | G68: =E68*F68 -> 70000 | H68: 20 | I68: 46309 | J68: 59.5 | K68: =E68*J68 -> 59500 | L68: 50 | M68: 178 | O68: =IF(I68="",E68*Y68,0) -> 0 | P68: =IF(I68="",R68-H68,(K68-H68-SUM(L68:N68)+R68-S68-T68)-G68)+(ROUND(R68*V68,0)-ROUND(R68*(1+V68),0)*W68) -> -8935.96 | Q68: =IF(I68="",(O68-G68-(O68*0.1425%*0.65)-(O68*0.3%)-S68-T68),0) -> 0 | R68: 2036 | U68: =(V68*50%)/(1+50%*V68) -> 0 | W68: 0.11 | X68: =(P68+Q68)/G68 -> -0.12765657 | Y68: =VLOOKUP(C68,每日行情!A:D,4,FALSE) -> 59.4 | Z68: =VLOOKUP(C68,每日行情!A:E,5,FALSE) -> -0.4 | AA68: =IF(I68="",((TODAY()-A68)*G68)/365.24,((I68-A68)*G68)/365.24) -> 28556.566 | AB68: 抽籤
A69: 46220 | C69: 00631L | D69: =VLOOKUP(C69,每日行情!A:B,2,FALSE) -> 元大台灣50正2 | E69: 1000 | F69: 33.61 | G69: =E69*F69 -> 33610 | H69: 28 | I69: 46225 | J69: 35.22 | K69: =E69*J69 -> 35220 | L69: 30 | M69: 35 | O69: =IF(I69="",E69*Y69,0) -> 0 | P69: =IF(I69="",R69-H69,(K69-H69-SUM(L69:N69)+R69-S69-T69)-G69)+(ROUND(R69*V69,0)-ROUND(R69*(1+V69),0)*W69) -> 1517 | Q69: =IF(I69="",(O69-G69-(O69*0.1425%*0.65)-(O69*0.3%)-S69-T69),0) -> 0 | U69: =(V69*50%)/(1+50%*V69) -> 0 | W69: 0.11 | X69: =(P69+Q69)/G69 -> 0.045135376 | Y69: =VLOOKUP(C69,每日行情!A:D,4,FALSE) -> 37.15 | Z69: =VLOOKUP(C69,每日行情!A:E,5,FALSE) -> 0.01 | AA69: =IF(I69="",((TODAY()-A69)*G69)/365.24,((I69-A69)*G69)/365.24) -> 460.10842 | AB69: 存股
A70: 46231 | C70: 00631L | D70: =VLOOKUP(C70,每日行情!A:B,2,FALSE) -> 元大台灣50正2 | E70: 1000 | F70: 31.28 | G70: =E70*F70 -> 31280 | H70: 26 | I70: 46234 | J70: 32.83 | K70: =E70*J70 -> 32830 | L70: 28 | M70: 32 | O70: =IF(I70="",E70*Y70,0) -> 0 | P70: =IF(I70="",R70-H70,(K70-H70-SUM(L70:N70)+R70-S70-T70)-G70)+(ROUND(R70*V70,0)-ROUND(R70*(1+V70),0)*W70) -> 1464 | Q70: =IF(I70="",(O70-G70-(O70*0.1425%*0.65)-(O70*0.3%)-S70-T70),0) -> 0 | U70: =(V70*50%)/(1+50%*V70) -> 0 | W70: 0.11 | X70: =(P70+Q70)/G70 -> 0.046803069 | Y70: =VLOOKUP(C70,每日行情!A:D,4,FALSE) -> 37.15 | Z70: =VLOOKUP(C70,每日行情!A:E,5,FALSE) -> 0.01 | AA70: =IF(I70="",((TODAY()-A70)*G70)/365.24,((I70-A70)*G70)/365.24) -> 256.92695 | AB70: 存股
A75: =MIN(A122:A122) -> 0
A76: 45614 | C76: 895 | D76: =VLOOKUP(C76,每日行情!A:B,2,FALSE) -> 富邦未來車 | E76: 160 | F76: 31.12 | G76: =E76*F76 -> 4979.2 | H76: 1 | K76: =E76*J76 -> 0 | L76: =ROUND(J76*E76*0.1425%,0) -> 0 | M76: =ROUND(J76*E76*0.3%,0) -> 0 | O76: =IF(I76="",E76*Y76,0) -> 8128 | P76: =IF(I76="",R76-H76,(K76-H76-SUM(L76:N76)+R76-S76-T76)-G76)+(ROUND(R76*V76,0)-ROUND(R76*(1+V76),0)*W76) -> -1 | Q76: =IF(I76="",(O76-G76-(O76*0.1425%*0.65)-(O76*0.3%)-S76-T76),0) -> 3116.8874 | U76: =(V76*50%)/(1+50%*V76) -> 0 | W76: 0.11 | X76: =(P76+Q76)/G76 -> 0.62578074 | Y76: =VLOOKUP(C76,每日行情!A:D,4,FALSE) -> 50.8 | Z76: =VLOOKUP(C76,每日行情!A:E,5,FALSE) -> 0.35 | AA76: =IF(I76="",((TODAY()-A76)*G76)/365.24,((I76-A76)*G76)/365.24) -> 9501.9779 | AB76: 存股 | AD76: 富邦-台股定期定額
A77: 45642 | C77: 895 | D77: =VLOOKUP(C77,每日行情!A:B,2,FALSE) -> 富邦未來車 | E77: 154 | F77: 32.37 | G77: 4984 | H77: 1 | K77: =E77*J77 -> 0 | L77: =ROUND(J77*E77*0.1425%,0) -> 0 | M77: =ROUND(J77*E77*0.3%,0) -> 0 | O77: =IF(I77="",E77*Y77,0) -> 7823.2 | P77: =IF(I77="",R77-H77,(K77-H77-SUM(L77:N77)+R77-S77-T77)-G77)+(ROUND(R77*V77,0)-ROUND(R77*(1+V77),0)*W77) -> -1 | Q77: =IF(I77="",(O77-G77-(O77*0.1425%*0.65)-(O77*0.3%)-S77-T77),0) -> 2808.4842 | U77: =(V77*50%)/(1+50%*V77) -> 0 | W77: 0.11 | X77: =(P77+Q77)/G77 -> 0.56329939 | Y77: =VLOOKUP(C77,每日行情!A:D,4,FALSE) -> 50.8 | Z77: =VLOOKUP(C77,每日行情!A:E,5,FALSE) -> 0.35 | AA77: =IF(I77="",((TODAY()-A77)*G77)/365.24,((I77-A77)*G77)/365.24) -> 9129.0549 | AB77: 存股 | AD77: 富邦-台股定期定額
A78: 45673 | C78: 895 | D78: =VLOOKUP(C78,每日行情!A:B,2,FALSE) -> 富邦未來車 | E78: 155 | F78: 32.2 | G78: 4991 | H78: 1 | K78: =E78*J78 -> 0 | L78: =ROUND(J78*E78*0.1425%,0) -> 0 | M78: =ROUND(J78*E78*0.3%,0) -> 0 | O78: =IF(I78="",E78*Y78,0) -> 7874 | P78: =IF(I78="",R78-H78,(K78-H78-SUM(L78:N78)+R78-S78-T78)-G78)+(ROUND(R78*V78,0)-ROUND(R78*(1+V78),0)*W78) -> -1 | Q78: =IF(I78="",(O78-G78-(O78*0.1425%*0.65)-(O78*0.3%)-S78-T78),0) -> 2852.0847 | U78: =(V78*50%)/(1+50%*V78) -> 0 | W78: 0.11 | X78: =(P78+Q78)/G78 -> 0.57124518 | Y78: =VLOOKUP(C78,每日行情!A:D,4,FALSE) -> 50.8 | Z78: =VLOOKUP(C78,每日行情!A:E,5,FALSE) -> 0.35 | AA78: =IF(I78="",((TODAY()-A78)*G78)/365.24,((I78-A78)*G78)/365.24) -> 8718.262 | AB78: 存股 | AD78: 富邦-台股定期定額
A79: 45705 | C79: 895 | D79: =VLOOKUP(C79,每日行情!A:B,2,FALSE) -> 富邦未來車 | E79: 157 | F79: 31.68 | G79: 4973 | H79: 1 | K79: =E79*J79 -> 0 | L79: =ROUND(J79*E79*0.1425%,0) -> 0 | M79: =ROUND(J79*E79*0.3%,0) -> 0 | O79: =IF(I79="",E79*Y79,0) -> 7975.6 | P79: =IF(I79="",R79-H79,(K79-H79-SUM(L79:N79)+R79-S79-T79)-G79)+(ROUND(R79*V79,0)-ROUND(R79*(1+V79),0)*W79) -> -1 | Q79: =IF(I79="",(O79-G79-(O79*0.1425%*0.65)-(O79*0.3%)-S79-T79),0) -> 2971.2858 | U79: =(V79*50%)/(1+50%*V79) -> 0 | W79: 0.11 | X79: =(P79+Q79)/G79 -> 0.59728249 | Y79: =VLOOKUP(C79,每日行情!A:D,4,FALSE) -> 50.8 | Z79: =VLOOKUP(C79,每日行情!A:E,5,FALSE) -> 0.35 | AA79: =IF(I79="",((TODAY()-A79)*G79)/365.24,((I79-A79)*G79)/365.24) -> 8251.1171 | AB79: 存股 | AD79: 富邦-台股定期定額
A80: 45733 | C80: 895 | D80: =VLOOKUP(C80,每日行情!A:B,2,FALSE) -> 富邦未來車 | E80: 176 | F80: 28.3 | G80: 4980 | H80: 1 | K80: =E80*J80 -> 0 | L80: =ROUND(J80*E80*0.1425%,0) -> 0 | M80: =ROUND(J80*E80*0.3%,0) -> 0 | O80: =IF(I80="",E80*Y80,0) -> 8940.8 | P80: =IF(I80="",R80-H80,(K80-H80-SUM(L80:N80)+R80-S80-T80)-G80)+(ROUND(R80*V80,0)-ROUND(R80*(1+V80),0)*W80) -> -1 | Q80: =IF(I80="",(O80-G80-(O80*0.1425%*0.65)-(O80*0.3%)-S80-T80),0) -> 3925.6962 | U80: =(V80*50%)/(1+50%*V80) -> 0 | W80: 0.11 | X80: =(P80+Q80)/G80 -> 0.7880916 | Y80: =VLOOKUP(C80,每日行情!A:D,4,FALSE) -> 50.8 | Z80: =VLOOKUP(C80,每日行情!A:E,5,FALSE) -> 0.35 | AA80: =IF(I80="",((TODAY()-A80)*G80)/365.24,((I80-A80)*G80)/365.24) -> 7880.955 | AB80: 存股 | AD80: 富邦-台股定期定額
A81: 45763 | C81: 895 | D81: =VLOOKUP(C81,每日行情!A:B,2,FALSE) -> 富邦未來車 | E81: 193 | F81: 25.84 | G81: 4987 | H81: 1 | K81: =E81*J81 -> 0 | L81: =ROUND(J81*E81*0.1425%,0) -> 0 | M81: =ROUND(J81*E81*0.3%,0) -> 0 | O81: =IF(I81="",E81*Y81,0) -> 9804.4 | P81: =IF(I81="",R81-H81,(K81-H81-SUM(L81:N81)+R81-S81-T81)-G81)+(ROUND(R81*V81,0)-ROUND(R81*(1+V81),0)*W81) -> -1 | Q81: =IF(I81="",(O81-G81-(O81*0.1425%*0.65)-(O81*0.3%)-S81-T81),0) -> 4778.9055 | U81: =(V81*50%)/(1+50%*V81) -> 0 | W81: 0.11 | X81: =(P81+Q81)/G81 -> 0.95807208 | Y81: =VLOOKUP(C81,每日行情!A:D,4,FALSE) -> 50.8 | Z81: =VLOOKUP(C81,每日行情!A:E,5,FALSE) -> 0.35 | AA81: =IF(I81="",((TODAY()-A81)*G81)/365.24,((I81-A81)*G81)/365.24) -> 7482.4116 | AB81: 存股 | AD81: 富邦-台股定期定額
A82: 45793 | C82: 895 | D82: =VLOOKUP(C82,每日行情!A:B,2,FALSE) -> 富邦未來車 | E82: 171 | F82: 29.12 | G82: 4979 | H82: 1 | K82: =E82*J82 -> 0 | L82: =ROUND(J82*E82*0.1425%,0) -> 0 | M82: =ROUND(J82*E82*0.3%,0) -> 0 | O82: =IF(I82="",E82*Y82,0) -> 8686.8 | P82: =IF(I82="",R82-H82,(K82-H82-SUM(L82:N82)+R82-S82-T82)-G82)+(ROUND(R82*V82,0)-ROUND(R82*(1+V82),0)*W82) -> -1 | Q82: =IF(I82="",(O82-G82-(O82*0.1425%*0.65)-(O82*0.3%)-S82-T82),0) -> 3673.6935 | U82: =(V82*50%)/(1+50%*V82) -> 0 | W82: 0.11 | X82: =(P82+Q82)/G82 -> 0.73763676 | Y82: =VLOOKUP(C82,每日行情!A:D,4,FALSE) -> 50.8 | Z82: =VLOOKUP(C82,每日行情!A:E,5,FALSE) -> 0.35 | AA82: =IF(I82="",((TODAY()-A82)*G82)/365.24,((I82-A82)*G82)/365.24) -> 7061.4445 | AB82: 存股 | AD82: 富邦-台股定期定額
A83: 45824 | C83: 895 | D83: =VLOOKUP(C83,每日行情!A:B,2,FALSE) -> 富邦未來車 | E83: 172 | F83: 29 | G83: 4988 | H83: 1 | K83: =E83*J83 -> 0 | L83: =ROUND(J83*E83*0.1425%,0) -> 0 | M83: =ROUND(J83*E83*0.3%,0) -> 0 | O83: =IF(I83="",E83*Y83,0) -> 8737.6 | P83: =IF(I83="",R83-H83,(K83-H83-SUM(L83:N83)+R83-S83-T83)-G83)+(ROUND(R83*V83,0)-ROUND(R83*(1+V83),0)*W83) -> -1 | Q83: =IF(I83="",(O83-G83-(O83*0.1425%*0.65)-(O83*0.3%)-S83-T83),0) -> 3715.294 | U83: =(V83*50%)/(1+50%*V83) -> 0 | W83: 0.11 | X83: =(P83+Q83)/G83 -> 0.74464595 | Y83: =VLOOKUP(C83,每日行情!A:D,4,FALSE) -> 50.8 | Z83: =VLOOKUP(C83,每日行情!A:E,5,FALSE) -> 0.35 | AA83: =IF(I83="",((TODAY()-A83)*G83)/365.24,((I83-A83)*G83)/365.24) -> 6650.8488 | AB83: 存股 | AD83: 富邦-台股定期定額
A84: 45854 | C84: 895 | D84: =VLOOKUP(C84,每日行情!A:B,2,FALSE) -> 富邦未來車 | E84: 160 | F84: 31.14 | G84: 4982 | H84: 1 | K84: =E84*J84 -> 0 | L84: =ROUND(J84*E84*0.1425%,0) -> 0 | M84: =ROUND(J84*E84*0.3%,0) -> 0 | O84: =IF(I84="",E84*Y84,0) -> 8128 | P84: =IF(I84="",R84-H84,(K84-H84-SUM(L84:N84)+R84-S84-T84)-G84)+(ROUND(R84*V84,0)-ROUND(R84*(1+V84),0)*W84) -> -1 | Q84: =IF(I84="",(O84-G84-(O84*0.1425%*0.65)-(O84*0.3%)-S84-T84),0) -> 3114.0874 | U84: =(V84*50%)/(1+50%*V84) -> 0 | W84: 0.11 | X84: =(P84+Q84)/G84 -> 0.62486701 | Y84: =VLOOKUP(C84,每日行情!A:D,4,FALSE) -> 50.8 | Z84: =VLOOKUP(C84,每日行情!A:E,5,FALSE) -> 0.35 | AA84: =IF(I84="",((TODAY()-A84)*G84)/365.24,((I84-A84)*G84)/365.24) -> 6233.6382 | AB84: 存股 | AD84: 富邦-台股定期定額
A85: 45887 | C85: 895 | D85: =VLOOKUP(C85,每日行情!A:B,2,FALSE) -> 富邦未來車 | E85: 150 | F85: 33.15 | G85: 4972 | H85: 1 | K85: =E85*J85 -> 0 | L85: =ROUND(J85*E85*0.1425%,0) -> 0 | M85: =ROUND(J85*E85*0.3%,0) -> 0 | O85: =IF(I85="",E85*Y85,0) -> 7620 | P85: =IF(I85="",R85-H85,(K85-H85-SUM(L85:N85)+R85-S85-T85)-G85)+(ROUND(R85*V85,0)-ROUND(R85*(1+V85),0)*W85) -> -1 | Q85: =IF(I85="",(O85-G85-(O85*0.1425%*0.65)-(O85*0.3%)-S85-T85),0) -> 2618.082 | U85: =(V85*50%)/(1+50%*V85) -> 0 | W85: 0.11 | X85: =(P85+Q85)/G85 -> 0.52636403 | Y85: =VLOOKUP(C85,每日行情!A:D,4,FALSE) -> 50.8 | Z85: =VLOOKUP(C85,每日行情!A:E,5,FALSE) -> 0.35 | AA85: =IF(I85="",((TODAY()-A85)*G85)/365.24,((I85-A85)*G85)/365.24) -> 5771.8979 | AB85: 存股 | AD85: 富邦-台股定期定額
A86: 45916 | C86: 895 | D86: =VLOOKUP(C86,每日行情!A:B,2,FALSE) -> 富邦未來車 | E86: 144 | F86: 34.64 | G86: 4988 | H86: 1 | K86: =E86*J86 -> 0 | L86: =ROUND(J86*E86*0.1425%,0) -> 0 | M86: =ROUND(J86*E86*0.3%,0) -> 0 | O86: =IF(I86="",E86*Y86,0) -> 7315.2 | P86: =IF(I86="",R86-H86,(K86-H86-SUM(L86:N86)+R86-S86-T86)-G86)+(ROUND(R86*V86,0)-ROUND(R86*(1+V86),0)*W86) -> -1 | Q86: =IF(I86="",(O86-G86-(O86*0.1425%*0.65)-(O86*0.3%)-S86-T86),0) -> 2298.4787 | U86: =(V86*50%)/(1+50%*V86) -> 0 | W86: 0.11 | X86: =(P86+Q86)/G86 -> 0.46060118 | Y86: =VLOOKUP(C86,每日行情!A:D,4,FALSE) -> 50.8 | Z86: =VLOOKUP(C86,每日行情!A:E,5,FALSE) -> 0.35 | AA86: =IF(I86="",((TODAY()-A86)*G86)/365.24,((I86-A86)*G86)/365.24) -> 5394.4256 | AB86: 存股 | AD86: 富邦-台股定期定額
A87: 45946 | C87: 895 | D87: =VLOOKUP(C87,每日行情!A:B,2,FALSE) -> 富邦未來車 | E87: 133 | F87: 37.43 | G87: 4978 | H87: 1 | K87: =E87*J87 -> 0 | L87: =ROUND(J87*E87*0.1425%,0) -> 0 | M87: =ROUND(J87*E87*0.3%,0) -> 0 | O87: =IF(I87="",E87*Y87,0) -> 6756.4 | P87: =IF(I87="",R87-H87,(K87-H87-SUM(L87:N87)+R87-S87-T87)-G87)+(ROUND(R87*V87,0)-ROUND(R87*(1+V87),0)*W87) -> -1 | Q87: =IF(I87="",(O87-G87-(O87*0.1425%*0.65)-(O87*0.3%)-S87-T87),0) -> 1751.8727 | U87: =(V87*50%)/(1+50%*V87) -> 0 | W87: 0.11 | X87: =(P87+Q87)/G87 -> 0.35172211 | Y87: =VLOOKUP(C87,每日行情!A:D,4,FALSE) -> 50.8 | Z87: =VLOOKUP(C87,每日行情!A:E,5,FALSE) -> 0.35 | AA87: =IF(I87="",((TODAY()-A87)*G87)/365.24,((I87-A87)*G87)/365.24) -> 4974.7289 | AB87: 存股 | AD87: 富邦-台股定期定額
A88: 45978 | C88: 895 | D88: =VLOOKUP(C88,每日行情!A:B,2,FALSE) -> 富邦未來車 | E88: 131 | F88: 38.04 | G88: 4983 | H88: 1 | K88: =E88*J88 -> 0 | L88: =ROUND(J88*E88*0.1425%,0) -> 0 | M88: =ROUND(J88*E88*0.3%,0) -> 0 | O88: =IF(I88="",E88*Y88,0) -> 6654.8 | P88: =IF(I88="",R88-H88,(K88-H88-SUM(L88:N88)+R88-S88-T88)-G88)+(ROUND(R88*V88,0)-ROUND(R88*(1+V88),0)*W88) -> -1 | Q88: =IF(I88="",(O88-G88-(O88*0.1425%*0.65)-(O88*0.3%)-S88-T88),0) -> 1645.6716 | U88: =(V88*50%)/(1+50%*V88) -> 0 | W88: 0.11 | X88: =(P88+Q88)/G88 -> 0.33005651 | Y88: =VLOOKUP(C88,每日行情!A:D,4,FALSE) -> 50.8 | Z88: =VLOOKUP(C88,每日行情!A:E,5,FALSE) -> 0.35 | AA88: =IF(I88="",((TODAY()-A88)*G88)/365.24,((I88-A88)*G88)/365.24) -> 4543.147 | AB88: 存股 | AD88: 富邦-台股定期定額
... A93: 46160 | C93: 895 | D93: =VLOOKUP(C93,每日行情!A:B,2,FALSE) -> 富邦未來車 | E93: 101 | F93: 49.19 | G93: 4968 | H93: 1 | K93: =E93*J93 -> 0 | L93: =ROUND(J93*E93*0.1425%,0) -> 0 | M93: =ROUND(J93*E93*0.3%,0) -> 0 | O93: =IF(I93="",E93*Y93,0) -> 5130.8 | P93: =IF(I93="",R93-H93,(K93-H93-SUM(L93:N93)+R93-S93-T93)-G93)+(ROUND(R93*V93,0)-ROUND(R93*(1+V93),0)*W93) -> -1 | Q93: =IF(I93="",(O93-G93-(O93*0.1425%*0.65)-(O93*0.3%)-S93-T93),0) -> 142.6552 | U93: =(V93*50%)/(1+50%*V93) -> 0 | W93: 0.11 | X93: =(P93+Q93)/G93 -> 0.028513526 | Y93: =VLOOKUP(C93,每日行情!A:D,4,FALSE) -> 50.8 | Z93: =VLOOKUP(C93,每日行情!A:E,5,FALSE) -> 0.35 | AA93: =IF(I93="",((TODAY()-A93)*G93)/365.24,((I93-A93)*G93)/365.24) -> 2053.9043 | AB93: 存股 | AD93: 富邦-台股定期定額
A94: 46090 | C94: 00991A | D94: =VLOOKUP(C94,每日行情!A:B,2,FALSE) -> 主動復華未來50 | E94: 876 | F94: 11.12 | G94: 9741 | H94: 1 | K94: =E94*J94 -> 0 | L94: =ROUND(J94*E94*0.1425%,0) -> 0 | M94: =ROUND(J94*E94*0.3%,0) -> 0 | O94: =IF(I94="",E94*Y94,0) -> 15198.6 | P94: =IF(I94="",R94-H94,(K94-H94-SUM(L94:N94)+R94-S94-T94)-G94)+(ROUND(R94*V94,0)-ROUND(R94*(1+V94),0)*W94) -> -1 | Q94: =IF(I94="",(O94-G94-(O94*0.1425%*0.65)-(O94*0.3%)-S94-T94),0) -> 5397.9265 | U94: =(V94*50%)/(1+50%*V94) -> 0 | W94: 0.11 | X94: =(P94+Q94)/G94 -> 0.55404235 | Y94: =VLOOKUP(C94,每日行情!A:D,4,FALSE) -> 17.35 | Z94: =VLOOKUP(C94,每日行情!A:E,5,FALSE) -> 0.18 | AA94: =IF(I94="",((TODAY()-A94)*G94)/365.24,((I94-A94)*G94)/365.24) -> 5894.0998 | AB94: 存股 | AD94: 富邦-台股定期定額
A95: 46120 | C95: 00991A | D95: =VLOOKUP(C95,每日行情!A:B,2,FALSE) -> 主動復華未來50 | E95: 740 | F95: 13.5 | G95: 9858 | H95: 1 | K95: =E95*J95 -> 0 | L95: =ROUND(J95*E95*0.1425%,0) -> 0 | M95: =ROUND(J95*E95*0.3%,0) -> 0 | O95: =IF(I95="",E95*Y95,0) -> 12839 | P95: =IF(I95="",R95-H95,(K95-H95-SUM(L95:N95)+R95-S95-T95)-G95)+(ROUND(R95*V95,0)-ROUND(R95*(1+V95),0)*W95) -> -1 | Q95: =IF(I95="",(O95-G95-(O95*0.1425%*0.65)-(O95*0.3%)-S95-T95),0) -> 2930.5909 | U95: =(V95*50%)/(1+50%*V95) -> 0 | W95: 0.11 | X95: =(P95+Q95)/G95 -> 0.29717903 | Y95: =VLOOKUP(C95,每日行情!A:D,4,FALSE) -> 17.35 | Z95: =VLOOKUP(C95,每日行情!A:E,5,FALSE) -> 0.18 | AA95: =IF(I95="",((TODAY()-A95)*G95)/365.24,((I95-A95)*G95)/365.24) -> 5155.1802 | AB95: 存股 | AD95: 富邦-台股定期定額
A96: 46097 | C96: 895 | D96: =VLOOKUP(C96,每日行情!A:B,2,FALSE) -> 富邦未來車 | E96: 125 | F96: 40 | G96: 5000 | H96: 1 | K96: =E96*J96 -> 0 | L96: =ROUND(J96*E96*0.1425%,0) -> 0 | M96: =ROUND(J96*E96*0.3%,0) -> 0 | O96: =IF(I96="",E96*Y96,0) -> 6350 | P96: =IF(I96="",R96-H96,(K96-H96-SUM(L96:N96)+R96-S96-T96)-G96)+(ROUND(R96*V96,0)-ROUND(R96*(1+V96),0)*W96) -> -1 | Q96: =IF(I96="",(O96-G96-(O96*0.1425%*0.65)-(O96*0.3%)-S96-T96),0) -> 1325.0683 | U96: =(V96*50%)/(1+50%*V96) -> 0 | W96: 0.11 | X96: =(P96+Q96)/G96 -> 0.26481366 | Y96: =VLOOKUP(C96,每日行情!A:D,4,FALSE) -> 50.8 | Z96: =VLOOKUP(C96,每日行情!A:E,5,FALSE) -> 0.35 | AA96: =IF(I96="",((TODAY()-A96)*G96)/365.24,((I96-A96)*G96)/365.24) -> 2929.5805 | AB96: 存股 | AD96: 富邦-台股定期定額
A97: 46132 | C97: 2330 | D97: =VLOOKUP(C97,每日行情!A:B,2,FALSE) -> 台積電 | E97: 100 | F97: 2050 | G97: =E97*F97 -> 205000 | H97: 175 | K97: =E97*J97 -> 0 | L97: =ROUND(J97*E97*0.1425%,0) -> 0 | M97: =ROUND(J97*E97*0.3%,0) -> 0 | O97: =IF(I97="",E97*Y97,0) -> 242000 | P97: =IF(I97="",R97-H97,(K97-H97-SUM(L97:N97)+R97-S97-T97)-G97)+(ROUND(R97*V97,0)-ROUND(R97*(1+V97),0)*W97) -> -175 | Q97: =IF(I97="",(O97-G97-(O97*0.1425%*0.65)-(O97*0.3%)-S97-T97),0) -> 36049.848 | U97: =(V97*50%)/(1+50%*V97) -> 0 | W97: 0.11 | X97: =(P97+Q97)/G97 -> 0.17499926 | Y97: =VLOOKUP(C97,每日行情!A:D,4,FALSE) -> 2420 | Z97: =VLOOKUP(C97,每日行情!A:E,5,FALSE) -> -20 | AA97: =IF(I97="",((TODAY()-A97)*G97)/365.24,((I97-A97)*G97)/365.24) -> 100468.19 | AB97: 存股
A98: 46146 | C98: 00981A | D98: =VLOOKUP(C98,每日行情!A:B,2,FALSE) -> 主動統一台股增長 | E98: 2000 | F98: 29.4 | G98: =E98*F98 -> 58800 | H98: 50 | K98: =E98*J98 -> 0 | L98: =ROUND(J98*E98*0.1425%,0) -> 0 | M98: =ROUND(J98*E98*0.3%,0) -> 0 | O98: =IF(I98="",E98*Y98,0) -> 59060 | P98: =IF(I98="",R98-H98,(K98-H98-SUM(L98:N98)+R98-S98-T98)-G98)+(ROUND(R98*V98,0)-ROUND(R98*(1+V98),0)*W98) -> 1071.4 | Q98: =IF(I98="",(O98-G98-(O98*0.1425%*0.65)-(O98*0.3%)-S98-T98),0) -> 28.115675 | R98: 1260 | U98: =(V98*50%)/(1+50%*V98) -> 0 | W98: 0.11 | X98: =(P98+Q98)/G98 -> 0.018699246 | Y98: =VLOOKUP(C98,每日行情!A:D,4,FALSE) -> 29.53 | Z98: =VLOOKUP(C98,每日行情!A:E,5,FALSE) -> 0.13 | AA98: =IF(I98="",((TODAY()-A98)*G98)/365.24,((I98-A98)*G98)/365.24) -> 26563.356 | AB98: 存股 | AD98: 富邦-台股定期定額
A99: 46148 | C99: 6525 | D99: =VLOOKUP(C99,每日行情!A:B,2,FALSE) -> 捷敏-KY | E99: 1000 | F99: 103.5 | G99: =E99*F99 -> 103500 | H99: 88 | K99: =E99*J99 -> 0 | L99: =ROUND(J99*E99*0.1425%,0) -> 0 | M99: =ROUND(J99*E99*0.3%,0) -> 0 | O99: =IF(I99="",E99*Y99,0) -> 128500 | P99: =IF(I99="",R99-H99,(K99-H99-SUM(L99:N99)+R99-S99-T99)-G99)+(ROUND(R99*V99,0)-ROUND(R99*(1+V99),0)*W99) -> 4362 | Q99: =IF(I99="",(O99-G99-(O99*0.1425%*0.65)-(O99*0.3%)-S99-T99),0) -> 24495.477 | R99: 5000 | U99: =(V99*50%)/(1+50%*V99) -> 0 | W99: 0.11 | X99: =(P99+Q99)/G99 -> 0.2788162 | Y99: =VLOOKUP(C99,每日行情!A:D,4,FALSE) -> 128.5 | Z99: =VLOOKUP(C99,每日行情!A:E,5,FALSE) -> 0 | AA99: =IF(I99="",((TODAY()-A99)*G99)/365.24,((I99-A99)*G99)/365.24) -> 46190.176 | AB99: 阿水一式
A100: 46150 | C100: 00991A | D100: =VLOOKUP(C100,每日行情!A:B,2,FALSE) -> 主動復華未來50 | E100: 563 | F100: 17.51 | G100: 9858 | H100: 1 | K100: =E100*J100 -> 0 | L100: =ROUND(J100*E100*0.1425%,0) -> 0 | M100: =ROUND(J100*E100*0.3%,0) -> 0 | O100: =IF(I100="",E100*Y100,0) -> 9768.05 | P100: =IF(I100="",R100-H100,(K100-H100-SUM(L100:N100)+R100-S100-T100)-G100)+(ROUND(R100*V100,0)-ROUND(R100*(1+V100),0)*W100) -> -1 | Q100: =IF(I100="",(O100-G100-(O100*0.1425%*0.65)-(O100*0.3%)-S100-T100),0) -> -128.30181 | U100: =(V100*50%)/(1+50%*V100) -> 0 | W100: 0.11 | X100: =(P100+Q100)/G100 -> -0.013116434 | Y100: =VLOOKUP(C100,每日行情!A:D,4,FALSE) -> 17.35 | Z100: =VLOOKUP(C100,每日行情!A:E,5,FALSE) -> 0.18 | AA100: =IF(I100="",((TODAY()-A100)*G100)/365.24,((I100-A100)*G100)/365.24) -> 4345.466 | AB100: 存股 | AD100: 富邦-台股定期定額
A101: 46150 | C101: 6788 | D101: =VLOOKUP(C101,每日行情!A:B,2,FALSE) -> 華景電 | E101: 200 | F101: 449.5 | G101: =E101*F101 -> 89900 | H101: 76 | K101: =E101*J101 -> 0 | L101: =ROUND(J101*E101*0.1425%,0) -> 0 | M101: =ROUND(J101*E101*0.3%,0) -> 0 | O101: =IF(I101="",E101*Y101,0) -> 72300 | P101: =IF(I101="",R101-H101,(K101-H101-SUM(L101:N101)+R101-S101-T101)-G101)+(ROUND(R101*V101,0)-ROUND(R101*(1+V101),0)*W101) -> 2594 | Q101: =IF(I101="",(O101-G101-(O101*0.1425%*0.65)-(O101*0.3%)-S101-T101),0) -> -17883.868 | R101: 3000 | U101: =(V101*50%)/(1+50%*V101) -> 0 | W101: 0.11 | X101: =(P101+Q101)/G101 -> -0.17007639 | Y101: =VLOOKUP(C101,每日行情!A:D,4,FALSE) -> 361.5 | Z101: =VLOOKUP(C101,每日行情!A:E,5,FALSE) -> 3 | AA101: =IF(I101="",((TODAY()-A101)*G101)/365.24,((I101-A101)*G101)/365.24) -> 39628.463 | AB101: 強勢股
A102: 46153 | C102: 2330 | D102: =VLOOKUP(C102,每日行情!A:B,2,FALSE) -> 台積電 | E102: 10 | F102: 2265 | G102: =E102*F102 -> 22650 | H102: 19 | K102: =E102*J102 -> 0 | L102: =ROUND(J102*E102*0.1425%,0) -> 0 | M102: =ROUND(J102*E102*0.3%,0) -> 0 | O102: =IF(I102="",E102*Y102,0) -> 24200 | P102: =IF(I102="",R102-H102,(K102-H102-SUM(L102:N102)+R102-S102-T102)-G102)+(ROUND(R102*V102,0)-ROUND(R102*(1+V102),0)*W102) -> 1253.7 | Q102: =IF(I102="",(O102-G102-(O102*0.1425%*0.65)-(O102*0.3%)-S102-T102),0) -> 1454.9848 | R102: 1430 | U102: =(V102*50%)/(1+50%*V102) -> 0 | W102: 0.11 | X102: =(P102+Q102)/G102 -> 0.11958873 | Y102: =VLOOKUP(C102,每日行情!A:D,4,FALSE) -> 2420 | Z102: =VLOOKUP(C102,每日行情!A:E,5,FALSE) -> -20 | AA102: =IF(I102="",((TODAY()-A102)*G102)/365.24,((I102-A102)*G102)/365.24) -> 9798.2149 | AB102: 存股
A103: 46155 | C103: 00631L | D103: =VLOOKUP(C103,每日行情!A:B,2,FALSE) -> 元大台灣50正2 | E103: 2000 | F103: 31.88 | G103: =E103*F103 -> 63760 | H103: 54 | K103: =E103*J103 -> 0 | L103: =ROUND(J103*E103*0.1425%,0) -> 0 | M103: =ROUND(J103*E103*0.3%,0) -> 0 | O103: =IF(I103="",E103*Y103,0) -> 74300 | P103: =IF(I103="",R103-H103,(K103-H103-SUM(L103:N103)+R103-S103-T103)-G103)+(ROUND(R103*V103,0)-ROUND(R103*(1+V103),0)*W103) -> -54 | Q103: =IF(I103="",(O103-G103-(O103*0.1425%*0.65)-(O103*0.3%)-S103-T103),0) -> 10248.28 | U103: =(V103*50%)/(1+50%*V103) -> 0 | W103: 0.11 | X103: =(P103+Q103)/G103 -> 0.15988519 | Y103: =VLOOKUP(C103,每日行情!A:D,4,FALSE) -> 37.15 | Z103: =VLOOKUP(C103,每日行情!A:E,5,FALSE) -> 0.01 | AA103: =IF(I103="",((TODAY()-A103)*G103)/365.24,((I103-A103)*G103)/365.24) -> 27232.943 | AB103: 存股
A104: 46157 | C104: 6788 | D104: =VLOOKUP(C104,每日行情!A:B,2,FALSE) -> 華景電 | E104: 100 | F104: 411 | G104: =E104*F104 -> 41100 | H104: 35 | J104: 328.5/46 | K104: =E104*J104 -> #VALUE! | L104: 12 | M104: 45 | O104: =IF(I104="",E104*Y104,0) -> 36150 | P104: =IF(I104="",R104-H104,(K104-H104-SUM(L104:N104)+R104-S104-T104)-G104)+(ROUND(R104*V104,0)-ROUND(R104*(1+V104),0)*W104) -> 1300 | Q104: =IF(I104="",(O104-G104-(O104*0.1425%*0.65)-(O104*0.3%)-S104-T104),0) -> -5091.9339 | R104: 1500 | U104: =(V104*50%)/(1+50%*V104) -> 0 | W104: 0.11 | X104: =(P104+Q104)/G104 -> -0.092261166 | Y104: =VLOOKUP(C104,每日行情!A:D,4,FALSE) -> 361.5 | Z104: =VLOOKUP(C104,每日行情!A:E,5,FALSE) -> 3 | AA104: =IF(I104="",((TODAY()-A104)*G104)/365.24,((I104-A104)*G104)/365.24) -> 17329.427 | AB104: 強勢股
A105: 46160 | C105: 910 | D105: =VLOOKUP(C105,每日行情!A:B,2,FALSE) -> 第一金太空衛星 | E105: 66 | F105: 75.5 | G105: 4983 | H105: 1 | K105: =E105*J105 -> 0 | L105: =ROUND(J105*E105*0.1425%,0) -> 0 | M105: =ROUND(J105*E105*0.3%,0) -> 0 | O105: =IF(I105="",E105*Y105,0) -> 3408.9 | P105: =IF(I105="",R105-H105,(K105-H105-SUM(L105:N105)+R105-S105-T105)-G105)+(ROUND(R105*V105,0)-ROUND(R105*(1+V105),0)*W105) -> -1 | Q105: =IF(I105="",(O105-G105-(O105*0.1425%*0.65)-(O105*0.3%)-S105-T105),0) -> -1587.4842 | U105: =(V105*50%)/(1+50%*V105) -> 0 | W105: 0.11 | X105: =(P105+Q105)/G105 -> -0.31878069 | Y105: =VLOOKUP(C105,每日行情!A:D,4,FALSE) -> 51.65 | Z105: =VLOOKUP(C105,每日行情!A:E,5,FALSE) -> 1.75 | AA105: =IF(I105="",((TODAY()-A105)*G105)/365.24,((I105-A105)*G105)/365.24) -> 2060.1057 | AB105: 存股 | AD105: 富邦-台股定期定額
A106: 46170 | C106: 1802 | D106: =VLOOKUP(C106,每日行情!A:B,2,FALSE) -> 台玻 | E106: 1000 | F106: 70.6 | G106: =E106*F106 -> 70600 | H106: 60 | K106: =E106*J106 -> 0 | L106: =ROUND(J106*E106*0.1425%,0) -> 0 | M106: =ROUND(J106*E106*0.3%,0) -> 0 | O106: =IF(I106="",E106*Y106,0) -> 66900 | P106: =IF(I106="",R106-H106,(K106-H106-SUM(L106:N106)+R106-S106-T106)-G106)+(ROUND(R106*V106,0)-ROUND(R106*(1+V106),0)*W106) -> -60 | Q106: =IF(I106="",(O106-G106-(O106*0.1425%*0.65)-(O106*0.3%)-S106-T106),0) -> -3962.6661 | U106: =(V106*50%)/(1+50%*V106) -> 0 | W106: 0.11 | X106: =(P106+Q106)/G106 -> -0.056978274 | Y106: =VLOOKUP(C106,每日行情!A:D,4,FALSE) -> 66.9 | Z106: =VLOOKUP(C106,每日行情!A:E,5,FALSE) -> 4.2 | AA106: =IF(I106="",((TODAY()-A106)*G106)/365.24,((I106-A106)*G106)/365.24) -> 27254.956 | AB106: 存股
A107: 46174 | C107: 4906 | D107: =VLOOKUP(C107,每日行情!A:B,2,FALSE) -> 正文 | E107: 1000 | F107: 53.3 | G107: =E107*F107 -> 53300 | H107: 45 | K107: =E107*J107 -> 0 | L107: =ROUND(J107*E107*0.1425%,0) -> 0 | M107: =ROUND(J107*E107*0.3%,0) -> 0 | O107: =IF(I107="",E107*Y107,0) -> 44850 | P107: =IF(I107="",R107-H107,(K107-H107-SUM(L107:N107)+R107-S107-T107)-G107)+(ROUND(R107*V107,0)-ROUND(R107*(1+V107),0)*W107) -> 343.93 | Q107: =IF(I107="",(O107-G107-(O107*0.1425%*0.65)-(O107*0.3%)-S107-T107),0) -> -8626.0923 | R107: 437 | U107: =(V107*50%)/(1+50%*V107) -> 0 | W107: 0.11 | X107: =(P107+Q107)/G107 -> -0.15538766 | Y107: =VLOOKUP(C107,每日行情!A:D,4,FALSE) -> 44.85 | Z107: =VLOOKUP(C107,每日行情!A:E,5,FALSE) -> 4.05 | AA107: =IF(I107="",((TODAY()-A107)*G107)/365.24,((I107-A107)*G107)/365.24) -> 19992.608
A108: 46178 | C108: 00631L | D108: =VLOOKUP(C108,每日行情!A:B,2,FALSE) -> 元大台灣50正2 | E108: 1000 | F108: 37.37 | G108: =E108*F108 -> 37370 | H108: 31 | K108: =E108*J108 -> 0 | L108: =ROUND(J108*E108*0.1425%,0) -> 0 | M108: =ROUND(J108*E108*0.3%,0) -> 0 | O108: =IF(I108="",E108*Y108,0) -> 37150 | P108: =IF(I108="",R108-H108,(K108-H108-SUM(L108:N108)+R108-S108-T108)-G108)+(ROUND(R108*V108,0)-ROUND(R108*(1+V108),0)*W108) -> -31 | Q108: =IF(I108="",(O108-G108-(O108*0.1425%*0.65)-(O108*0.3%)-S108-T108),0) -> -365.86019 | U108: =(V108*50%)/(1+50%*V108) -> 0 | W108: 0.11 | X108: =(P108+Q108)/G108 -> -0.010619753 | Y108: =VLOOKUP(C108,每日行情!A:D,4,FALSE) -> 37.15 | Z108: =VLOOKUP(C108,每日行情!A:E,5,FALSE) -> 0.01 | AA108: =IF(I108="",((TODAY()-A108)*G108)/365.24,((I108-A108)*G108)/365.24) -> 13608.066 | AB108: 存股
...

Sheet 總投報率
A1: 年度 | C1: 投資損益 | D1: 交易金額 | E1: 存款均額 | F1: 交易成本 | G1: 投資收益率 交易金額計 | H1: 投資收益率 存款均額計 | I1: 年化報酬率 交易金額計
A2: 2014 | B2: 股票 | C2: ='14股'!P63 -> -29302.16 | D2: ='14股'!G63 -> 3121360 | F2: =SUM('14股'!H63,'14股'!L63:M63) -> 14624 | G2: =C2/D2 -> -0.0093876259 | I2: =C2/'14股'!Z63 -> -0.058821585
A3: 2015 | B3: 股票 | C3: ='15股'!P144 -> -92925.805 | D3: ='15股'!G144 -> 6783148 | F3: =SUM('15股'!H144,'15股'!L144:M144) -> 31607.265 | G3: ='15股'!X144 -> -0.01369951 | I3: ='15股'!Z144 -> -0.24262861
A4: 2015 | B4: 存股 | C4: =存股!P30 -> -2577.94 | D4: =存股!G30 -> 328900 | F4: =SUM(存股!H30,存股!L30:M30) -> 376 | G4: =存股!X30 -> -0.0078380663 | I4: =存股!Z30 -> -6.2059621e-05
A5: 2016 | B5: 股票 | C5: ='16股'!P54 -> -24718 | D5: ='16股'!G54 -> 1740430 | F5: =SUM('16股'!H54,'16股'!L54:M54) -> 8165 | G5: ='16股'!X54 -> -0.014202237 | I5: ='16股'!Z54 -> -0.45754309 | J5: 阿水一式
A6: 2016 | B6: 存股 | C6: =存股!P31 -> -2859 | D6: =存股!G31 -> 96700 | F6: =SUM(存股!H31,存股!L31:M31) -> 509 | G6: =存股!X31 -> -0.029565667 | I6: =存股!Z31 -> -0.00023666987
A7: 2016 | B7: 期權 | C7: ='16期'!I692 -> -196694 | F7: ='16期'!G692 -> 73128 | G7: ='16期'!J692 -> -0.51761579 | I7: ='16期'!L692 -> -1.0878632 | J7: 阿水期權專班
A8: 2017 | B8: 股票 | C8: =SUM('17股'!P37:R37) -> -9215.02 | D8: ='17股'!G37 -> 856390 | F8: =SUM('17股'!H37,'17股'!L37:M37) -> 4062 | G8: ='17股'!X37 -> -0.013410969 | I8: ='17股'!Z37 -> -0.25763429 | J8: 阿水學院
A9: 2017 | B9: 期權 | C9: ='17期'!I378 -> -30008 | F9: ='17期'!G378 -> 12858 | G9: ='17期'!J378 -> -0.6456388 | J9: 阿水心魔班
A10: 2018 | B10: 股票 | C10: =SUM('18股'!P21:R21) -> -8655 | D10: ='18股'!G21 -> 163650 | F10: =SUM('18股'!H21,'18股'!L21:M21) -> 755 | G10: ='18股'!X21 -> -0.052887259 | I10: ='18股'!Z21 -> -1.3802953 | J10: 阿水學院
A11: 2018 | B11: 期權 | C11: ='18期'!H1852 -> -39537 | F11: ='18期'!F1852 -> 17208 | G11: ='18期'!I1852 -> -0.31743878 | J11: 阿水制霸班
A12: 2019 | B12: 股票 | C12: ='19股'!P18 -> -5332.5 | D12: ='19股'!G18 -> 70900 | F12: =SUM('19股'!H18,'19股'!L18:M18) -> 312.5 | G12: ='19股'!X18 -> -0.075211566 | I12: ='19股'!Z18 -> -2.6195592 | J12: 阿水學院
A13: 2019 | B13: 期權 | C13: ='19期'!H290 -> -45194 | F13: ='19期'!F290 -> 7526 | G13: ='19期'!I290 -> -0.56950955
A14: 2021 | B14: 期權(共) | C14: -100000 | F14: ='19期'!F291 -> 103194 | G14: ='19期'!I291 -> -2.1376074
A15: 2022 | B15: 期權 | C15: ='Even 期權'!L16 -> -12453
A16: 2023 | B16: 期權 | C16: ='Even 期權'!L22 -> -4988
A17: 2024 | B17: 期權 | C17: ='Even 期權'!L151 -> -70451
A18: 2025 | B18: 期權 | C18: ='Even 期權'!L1007 -> -313818
A19: 2025 | B19: 股票 | C19: ='2025'!P126 -> -24467.26 | D19: ='2025'!G126 -> 7186798.2 | F19: =SUM('2025'!H126,'2025'!L126:M126) -> 5940 | G19: ='2025'!X126 -> 0.011833651 | I19: ='2025'!Z126 -> 0.15872091
C21: =SUM(C2:C20) -> -1013195.7 | D21: =SUM(D2:D20) -> 20348276 | F21: =SUM(F2:F20) -> 280264.77 | G21: =C21/D21 -> -0.049792704 | I21: -0.73595948

Sheet Even 期權
A1: 成交日期 | B1: 商品代號 | C1: 商品名稱 | D1: 新／平 | E1: 買賣別 | F1: 當沖 | G1: 成交量 | H1: 成交價 | I1: 權利金 | J1: 手續費 | K1: 交易稅 | L1: 投資損益 | N1: 損益
A2: 44562 | C2: 入金 | L2: 91259 | M2: =L2 -> 91259
A3: 44657 | B3: TXO | C3: 週W1 C 02 17700 C | D3: 新倉 | E3: 賣 | F3: - | G3: 1 | H3: 98 | I3: =IF(OR(AND(D3="新倉",E3="買"),AND(D3="平倉",E3="賣")),-G3*H3*50,G3*H3*50) -> 4900 | J3: 18 | K3: 6 | L3: =IF(B3="TXO",I3-SUM(J3:K3),IF(B3="FITX",IF(D3="新倉",-SUM(J3:K3),IF(E3="賣",(H3-H2)*G3*200-SUM(J3:K3),(H2-H3)*G3*200-SUM(J3:K3))),IF(D3="新倉",-SUM(J3:K3),IF(E3="賣",(H3-H2)*G3*50-SUM(J3:K3),(H2-H3)*G3*50-SUM(J3:K3))))) -> 4876 | M3: =L3 -> 4876 | O3: 放棄 | P3: 元大期貨
A4: 44657 | B4: TXO | C4: 週W1 C 02 17600 C | D4: 新倉 | E4: 買 | F4: - | G4: 1 | H4: 137 | I4: =IF(OR(AND(D4="新倉",E4="買"),AND(D4="平倉",E4="賣")),-G4*H4*50,G4*H4*50) -> -6850 | J4: 18 | K4: 6 | L4: =IF(B4="TXO",I4-SUM(J4:K4),IF(B4="FITX",IF(D4="新倉",-SUM(J4:K4),IF(E4="賣",(H4-H3)*G4*200-SUM(J4:K4),(H3-H4)*G4*200-SUM(J4:K4))),IF(D4="新倉",-SUM(J4:K4),IF(E4="賣",(H4-H3)*G4*50-SUM(J4:K4),(H3-H4)*G4*50-SUM(J4:K4))))) -> -6874 | M4: =L4 -> -6874 | O4: 放棄 | P4: 元大期貨
A5: 44658 | B5: FIMTX | C5: 小指05 | D5: 新倉 | E5: 買 | F5: - | G5: 2 | H5: 17361 | I5: 0 | J5: 46 | K5: 34 | L5: =IF(B5="TXO",I5-SUM(J5:K5),IF(B5="FITX",IF(D5="新倉",-SUM(J5:K5),IF(E5="賣",(H5-H4)*G5*200-SUM(J5:K5),(H4-H5)*G5*200-SUM(J5:K5))),IF(D5="新倉",-SUM(J5:K5),IF(E5="賣",(H5-H4)*G5*50-SUM(J5:K5),(H4-H5)*G5*50-SUM(J5:K5))))) -> -80 | M5: =L5 -> -80 | N5: =IF(B5="TXO","",IF(D5="新倉","",IF(E5="賣",(H5-#REF!)*G5,(#REF!-H5)*G5))) | O5: 新倉 | P5: 元大期貨
A6: 44658 | B6: FIMTX | C6: 小指05 | D6: 平倉 | E6: 賣 | F6: - | G6: 2 | H6: 17346 | I6: 0 | J6: 46 | K6: 34 | L6: =IF(B6="TXO",I6-SUM(J6:K6),IF(B6="FITX",IF(D6="新倉",-SUM(J6:K6),IF(E6="賣",(H6-H5)*G6*200-SUM(J6:K6),(H5-H6)*G6*200-SUM(J6:K6))),IF(D6="新倉",-SUM(J6:K6),IF(E6="賣",(H6-H5)*G6*50-SUM(J6:K6),(H5-H6)*G6*50-SUM(J6:K6))))) -> -1580 | M6: =L6 -> -1580 | N6: =IF(B6="TXO","",IF(D6="新倉","",IF(E6="賣",(H6-H5)*G6,(H5-H6)*G6))) -> -30 | O6: 平倉 | P6: 元大期貨
A7: 44727 | B7: TXO | C7: 週W2 P 02 15900 P | D7: 新倉 | E7: 買 | F7: - | G7: 1 | H7: 26 | I7: =IF(OR(AND(D7="新倉",E7="買"),AND(D7="平倉",E7="賣")),-G7*H7*50,G7*H7*50) -> -1300 | J7: 18 | K7: 1 | L7: =IF(B7="TXO",I7-SUM(J7:K7),IF(B7="FITX",IF(D7="新倉",-SUM(J7:K7),IF(E7="賣",(H7-H6)*G7*200-SUM(J7:K7),(H6-H7)*G7*200-SUM(J7:K7))),IF(D7="新倉",-SUM(J7:K7),IF(E7="賣",(H7-H6)*G7*50-SUM(J7:K7),(H6-H7)*G7*50-SUM(J7:K7))))) -> -1319 | M7: =L7 -> -1319 | O7: 放棄 | P7: 元大期貨
A8: 44740 | B8: TXO | C8: 週W5 C 02 16650 C | D8: 新倉 | E8: 賣 | F8: - | G8: 1 | H8: 23 | I8: =IF(OR(AND(D8="新倉",E8="買"),AND(D8="平倉",E8="賣")),-G8*H8*50,G8*H8*50) -> 1150 | J8: 18 | K8: 2 | L8: =IF(B8="TXO",I8-SUM(J8:K8),IF(B8="FITX",IF(D8="新倉",-SUM(J8:K8),IF(E8="賣",(H8-H7)*G8*200-SUM(J8:K8),(H7-H8)*G8*200-SUM(J8:K8))),IF(D8="新倉",-SUM(J8:K8),IF(E8="賣",(H8-H7)*G8*50-SUM(J8:K8),(H7-H8)*G8*50-SUM(J8:K8))))) -> 1130 | M8: =L8 -> 1130 | O8: 放棄 | P8: 元大期貨
A9: 44740 | B9: TXO | C9: 週W5 C 02 16550 C | D9: 新倉 | E9: 買 | F9: - | G9: 1 | H9: 53 | I9: =IF(OR(AND(D9="新倉",E9="買"),AND(D9="平倉",E9="賣")),-G9*H9*50,G9*H9*50) -> -2650 | J9: 18 | K9: 2 | L9: =IF(B9="TXO",I9-SUM(J9:K9),IF(B9="FITX",IF(D9="新倉",-SUM(J9:K9),IF(E9="賣",(H9-H8)*G9*200-SUM(J9:K9),(H8-H9)*G9*200-SUM(J9:K9))),IF(D9="新倉",-SUM(J9:K9),IF(E9="賣",(H9-H8)*G9*50-SUM(J9:K9),(H8-H9)*G9*50-SUM(J9:K9))))) -> -2670 | M9: =L9 -> -2670 | O9: 放棄 | P9: 元大期貨
A10: 44755 | B10: TXO | C10: 週W2 P 02 13800 P | D10: 新倉 | E10: 買 | F10: - | G10: 2 | H10: 3 | I10: =IF(OR(AND(D10="新倉",E10="買"),AND(D10="平倉",E10="賣")),-G10*H10*50,G10*H10*50) -> -300 | J10: 36 | L10: =IF(B10="TXO",I10-SUM(J10:K10),IF(B10="FITX",IF(D10="新倉",-SUM(J10:K10),IF(E10="賣",(H10-H9)*G10*200-SUM(J10:K10),(H9-H10)*G10*200-SUM(J10:K10))),IF(D10="新倉",-SUM(J10:K10),IF(E10="賣",(H10-H9)*G10*50-SUM(J10:K10),(H9-H10)*G10*50-SUM(J10:K10))))) -> -336 | M10: =L10 -> -336 | O10: 放棄 | P10: 元大期貨
A11: 44755 | B11: TXO | C11: 週W2 P 02 13850 P | D11: 新倉 | E11: 買 | F11: - | G11: 2 | H11: 4 | I11: =IF(OR(AND(D11="新倉",E11="買"),AND(D11="平倉",E11="賣")),-G11*H11*50,G11*H11*50) -> -400 | J11: 36 | L11: =IF(B11="TXO",I11-SUM(J11:K11),IF(B11="FITX",IF(D11="新倉",-SUM(J11:K11),IF(E11="賣",(H11-H10)*G11*200-SUM(J11:K11),(H10-H11)*G11*200-SUM(J11:K11))),IF(D11="新倉",-SUM(J11:K11),IF(E11="賣",(H11-H10)*G11*50-SUM(J11:K11),(H10-H11)*G11*50-SUM(J11:K11))))) -> -436 | M11: =L11 -> -436 | O11: 放棄 | P11: 元大期貨
A12: 44763 | B12: TXO | C12: 週W4 P 02 14550 P | D12: 新倉 | E12: 買 | F12: - | G12: 1 | H12: 60 | I12: =IF(OR(AND(D12="新倉",E12="買"),AND(D12="平倉",E12="賣")),-G12*H12*50,G12*H12*50) -> -3000 | J12: 18 | K12: 3 | L12: =IF(B12="TXO",I12-SUM(J12:K12),IF(B12="FITX",IF(D12="新倉",-SUM(J12:K12),IF(E12="賣",(H12-H11)*G12*200-SUM(J12:K12),(H11-H12)*G12*200-SUM(J12:K12))),IF(D12="新倉",-SUM(J12:K12),IF(E12="賣",(H12-H11)*G12*50-SUM(J12:K12),(H11-H12)*G12*50-SUM(J12:K12))))) -> -3021 | M12: =L12 -> -3021 | O12: 放棄 | P12: 元大期貨
A13: 44851 | B13: TXO | C13: 週W5 C 02 13350 C | D13: 新倉 | E13: 買 | F13: - | G13: 1 | H13: 20 | I13: =IF(OR(AND(D13="新倉",E13="買"),AND(D13="平倉",E13="賣")),-G13*H13*50,G13*H13*50) -> -1000 | J13: 18 | K13: 1 | L13: =IF(B13="TXO",I13-SUM(J13:K13),IF(B13="FITX",IF(D13="新倉",-SUM(J13:K13),IF(E13="賣",(H13-H12)*G13*200-SUM(J13:K13),(H12-H13)*G13*200-SUM(J13:K13))),IF(D13="新倉",-SUM(J13:K13),IF(E13="賣",(H13-H12)*G13*50-SUM(J13:K13),(H12-H13)*G13*50-SUM(J13:K13))))) -> -1019 | M13: =L13 -> -1019 | O13: 放棄 | P13: 元大期貨
A14: 44901 | B14: TXO | C14: 週W1 C 02 15200 C | D14: 新倉 | E14: 買 | F14: - | G14: 2 | H14: 7.2 | I14: =IF(OR(AND(D14="新倉",E14="買"),AND(D14="平倉",E14="賣")),-G14*H14*50,G14*H14*50) -> -720 | J14: 27 | L14: =IF(B14="TXO",I14-SUM(J14:K14),IF(B14="FITX",IF(D14="新倉",-SUM(J14:K14),IF(E14="賣",(H14-H13)*G14*200-SUM(J14:K14),(H13-H14)*G14*200-SUM(J14:K14))),IF(D14="新倉",-SUM(J14:K14),IF(E14="賣",(H14-H13)*G14*50-SUM(J14:K14),(H13-H14)*G14*50-SUM(J14:K14))))) -> -747 | M14: =L14 -> -747 | O14: 放棄 | P14: 元大期貨
A15: 44901 | B15: TXO | C15: 週W1 C 02 15200 C | D15: 新倉 | E15: 買 | F15: - | G15: 1 | H15: 7 | I15: =IF(OR(AND(D15="新倉",E15="買"),AND(D15="平倉",E15="賣")),-G15*H15*50,G15*H15*50) -> -350 | J15: 27 | L15: =IF(B15="TXO",I15-SUM(J15:K15),IF(B15="FITX",IF(D15="新倉",-SUM(J15:K15),IF(E15="賣",(H15-H14)*G15*200-SUM(J15:K15),(H14-H15)*G15*200-SUM(J15:K15))),IF(D15="新倉",-SUM(J15:K15),IF(E15="賣",(H15-H14)*G15*50-SUM(J15:K15),(H14-H15)*G15*50-SUM(J15:K15))))) -> -377 | M15: =L15 -> -377 | O15: 放棄 | P15: 元大期貨
A16: 2022總計 | B16: 帳戶餘額 | C16: =M2+M16 -> 78806 | L16: =SUM(L3:L15) -> -12453 | M16: =SUM(M3:M15) -> -12453
A17: 44927 | C17: 出金 | L17: 40000 | M17: =L17 -> 40000
A18: 44927 | C18: 2022 帳戶餘額 | L18: 38806 | M18: =L18 -> 38806
A19: 44957 | B19: TXO | C19: 週W1 C 02 15800 C | D19: 新倉 | E19: 買 | F19: - | G19: 10 | H19: 2.6 | I19: =IF(D19="新倉",-G19*H19*50,G19*H19*50) -> -1300 | J19: 180 | K19: 0 | L19: =IF(B19="TXO",I19-SUM(J19:K19),IF(B19="FITX",IF(D19="新倉",-SUM(J19:K19),IF(E19="賣",(H19-H18)*G19*200-SUM(J19:K19),(H18-H19)*G19*200-SUM(J19:K19))),IF(D19="新倉",-SUM(J19:K19),IF(E19="賣",(H19-H18)*G19*50-SUM(J19:K19),(H18-H19)*G19*50-SUM(J19:K19))))) -> -1480 | M19: =L19 -> -1480 | O19: 放棄 | P19: 元大期貨
A20: 44958 | B20: TXO | C20: 週W1 C 02 15400 C | D20: 新倉 | E20: 買 | F20: - | G20: 2 | H20: 10 | I20: =IF(D20="新倉",-G20*H20*50,G20*H20*50) -> -1000 | J20: 36 | K20: 2 | L20: =IF(B20="TXO",I20-SUM(J20:K20),IF(B20="FITX",IF(D20="新倉",-SUM(J20:K20),IF(E20="賣",(H20-H19)*G20*200-SUM(J20:K20),(H19-H20)*G20*200-SUM(J20:K20))),IF(D20="新倉",-SUM(J20:K20),IF(E20="賣",(H20-H19)*G20*50-SUM(J20:K20),(H19-H20)*G20*50-SUM(J20:K20))))) -> -1038 | M20: =L20 -> -1038 | O20: 放棄 | P20: 元大期貨
A21: 44998 | B21: TXO | C21: 週W2 P 02 15250 P | D21: 新倉 | E21: 買 | F21: - | G21: 1 | H21: 49 | I21: =IF(D21="新倉",-G21*H21*50,G21*H21*50) -> -2450 | J21: 18 | K21: 2 | L21: =IF(B21="TXO",I21-SUM(J21:K21),IF(B21="FITX",IF(D21="新倉",-SUM(J21:K21),IF(E21="賣",(H21-H20)*G21*200-SUM(J21:K21),(H20-H21)*G21*200-SUM(J21:K21))),IF(D21="新倉",-SUM(J21:K21),IF(E21="賣",(H21-H20)*G21*50-SUM(J21:K21),(H20-H21)*G21*50-SUM(J21:K21))))) -> -2470 | M21: =L21 -> -2470 | O21: 放棄 | P21: 元大期貨
A22: 2023總計 | B22: 帳戶餘額 | C22: =M18+M22 -> 33818 | L22: =SUM(L19:L21) -> -4988 | M22: =SUM(M19:M21) -> -4988
A23: 45292 | C23: 2023 帳戶餘額 | L23: =C22 -> 33818 | M23: =L23 -> 33818
A24: 45313 | B24: TXO | C24: 週W4 C 01 17900 C | D24: 新倉 | E24: 買 | F24: - | G24: 1 | H24: 43.5 | I24: =IF(D24="新倉",-G24*H24*50,G24*H24*50) -> -2175 | J24: 18 | K24: 2 | L24: =IF(B24="TXO",I24-SUM(J24:K24),IF(B24="FITX",IF(D24="新倉",-SUM(J24:K24),IF(E24="賣",(H24-H23)*G24*200-SUM(J24:K24),(H23-H24)*G24*200-SUM(J24:K24))),IF(D24="新倉",-SUM(J24:K24),IF(E24="賣",(H24-H23)*G24*50-SUM(J24:K24),(H23-H24)*G24*50-SUM(J24:K24))))) -> -2195 | M24: =L24 -> -2195 | N24: =M24 -> -2195 | O24: 放棄 | P24: 元大期貨
A25: 45313 | B25: TXO | C25: 週W4 P 01 17700 P | D25: 新倉 | E25: 買 | F25: - | G25: 1 | H25: 40 | I25: =IF(D25="新倉",-G25*H25*50,G25*H25*50) -> -2000 | J25: 18 | K25: 2 | L25: =IF(B25="TXO",I25-SUM(J25:K25),IF(B25="FITX",IF(D25="新倉",-SUM(J25:K25),IF(E25="賣",(H25-H24)*G25*200-SUM(J25:K25),(H24-H25)*G25*200-SUM(J25:K25))),IF(D25="新倉",-SUM(J25:K25),IF(E25="賣",(H25-H24)*G25*50-SUM(J25:K25),(H24-H25)*G25*50-SUM(J25:K25))))) -> -2020 | M25: =L25 -> -2020 | N25: =M25 -> -2020 | O25: 放棄 | P25: 元大期貨
A26: 1月總計 | L26: =SUM(L24:L25) -> -4215 | M26: =SUM(M24:M25) -> -4215
A27: 45344 | B27: TXO | C27: 週W4 C 02 18950 C | D27: 新倉 | E27: 買 | F27: - | G27: 1 | H27: 43 | I27: =IF(D27="新倉",-G27*H27*50,G27*H27*50) -> -2150 | J27: 18 | K27: 2 | L27: =IF(B27="TXO",I27-SUM(J27:K27),IF(B27="FITX",IF(D27="新倉",-SUM(J27:K27),IF(E27="賣",(H27-H26)*G27*200-SUM(J27:K27),(H26-H27)*G27*200-SUM(J27:K27))),IF(D27="新倉",-SUM(J27:K27),IF(E27="賣",(H27-H26)*G27*50-SUM(J27:K27),(H26-H27)*G27*50-SUM(J27:K27))))) -> -2170 | M27: =L27 -> -2170 | O27: 新倉 | P27: 元大期貨
A28: 45344 | B28: TXO | C28: 週W4 C 02 18950 C | D28: 平倉 | E28: 賣 | F28: - | G28: 1 | H28: 47.5 | I28: =IF(D28="新倉",-G28*H28*50,G28*H28*50) -> 2375 | J28: 18 | K28: 2 | L28: =IF(B28="TXO",I28-SUM(J28:K28),IF(B28="FITX",IF(D28="新倉",-SUM(J28:K28),IF(E28="賣",(H28-H27)*G28*200-SUM(J28:K28),(H27-H28)*G28*200-SUM(J28:K28))),IF(D28="新倉",-SUM(J28:K28),IF(E28="賣",(H28-H27)*G28*50-SUM(J28:K28),(H27-H28)*G28*50-SUM(J28:K28))))) -> 2355 | M28: =L28 -> 2355 | N28: =SUM(M27:M28) -> 185 | O28: 平倉 | P28: 元大期貨
A29: 45349 | B29: TXO | C29: 週W4 C 02 18950 C | D29: 新倉 | E29: 買 | F29: - | G29: 1 | H29: 20 | I29: =IF(D29="新倉",-G29*H29*50,G29*H29*50) -> -1000 | J29: 18 | K29: 1 | L29: =IF(B29="TXO",I29-SUM(J29:K29),IF(B29="FITX",IF(D29="新倉",-SUM(J29:K29),IF(E29="賣",(H29-H28)*G29*200-SUM(J29:K29),(H28-H29)*G29*200-SUM(J29:K29))),IF(D29="新倉",-SUM(J29:K29),IF(E29="賣",(H29-H28)*G29*50-SUM(J29:K29),(H28-H29)*G29*50-SUM(J29:K29))))) -> -1019 | M29: =L29 -> -1019 | O29: 新倉 | P29: 元大期貨
A30: 45351 | B30: TXO | C30: 週W4 C 02 18950 C | D30: 平倉 | E30: 賣 | F30: - | G30: 1 | H30: 43 | I30: =IF(D30="新倉",-G30*H30*50,G30*H30*50) -> 2150 | J30: 18 | K30: 19 | L30: =IF(B30="TXO",I30-SUM(J30:K30),IF(B30="FITX",IF(D30="新倉",-SUM(J30:K30),IF(E30="賣",(H30-H29)*G30*200-SUM(J30:K30),(H29-H30)*G30*200-SUM(J30:K30))),IF(D30="新倉",-SUM(J30:K30),IF(E30="賣",(H30-H29)*G30*50-SUM(J30:K30),(H29-H30)*G30*50-SUM(J30:K30))))) -> 2113 | M30: =L30 -> 2113 | N30: =SUM(M29:M30) -> 1094 | O30: 履約 | P30: 元大期貨
A31: 2月總計 | L31: =SUM(L27:L30) -> 1279 | M31: =SUM(M27:M30) -> 1279
A32: 45371 | B32: TXO | C32: 台選 03P19850 | D32: 新倉 | E32: 買 | F32: - | G32: 1 | H32: 12 | I32: =IF(D32="新倉",-G32*H32*50,G32*H32*50) -> -600 | J32: 18 | K32: 1 | L32: =IF(B32="TXO",I32-SUM(J32:K32),IF(B32="FITX",IF(D32="新倉",-SUM(J32:K32),IF(E32="賣",(H32-H31)*G32*200-SUM(J32:K32),(H31-H32)*G32*200-SUM(J32:K32))),IF(D32="新倉",-SUM(J32:K32),IF(E32="賣",(H32-H31)*G32*50-SUM(J32:K32),(H31-H32)*G32*50-SUM(J32:K32))))) -> -619 | M32: =L32 -> -619 | O32: 新倉 | P32: 元大期貨
A33: 45371 | B33: TXO | C33: 台選 03P19850 | D33: 平倉 | E33: 賣 | F33: - | G33: 1 | H33: 24.5 | I33: =IF(D33="新倉",-G33*H33*50,G33*H33*50) -> 1225 | J33: 18 | K33: 1 | L33: =IF(B33="TXO",I33-SUM(J33:K33),IF(B33="FITX",IF(D33="新倉",-SUM(J33:K33),IF(E33="賣",(H33-H32)*G33*200-SUM(J33:K33),(H32-H33)*G33*200-SUM(J33:K33))),IF(D33="新倉",-SUM(J33:K33),IF(E33="賣",(H33-H32)*G33*50-SUM(J33:K33),(H32-H33)*G33*50-SUM(J33:K33))))) -> 1206 | M33: =L33 -> 1206 | N33: =SUM(M32:M33) -> 587 | O33: 平倉 | P33: 元大期貨
A34: 3月總計 | L34: =SUM(L32:L33) -> 587 | M34: =SUM(M32:M33) -> 587
A35: 45418 | B35: TXO | C35: 週W2 C 05 20850 C | D35: 新倉 | E35: 買 | F35: - | G35: 3 | H35: 27 | I35: =IF(D35="新倉",-G35*H35*50,G35*H35*50) -> -4050 | J35: 54 | K35: 3 | L35: =IF(B35="TXO",I35-SUM(J35:K35),IF(B35="FITX",IF(D35="新倉",-SUM(J35:K35),IF(E35="賣",(H35-H34)*G35*200-SUM(J35:K35),(H34-H35)*G35*200-SUM(J35:K35))),IF(D35="新倉",-SUM(J35:K35),IF(E35="賣",(H35-H34)*G35*50-SUM(J35:K35),(H34-H35)*G35*50-SUM(J35:K35))))) -> -4107 | M35: =L35 -> -4107 | N35: =M35 -> -4107 | O35: 放棄 | P35: 元大期貨
A36: 45418 | B36: TXO | C36: 週W2 C 05 20900 C | D36: 新倉 | E36: 買 | F36: - | G36: 1 | H36: 24 | I36: =IF(D36="新倉",-G36*H36*50,G36*H36*50) -> -1200 | J36: 18 | K36: 1 | L36: =IF(B36="TXO",I36-SUM(J36:K36),IF(B36="FITX",IF(D36="新倉",-SUM(J36:K36),IF(E36="賣",(H36-H35)*G36*200-SUM(J36:K36),(H35-H36)*G36*200-SUM(J36:K36))),IF(D36="新倉",-SUM(J36:K36),IF(E36="賣",(H36-H35)*G36*50-SUM(J36:K36),(H35-H36)*G36*50-SUM(J36:K36))))) -> -1219 | M36: =L36 -> -1219 | N36: =M36 -> -1219 | O36: 放棄 | P36: 元大期貨
A37: 45419 | B37: TXO | C37: 週W2 P 05 20300 P | D37: 新倉 | E37: 買 | F37: - | G37: 1 | H37: 22 | I37: =IF(D37="新倉",-G37*H37*50,G37*H37*50) -> -1100 | J37: 18 | K37: 1 | L37: =IF(B37="TXO",I37-SUM(J37:K37),IF(B37="FITX",IF(D37="新倉",-SUM(J37:K37),IF(E37="賣",(H37-H36)*G37*200-SUM(J37:K37),(H36-H37)*G37*200-SUM(J37:K37))),IF(D37="新倉",-SUM(J37:K37),IF(E37="賣",(H37-H36)*G37*50-SUM(J37:K37),(H36-H37)*G37*50-SUM(J37:K37))))) -> -1119 | M37: =L37 -> -1119 | N37: =M37 -> -1119 | O37: 放棄 | P37: 元大期貨
A38: 5月總計 | L38: =SUM(L35:L37) -> -6445 | M38: =SUM(M35:M37) -> -6445
A39: 45462 | B39: TXO | C39: 台指 P 06 22700 P | D39: 新倉 | E39: 買 | F39: - | G39: 2 | H39: 10 | I39: =IF(D39="新倉",-G39*H39*50,G39*H39*50) -> -1000 | J39: 36 | K39: 2 | L39: =IF(B39="TXO",I39-SUM(J39:K39),IF(B39="FITX",IF(D39="新倉",-SUM(J39:K39),IF(E39="賣",(H39-H38)*G39*200-SUM(J39:K39),(H38-H39)*G39*200-SUM(J39:K39))),IF(D39="新倉",-SUM(J39:K39),IF(E39="賣",(H39-H38)*G39*50-SUM(J39:K39),(H38-H39)*G39*50-SUM(J39:K39))))) -> -1038 | M39: =L39 -> -1038 | N39: =M39 -> -1038 | O39: 放棄 | P39: 元大期貨
A40: 45468 | B40: TXO | C40: TXOW4 06 23050 C | D40: 新倉 | E40: 買 | F40: - | G40: 1 | H40: 20 | I40: =IF(D40="新倉",-G40*H40*50,G40*H40*50) -> -1000 | J40: 18 | K40: 1 | L40: =IF(B40="TXO",I40-SUM(J40:K40),IF(B40="FITX",IF(D40="新倉",-SUM(J40:K40),IF(E40="賣",(H40-H39)*G40*200-SUM(J40:K40),(H39-H40)*G40*200-SUM(J40:K40))),IF(D40="新倉",-SUM(J40:K40),IF(E40="賣",(H40-H39)*G40*50-SUM(J40:K40),(H39-H40)*G40*50-SUM(J40:K40))))) -> -1019 | M40: =L40 -> -1019 | O40: 新倉 | P40: 元大期貨
A41: 45469 | B41: TXO | C41: TXOW4 06 23050 C | D41: 平倉 | E41: 賣 | F41: - | G41: 1 | H41: 80 | I41: =IF(D41="新倉",-G41*H41*50,G41*H41*50) -> 4000 | J41: 18 | K41: 4 | L41: =IF(B41="TXO",I41-SUM(J41:K41),IF(B41="FITX",IF(D41="新倉",-SUM(J41:K41),IF(E41="賣",(H41-H40)*G41*200-SUM(J41:K41),(H40-H41)*G41*200-SUM(J41:K41))),IF(D41="新倉",-SUM(J41:K41),IF(E41="賣",(H41-H40)*G41*50-SUM(J41:K41),(H40-H41)*G41*50-SUM(J41:K41))))) -> 3978 | M41: =L41 -> 3978 | N41: =SUM(M40:M41) -> 2959 | O41: 平倉 | P41: 元大期貨
A42: 6月總計 | L42: =SUM(L39:L41) -> 1921 | M42: =SUM(M39:M41) -> 1921
A43: 45476 | B43: TXO | C43: 週W1 P 07 22650 P | D43: 新倉 | E43: 買 | F43: - | G43: 1 | H43: 20 | I43: =IF(D43="新倉",-G43*H43*50,G43*H43*50) -> -1000 | J43: 18 | K43: 1 | L43: =IF(B43="TXO",I43-SUM(J43:K43),IF(B43="FITX",IF(D43="新倉",-SUM(J43:K43),IF(E43="賣",(H43-H42)*G43*200-SUM(J43:K43),(H42-H43)*G43*200-SUM(J43:K43))),IF(D43="新倉",-SUM(J43:K43),IF(E43="賣",(H43-H42)*G43*50-SUM(J43:K43),(H42-H43)*G43*50-SUM(J43:K43))))) -> -1019 | M43: =L43 -> -1019 | N43: =M43 -> -1019 | O43: 放棄 | P43: 元大期貨
A44: 45482 | B44: TXO | C44: TXOW2 07 24200 C | D44: 新倉 | E44: 買 | F44: - | G44: 1 | H44: 30 | I44: -1500 | J44: 18 | K44: 2 | L44: =IF(B44="TXO",I44-SUM(J44:K44),IF(B44="FITX",IF(D44="新倉",-SUM(J44:K44),IF(E44="賣",(H44-H43)*G44*200-SUM(J44:K44),(H43-H44)*G44*200-SUM(J44:K44))),IF(D44="新倉",-SUM(J44:K44),IF(E44="賣",(H44-H43)*G44*50-SUM(J44:K44),(H43-H44)*G44*50-SUM(J44:K44))))) -> -1520 | M44: =L44 -> -1520 | N44: =M44 -> -1520 | O44: 放棄 | P44: 元大期貨
A45: 45482 | B45: TXO | C45: TXOW2 07 23600 P | D45: 新倉 | E45: 買 | F45: - | G45: 1 | H45: 29 | I45: -1450 | J45: 18 | K45: 1 | L45: =IF(B45="TXO",I45-SUM(J45:K45),IF(B45="FITX",IF(D45="新倉",-SUM(J45:K45),IF(E45="賣",(H45-H44)*G45*200-SUM(J45:K45),(H44-H45)*G45*200-SUM(J45:K45))),IF(D45="新倉",-SUM(J45:K45),IF(E45="賣",(H45-H44)*G45*50-SUM(J45:K45),(H44-H45)*G45*50-SUM(J45:K45))))) -> -1469 | M45: =L45 -> -1469 | N45: =M45 -> -1469 | O45: 放棄 | P45: 元大期貨
A46: 45489 | B46: TXO | C46: 台指選 07 24100 C | D46: 新倉 | E46: 買 | F46: - | G46: 1 | H46: 48.5 | I46: -2425 | J46: 18 | K46: 2 | L46: =IF(B46="TXO",I46-SUM(J46:K46),IF(B46="FITX",IF(D46="新倉",-SUM(J46:K46),IF(E46="賣",(H46-H45)*G46*200-SUM(J46:K46),(H45-H46)*G46*200-SUM(J46:K46))),IF(D46="新倉",-SUM(J46:K46),IF(E46="賣",(H46-H45)*G46*50-SUM(J46:K46),(H45-H46)*G46*50-SUM(J46:K46))))) -> -2445 | M46: =L46 -> -2445 | O46: 新倉 | P46: 元大期貨
A47: 45489 | B47: TXO | C47: 台指選 07 24100 C | D47: 平倉 | E47: 賣 | F47: - | G47: 1 | H47: 47.5 | I47: 2375 | J47: 18 | K47: 2 | L47: =IF(B47="TXO",I47-SUM(J47:K47),IF(B47="FITX",IF(D47="新倉",-SUM(J47:K47),IF(E47="賣",(H47-H46)*G47*200-SUM(J47:K47),(H46-H47)*G47*200-SUM(J47:K47))),IF(D47="新倉",-SUM(J47:K47),IF(E47="賣",(H47-H46)*G47*50-SUM(J47:K47),(H46-H47)*G47*50-SUM(J47:K47))))) -> 2355 | M47: =L47 -> 2355 | N47: =SUM(M46:M47) -> -90 | O47: 平倉 | P47: 元大期貨
A48: 45489 | B48: TXO | C48: 台指選 07 24200 C | D48: 新倉 | E48: 賣 | F48: - | G48: 1 | H48: 24 | I48: 1200 | J48: 18 | K48: 1 | L48: =IF(B48="TXO",I48-SUM(J48:K48),IF(B48="FITX",IF(D48="新倉",-SUM(J48:K48),IF(E48="賣",(H48-H47)*G48*200-SUM(J48:K48),(H47-H48)*G48*200-SUM(J48:K48))),IF(D48="新倉",-SUM(J48:K48),IF(E48="賣",(H48-H47)*G48*50-SUM(J48:K48),(H47-H48)*G48*50-SUM(J48:K48))))) -> 1181 | M48: =L48 -> 1181 | O48: 新倉 | P48: 元大期貨
A49: 45489 | B49: TXO | C49: 台指選 07 24200 C | D49: 平倉 | E49: 買 | F49: - | G49: 1 | H49: 24.5 | I49: -1225 | J49: 18 | K49: 1 | L49: =IF(B49="TXO",I49-SUM(J49:K49),IF(B49="FITX",IF(D49="新倉",-SUM(J49:K49),IF(E49="賣",(H49-H48)*G49*200-SUM(J49:K49),(H48-H49)*G49*200-SUM(J49:K49))),IF(D49="新倉",-SUM(J49:K49),IF(E49="賣",(H49-H48)*G49*50-SUM(J49:K49),(H48-H49)*G49*50-SUM(J49:K49))))) -> -1244 | M49: =L49 -> -1244 | N49: =SUM(M48:M49) -> -63 | O49: 平倉 | P49: 元大期貨
A50: 45489 | B50: TXO | C50: 台指選 07 24100 C | D50: 新倉 | E50: 買 | F50: - | G50: 1 | H50: 50 | I50: -2500 | J50: 18 | K50: 3 | L50: =IF(B50="TXO",I50-SUM(J50:K50),IF(B50="FITX",IF(D50="新倉",-SUM(J50:K50),IF(E50="賣",(H50-H49)*G50*200-SUM(J50:K50),(H49-H50)*G50*200-SUM(J50:K50))),IF(D50="新倉",-SUM(J50:K50),IF(E50="賣",(H50-H49)*G50*50-SUM(J50:K50),(H49-H50)*G50*50-SUM(J50:K50))))) -> -2521 | M50: =L50 -> -2521 | O50: 新倉 | P50: 元大期貨
A51: 45489 | B51: TXO | C51: 台指選 07 24200 C | D51: 新倉 | E51: 賣 | F51: - | G51: 1 | H51: 24.5 | I51: 1225 | J51: 18 | K51: 1 | L51: =IF(B51="TXO",I51-SUM(J51:K51),IF(B51="FITX",IF(D51="新倉",-SUM(J51:K51),IF(E51="賣",(H51-H50)*G51*200-SUM(J51:K51),(H50-H51)*G51*200-SUM(J51:K51))),IF(D51="新倉",-SUM(J51:K51),IF(E51="賣",(H51-H50)*G51*50-SUM(J51:K51),(H50-H51)*G51*50-SUM(J51:K51))))) -> 1206 | M51: =L51 -> 1206 | O51: 新倉 | P51: 元大期貨
A52: 45490 | B52: TXO | C52: 台指選 07 24100 C | D52: 平倉 | E52: 賣 | F52: - | G52: 1 | H52: 12.5 | I52: 625 | J52: 18 | K52: 1 | L52: =IF(B52="TXO",I52-SUM(J52:K52),IF(B52="FITX",IF(D52="新倉",-SUM(J52:K52),IF(E52="賣",(H52-H51)*G52*200-SUM(J52:K52),(H51-H52)*G52*200-SUM(J52:K52))),IF(D52="新倉",-SUM(J52:K52),IF(E52="賣",(H52-H51)*G52*50-SUM(J52:K52),(H51-H52)*G52*50-SUM(J52:K52))))) -> 606 | M52: =L52 -> 606 | O52: 平倉 | P52: 元大期貨
A53: 45490 | B53: TXO | C53: 台指選 07 24200 C | D53: 平倉 | E53: 買 | F53: - | G53: 1 | H53: 3.2 | I53: -160 | J53: 18 | K53: 0 | L53: =IF(B53="TXO",I53-SUM(J53:K53),IF(B53="FITX",IF(D53="新倉",-SUM(J53:K53),IF(E53="賣",(H53-H52)*G53*200-SUM(J53:K53),(H52-H53)*G53*200-SUM(J53:K53))),IF(D53="新倉",-SUM(J53:K53),IF(E53="賣",(H53-H52)*G53*50-SUM(J53:K53),(H52-H53)*G53*50-SUM(J53:K53))))) -> -178 | M53: =L53 -> -178 | N53: =SUM(M50:M53) -> -887 | O53: 平倉 | P53: 元大期貨
A54: 45490 | B54: TXO | C54: 台指選 07 23750 P | D54: 新倉 | E54: 買 | F54: - | G54: 1 | H54: 17.5 | I54: -875 | J54: 18 | K54: 1 | L54: =IF(B54="TXO",I54-SUM(J54:K54),IF(B54="FITX",IF(D54="新倉",-SUM(J54:K54),IF(E54="賣",(H54-H53)*G54*200-SUM(J54:K54),(H53-H54)*G54*200-SUM(J54:K54))),IF(D54="新倉",-SUM(J54:K54),IF(E54="賣",(H54-H53)*G54*50-SUM(J54:K54),(H53-H54)*G54*50-SUM(J54:K54))))) -> -894 | M54: =L54 -> -894 | O54: 新倉 | P54: 元大期貨
A55: 45490 | B55: TXO | C55: 台指選 07 23750 P | D55: 平倉 | E55: 賣 | F55: - | G55: 1 | H55: 94 | I55: 4700 | J55: 18 | K55: 5 | L55: =IF(B55="TXO",I55-SUM(J55:K55),IF(B55="FITX",IF(D55="新倉",-SUM(J55:K55),IF(E55="賣",(H55-H54)*G55*200-SUM(J55:K55),(H54-H55)*G55*200-SUM(J55:K55))),IF(D55="新倉",-SUM(J55:K55),IF(E55="賣",(H55-H54)*G55*50-SUM(J55:K55),(H54-H55)*G55*50-SUM(J55:K55))))) -> 4677 | M55: =L55 -> 4677 | N55: =SUM(M54:M55) -> 3783 | O55: 平倉 | P55: 元大期貨
A56: 45490 | B56: TXO | C56: 台指選 07 23850 C | D56: 新倉 | E56: 買 | F56: - | G56: 1 | H56: 60 | I56: -3000 | J56: 18 | K56: 3 | L56: =IF(B56="TXO",I56-SUM(J56:K56),IF(B56="FITX",IF(D56="新倉",-SUM(J56:K56),IF(E56="賣",(H56-H55)*G56*200-SUM(J56:K56),(H55-H56)*G56*200-SUM(J56:K56))),IF(D56="新倉",-SUM(J56:K56),IF(E56="賣",(H56-H55)*G56*50-SUM(J56:K56),(H55-H56)*G56*50-SUM(J56:K56))))) -> -3021 | M56: =L56 -> -3021 | O56: 新倉 | P56: 元大期貨
A57: 45490 | B57: TXO | C57: 台指選 07 23850 C | D57: 平倉 | E57: 賣 | F57: - | G57: 1 | H57: 140 | I57: 7000 | J57: 18 | K57: 7 | L57: =IF(B57="TXO",I57-SUM(J57:K57),IF(B57="FITX",IF(D57="新倉",-SUM(J57:K57),IF(E57="賣",(H57-H56)*G57*200-SUM(J57:K57),(H56-H57)*G57*200-SUM(J57:K57))),IF(D57="新倉",-SUM(J57:K57),IF(E57="賣",(H57-H56)*G57*50-SUM(J57:K57),(H56-H57)*G57*50-SUM(J57:K57))))) -> 6975 | M57: =L57 -> 6975 | N57: =SUM(M49:M57) -> 5606 | O57: 平倉 | P57: 元大期貨
A58: 45495 | B58: TXO | C58: 台指選W4 07 21600 P | D58: 新倉 | E58: 買 | F58: - | G58: 1 | H58: 14.5 | I58: -725 | J58: 18 | K58: 1 | L58: =IF(B58="TXO",I58-SUM(J58:K58),IF(B58="FITX",IF(D58="新倉",-SUM(J58:K58),IF(E58="賣",(H58-H57)*G58*200-SUM(J58:K58),(H57-H58)*G58*200-SUM(J58:K58))),IF(D58="新倉",-SUM(J58:K58),IF(E58="賣",(H58-H57)*G58*50-SUM(J58:K58),(H57-H58)*G58*50-SUM(J58:K58))))) -> -744 | M58: =L58 -> -744 | N58: =M58 -> -744 | O58: 放棄 | P58: 元大期貨
A59: 45496 | B59: TXO | C59: 台指選W4 07 22200 P | D59: 新倉 | E59: 買 | F59: - | G59: 1 | H59: 25 | I59: -1250 | J59: 18 | K59: 1 | L59: =IF(B59="TXO",I59-SUM(J59:K59),IF(B59="FITX",IF(D59="新倉",-SUM(J59:K59),IF(E59="賣",(H59-H58)*G59*200-SUM(J59:K59),(H58-H59)*G59*200-SUM(J59:K59))),IF(D59="新倉",-SUM(J59:K59),IF(E59="賣",(H59-H58)*G59*50-SUM(J59:K59),(H58-H59)*G59*50-SUM(J59:K59))))) -> -1269 | M59: =L59 -> -1269 | O59: 平倉 | P59: 元大期貨
A60: 45496 | B60: TXO | C60: 台指選W4 07 22300 P | D60: 新倉 | E60: 買 | F60: - | G60: 1 | H60: 19 | I60: -950 | J60: 18 | K60: 1 | L60: =IF(B60="TXO",I60-SUM(J60:K60),IF(B60="FITX",IF(D60="新倉",-SUM(J60:K60),IF(E60="賣",(H60-H59)*G60*200-SUM(J60:K60),(H59-H60)*G60*200-SUM(J60:K60))),IF(D60="新倉",-SUM(J60:K60),IF(E60="賣",(H60-H59)*G60*50-SUM(J60:K60),(H59-H60)*G60*50-SUM(J60:K60))))) -> -969 | M60: =L60 -> -969 | O60: 新倉 | P60: 元大期貨
A61: 45499 | B61: TXO | C61: 台指選W4 07 22300 P | D61: 平倉 | E61: 賣 | F61: - | G61: 1 | H61: 249 | I61: 12450 | J61: 18 | K61: 12 | L61: =IF(B61="TXO",I61-SUM(J61:K61),IF(B61="FITX",IF(D61="新倉",-SUM(J61:K61),IF(E61="賣",(H61-H60)*G61*200-SUM(J61:K61),(H60-H61)*G61*200-SUM(J61:K61))),IF(D61="新倉",-SUM(J61:K61),IF(E61="賣",(H61-H60)*G61*50-SUM(J61:K61),(H60-H61)*G61*50-SUM(J61:K61))))) -> 12420 | M61: =L61 -> 12420 | N61: =SUM(M60:M61) -> 11451 | O61: 平倉 | P61: 元大期貨
A62: 45499 | B62: TXO | C62: 台指選W4 07 22300 C | D62: 新倉 | E62: 買 | F62: - | G62: 1 | H62: 25 | I62: -1250 | J62: 18 | K62: 1 | L62: =IF(B62="TXO",I62-SUM(J62:K62),IF(B62="FITX",IF(D62="新倉",-SUM(J62:K62),IF(E62="賣",(H62-H61)*G62*200-SUM(J62:K62),(H61-H62)*G62*200-SUM(J62:K62))),IF(D62="新倉",-SUM(J62:K62),IF(E62="賣",(H62-H61)*G62*50-SUM(J62:K62),(H61-H62)*G62*50-SUM(J62:K62))))) -> -1269 | M62: =L62 -> -1269 | N62: =M62 -> -1269 | O62: 放棄 | P62: 元大期貨
A63: 45499 | B63: TXO | C63: 台指選W4 07 22200 P | D63: 平倉 | E63: 賣 | F63: - | G63: 1 | H63: 87 | I63: 4350 | J63: 18 | K63: 4 | L63: =IF(B63="TXO",I63-SUM(J63:K63),IF(B63="FITX",IF(D63="新倉",-SUM(J63:K63),IF(E63="賣",(H63-H62)*G63*200-SUM(J63:K63),(H62-H63)*G63*200-SUM(J63:K63))),IF(D63="新倉",-SUM(J63:K63),IF(E63="賣",(H63-H62)*G63*50-SUM(J63:K63),(H62-H63)*G63*50-SUM(J63:K63))))) -> 4328 | M63: =L63 -> 4328 | N63: =SUM(M59,M63) -> 3059 | O63: 平倉 | P63: 元大期貨
A64: 45502 | B64: TXO | C64: TXOW5 07 22400 C | D64: 新倉 | E64: 買 | F64: - | G64: 1 | H64: 119 | I64: -5950 | J64: 18 | K64: 6 | L64: =IF(B64="TXO",I64-SUM(J64:K64),IF(B64="FITX",IF(D64="新倉",-SUM(J64:K64),IF(E64="賣",(H64-H63)*G64*200-SUM(J64:K64),(H63-H64)*G64*200-SUM(J64:K64))),IF(D64="新倉",-SUM(J64:K64),IF(E64="賣",(H64-H63)*G64*50-SUM(J64:K64),(H63-H64)*G64*50-SUM(J64:K64))))) -> -5974 | M64: =L64 -> -5974 | N64: =M64 -> -5974 | O64: 放棄 | P64: 元大期貨
A65: 45502 | B65: TXO | C65: TXOW5 07 22450 C | D65: 新倉 | E65: 賣 | F65: - | G65: 1 | H65: 96 | I65: 4800 | J65: 18 | K65: 5 | L65: =IF(B65="TXO",I65-SUM(J65:K65),IF(B65="FITX",IF(D65="新倉",-SUM(J65:K65),IF(E65="賣",(H65-H64)*G65*200-SUM(J65:K65),(H64-H65)*G65*200-SUM(J65:K65))),IF(D65="新倉",-SUM(J65:K65),IF(E65="賣",(H65-H64)*G65*50-SUM(J65:K65),(H64-H65)*G65*50-SUM(J65:K65))))) -> 4777 | M65: =L65 -> 4777 | N65: =M65 -> 4777 | O65: 放棄 | P65: 元大期貨
A66: 45502 | B66: TXO | C66: TXOW5 07 22500 C | D66: 新倉 | E66: 買 | F66: - | G66: 1 | H66: 135 | I66: -6750 | J66: 18 | K66: 7 | L66: =IF(B66="TXO",I66-SUM(J66:K66),IF(B66="FITX",IF(D66="新倉",-SUM(J66:K66),IF(E66="賣",(H66-H65)*G66*200-SUM(J66:K66),(H65-H66)*G66*200-SUM(J66:K66))),IF(D66="新倉",-SUM(J66:K66),IF(E66="賣",(H66-H65)*G66*50-SUM(J66:K66),(H65-H66)*G66*50-SUM(J66:K66))))) -> -6775 | M66: =L66 -> -6775 | N66: =M66 -> -6775 | O66: 放棄 | P66: 元大期貨
A67: 45502 | B67: TXO | C67: TXOW5 07 22550 C | D67: 新倉 | E67: 賣 | F67: - | G67: 1 | H67: 113 | I67: 5650 | J67: 18 | K67: 6 | L67: =IF(B67="TXO",I67-SUM(J67:K67),IF(B67="FITX",IF(D67="新倉",-SUM(J67:K67),IF(E67="賣",(H67-H66)*G67*200-SUM(J67:K67),(H66-H67)*G67*200-SUM(J67:K67))),IF(D67="新倉",-SUM(J67:K67),IF(E67="賣",(H67-H66)*G67*50-SUM(J67:K67),(H66-H67)*G67*50-SUM(J67:K67))))) -> 5626 | M67: =L67 -> 5626 | N67: =M67 -> 5626 | O67: 履約 | P67: 元大期貨
A68: 45504 | B68: TXO | C68: TXOW5 07 22250 C | D68: 新倉 | E68: 買 | F68: - | G68: 1 | H68: 20 | I68: -1000 | J68: 18 | K68: 1 | L68: =IF(B68="TXO",I68-SUM(J68:K68),IF(B68="FITX",IF(D68="新倉",-SUM(J68:K68),IF(E68="賣",(H68-H67)*G68*200-SUM(J68:K68),(H67-H68)*G68*200-SUM(J68:K68))),IF(D68="新倉",-SUM(J68:K68),IF(E68="賣",(H68-H67)*G68*50-SUM(J68:K68),(H67-H68)*G68*50-SUM(J68:K68))))) -> -1019 | M68: =L68 -> -1019 | O68: 新倉 | P68: 元大期貨
A69: 45504 | B69: TXO | C69: TXOW5 07 22350 C | D69: 新倉 | E69: 買 | F69: - | G69: 1 | H69: 14 | I69: -700 | J69: 18 | K69: 1 | L69: =IF(B69="TXO",I69-SUM(J69:K69),IF(B69="FITX",IF(D69="新倉",-SUM(J69:K69),IF(E69="賣",(H69-H68)*G69*200-SUM(J69:K69),(H68-H69)*G69*200-SUM(J69:K69))),IF(D69="新倉",-SUM(J69:K69),IF(E69="賣",(H69-H68)*G69*50-SUM(J69:K69),(H68-H69)*G69*50-SUM(J69:K69))))) -> -719 | M69: =L69 -> -719 | O69: 新倉 | P69: 元大期貨
A70: 45504 | B70: TXO | C70: TXOW5 07 22250 C | D70: 平倉 | E70: 賣 | F70: - | G70: 1 | H70: 103 | I70: 5150 | J70: 18 | K70: 5 | L70: =IF(B70="TXO",I70-SUM(J70:K70),IF(B70="FITX",IF(D70="新倉",-SUM(J70:K70),IF(E70="賣",(H70-H69)*G70*200-SUM(J70:K70),(H69-H70)*G70*200-SUM(J70:K70))),IF(D70="新倉",-SUM(J70:K70),IF(E70="賣",(H70-H69)*G70*50-SUM(J70:K70),(H69-H70)*G70*50-SUM(J70:K70))))) -> 5127 | M70: =L70 -> 5127 | N70: =SUM(M66,M70) -> -1648 | O70: 平倉 | P70: 元大期貨
A71: 7月總計 | L71: =SUM(L43:L70) -> 16229 | M71: =SUM(M43:M70) -> 16229
A72: 45509 | B72: TXO | C72: 週W1 C 08 22350 C | D72: 新倉 | E72: 買 | F72: - | G72: 1 | H72: 9.6 | I72: -480 | J72: 18 | K72: 0 | L72: =IF(B72="TXO",I72-SUM(J72:K72),IF(B72="FITX",IF(D72="新倉",-SUM(J72:K72),IF(E72="賣",(H72-H71)*G72*200-SUM(J72:K72),(H71-H72)*G72*200-SUM(J72:K72))),IF(D72="新倉",-SUM(J72:K72),IF(E72="賣",(H72-H71)*G72*50-SUM(J72:K72),(H71-H72)*G72*50-SUM(J72:K72))))) -> -498 | M72: =L72 -> -498 | N72: =M72 -> -498 | O72: 放棄 | P72: 元大期貨
A73: 45509 | B73: TXO | C73: 週W1 C 08 22400 C | D73: 新倉 | E73: 賣 | F73: - | G73: 1 | H73: 6.8 | I73: 340 | J73: 18 | K73: 0 | L73: =IF(B73="TXO",I73-SUM(J73:K73),IF(B73="FITX",IF(D73="新倉",-SUM(J73:K73),IF(E73="賣",(H73-H72)*G73*200-SUM(J73:K73),(H72-H73)*G73*200-SUM(J73:K73))),IF(D73="新倉",-SUM(J73:K73),IF(E73="賣",(H73-H72)*G73*50-SUM(J73:K73),(H72-H73)*G73*50-SUM(J73:K73))))) -> 322 | M73: =L73 -> 322 | N73: =M73 -> 322 | O73: 履約 | P73: 元大期貨
A74: 45510 | B74: TXO | C74: 週W1 C 08 21300 C | D74: 新倉 | E74: 買 | F74: - | G74: 1 | H74: 36 | I74: -1800 | J74: 18 | K74: 2 | L74: =IF(B74="TXO",I74-SUM(J74:K74),IF(B74="FITX",IF(D74="新倉",-SUM(J74:K74),IF(E74="賣",(H74-H73)*G74*200-SUM(J74:K74),(H73-H74)*G74*200-SUM(J74:K74))),IF(D74="新倉",-SUM(J74:K74),IF(E74="賣",(H74-H73)*G74*50-SUM(J74:K74),(H73-H74)*G74*50-SUM(J74:K74))))) -> -1820 | M74: =L74 -> -1820 | N74: =M74 -> -1820 | O74: 放棄 | P74: 元大期貨
A75: 45510 | B75: TXO | C75: 週W1 P 08 18600 P | D75: 新倉 | E75: 買 | F75: - | G75: 1 | H75: 14 | I75: -700 | J75: 18 | K75: 1 | L75: =IF(B75="TXO",I75-SUM(J75:K75),IF(B75="FITX",IF(D75="新倉",-SUM(J75:K75),IF(E75="賣",(H75-H74)*G75*200-SUM(J75:K75),(H74-H75)*G75*200-SUM(J75:K75))),IF(D75="新倉",-SUM(J75:K75),IF(E75="賣",(H75-H74)*G75*50-SUM(J75:K75),(H74-H75)*G75*50-SUM(J75:K75))))) -> -719 | M75: =L75 -> -719 | N75: =M75 -> -719 | O75: 放棄 | P75: 元大期貨
A76: 45510 | B76: TXO | C76: 週W1 P 08 18600 P | D76: 新倉 | E76: 買 | F76: - | G76: 1 | H76: 25 | I76: -1250 | J76: 18 | K76: 1 | L76: =IF(B76="TXO",I76-SUM(J76:K76),IF(B76="FITX",IF(D76="新倉",-SUM(J76:K76),IF(E76="賣",(H76-H75)*G76*200-SUM(J76:K76),(H75-H76)*G76*200-SUM(J76:K76))),IF(D76="新倉",-SUM(J76:K76),IF(E76="賣",(H76-H75)*G76*50-SUM(J76:K76),(H75-H76)*G76*50-SUM(J76:K76))))) -> -1269 | M76: =L76 -> -1269 | N76: =M76 -> -1269 | O76: 放棄 | P76: 元大期貨
A77: 45510 | B77: TXO | C77: 週W1 P 08 19550 P | D77: 新倉 | E77: 買 | F77: - | G77: 1 | H77: 199 | I77: -9950 | J77: 18 | K77: 10 | L77: =IF(B77="TXO",I77-SUM(J77:K77),IF(B77="FITX",IF(D77="新倉",-SUM(J77:K77),IF(E77="賣",(H77-H76)*G77*200-SUM(J77:K77),(H76-H77)*G77*200-SUM(J77:K77))),IF(D77="新倉",-SUM(J77:K77),IF(E77="賣",(H77-H76)*G77*50-SUM(J77:K77),(H76-H77)*G77*50-SUM(J77:K77))))) -> -9978 | M77: =L77 -> -9978 | N77: =M77 -> -9978 | O77: 放棄 | P77: 元大期貨
A78: 45510 | B78: TXO | C78: 週W1 P 08 18500 P | D78: 新倉 | E78: 買 | F78: - | G78: 1 | H78: 33.5 | I78: -1675 | J78: 18 | K78: 2 | L78: =IF(B78="TXO",I78-SUM(J78:K78),IF(B78="FITX",IF(D78="新倉",-SUM(J78:K78),IF(E78="賣",(H78-H77)*G78*200-SUM(J78:K78),(H77-H78)*G78*200-SUM(J78:K78))),IF(D78="新倉",-SUM(J78:K78),IF(E78="賣",(H78-H77)*G78*50-SUM(J78:K78),(H77-H78)*G78*50-SUM(J78:K78))))) -> -1695 | M78: =L78 -> -1695 | N78: =M78 -> -1695 | O78: 放棄 | P78: 元大期貨
A79: 45510 | B79: TXO | C79: 週W1 P 08 19600 P | D79: 新倉 | E79: 買 | F79: - | G79: 1 | H79: 200 | I79: -10000 | J79: 18 | K79: 10 | L79: =IF(B79="TXO",I79-SUM(J79:K79),IF(B79="FITX",IF(D79="新倉",-SUM(J79:K79),IF(E79="賣",(H79-H78)*G79*200-SUM(J79:K79),(H78-H79)*G79*200-SUM(J79:K79))),IF(D79="新倉",-SUM(J79:K79),IF(E79="賣",(H79-H78)*G79*50-SUM(J79:K79),(H78-H79)*G79*50-SUM(J79:K79))))) -> -10028 | M79: =L79 -> -10028 | N79: =M79 -> -10028 | O79: 放棄 | P79: 元大期貨
A80: 45516 | B80: TXO | C80: TXOW2 08 21800 C | D80: 新倉 | E80: 買 | F80: - | G80: 1 | H80: 179 | I80: -8950 | J80: 18 | K80: 9 | L80: =IF(B80="TXO",I80-SUM(J80:K80),IF(B80="FITX",IF(D80="新倉",-SUM(J80:K80),IF(E80="賣",(H80-H79)*G80*200-SUM(J80:K80),(H79-H80)*G80*200-SUM(J80:K80))),IF(D80="新倉",-SUM(J80:K80),IF(E80="賣",(H80-H79)*G80*50-SUM(J80:K80),(H79-H80)*G80*50-SUM(J80:K80))))) -> -8977 | M80: =L80 -> -8977 | O80: 新倉 | P80: 元大期貨
A81: 45516 | B81: TXO | C81: TXOW2 08 22000 C | D81: 新倉 | E81: 買 | F81: - | G81: 1 | H81: 114 | I81: -5700 | J81: 18 | K81: 6 | L81: =IF(B81="TXO",I81-SUM(J81:K81),IF(B81="FITX",IF(D81="新倉",-SUM(J81:K81),IF(E81="賣",(H81-H80)*G81*200-SUM(J81:K81),(H80-H81)*G81*200-SUM(J81:K81))),IF(D81="新倉",-SUM(J81:K81),IF(E81="賣",(H81-H80)*G81*50-SUM(J81:K81),(H80-H81)*G81*50-SUM(J81:K81))))) -> -5724 | M81: =L81 -> -5724 | O81: 新倉 | P81: 元大期貨
A82: 45518 | B82: TXO | C82: TXOW2 08 21800 C | D82: 平倉 | E82: 賣 | F82: - | G82: 1 | H82: 241 | I82: 12050 | J82: 18 | K82: 12 | L82: =IF(B82="TXO",I82-SUM(J82:K82),IF(B82="FITX",IF(D82="新倉",-SUM(J82:K82),IF(E82="賣",(H82-H81)*G82*200-SUM(J82:K82),(H81-H82)*G82*200-SUM(J82:K82))),IF(D82="新倉",-SUM(J82:K82),IF(E82="賣",(H82-H81)*G82*50-SUM(J82:K82),(H81-H82)*G82*50-SUM(J82:K82))))) -> 12020 | M82: =L82 -> 12020 | N82: =SUM(M80,M82) -> 3043 | O82: 平倉 | P82: 元大期貨
A83: 45518 | B83: TXO | C83: TXOW2 08 22000 C | D83: 平倉 | E83: 賣 | F83: - | G83: 1 | H83: 114 | I83: =19*50 -> 950 | J83: 18 | K83: 22 | L83: =IF(B83="TXO",I83-SUM(J83:K83),IF(B83="FITX",IF(D83="新倉",-SUM(J83:K83),IF(E83="賣",(H83-H82)*G83*200-SUM(J83:K83),(H82-H83)*G83*200-SUM(J83:K83))),IF(D83="新倉",-SUM(J83:K83),IF(E83="賣",(H83-H82)*G83*50-SUM(J83:K83),(H82-H83)*G83*50-SUM(J83:K83))))) -> 910 | M83: =L83 -> 910 | N83: =SUM(M81,M83) -> -4814 | O83: 履約 | P83: 元大期貨
A84: 45524 | B84: TXO | C84: 台指 C 08 22600 C | D84: 新倉 | E84: 買 | F84: - | G84: 1 | H84: 30 | I84: -1500 | J84: 18 | K84: 2 | L84: =IF(B84="TXO",I84-SUM(J84:K84),IF(B84="FITX",IF(D84="新倉",-SUM(J84:K84),IF(E84="賣",(H84-H83)*G84*200-SUM(J84:K84),(H83-H84)*G84*200-SUM(J84:K84))),IF(D84="新倉",-SUM(J84:K84),IF(E84="賣",(H84-H83)*G84*50-SUM(J84:K84),(H83-H84)*G84*50-SUM(J84:K84))))) -> -1520 | M84: =L84 -> -1520 | N84: =M84 -> -1520 | O84: 放棄 | P84: 元大期貨
A85: 8月總計 | L85: =SUM(L72:L84) -> -28976 | M85: =SUM(M72:M84) -> -28976
A86: 45544 | B86: TXO | C86: 週W2 P 09 20700 P | D86: 新倉 | E86: 買 | F86: - | G86: 1 | H86: 163 | I86: -8150 | J86: 18 | K86: 8 | L86: =IF(B86="TXO",I86-SUM(J86:K86),IF(B86="FITX",IF(D86="新倉",-SUM(J86:K86),IF(E86="賣",(H86-H85)*G86*200-SUM(J86:K86),(H85-H86)*G86*200-SUM(J86:K86))),IF(D86="新倉",-SUM(J86:K86),IF(E86="賣",(H86-H85)*G86*50-SUM(J86:K86),(H85-H86)*G86*50-SUM(J86:K86))))) -> -8176 | M86: =L86 -> -8176 | N86: =M86 -> -8176 | O86: 放棄 | P86: 元大期貨
A87: 45545 | B87: TXO | C87: 週W2 P 09 20850 P | D87: 新倉 | E87: 買 | F87: - | G87: 1 | H87: 76 | I87: -3800 | J87: 18 | K87: 4 | L87: =IF(B87="TXO",I87-SUM(J87:K87),IF(B87="FITX",IF(D87="新倉",-SUM(J87:K87),IF(E87="賣",(H87-H86)*G87*200-SUM(J87:K87),(H86-H87)*G87*200-SUM(J87:K87))),IF(D87="新倉",-SUM(J87:K87),IF(E87="賣",(H87-H86)*G87*50-SUM(J87:K87),(H86-H87)*G87*50-SUM(J87:K87))))) -> -3822 | M87: =L87 -> -3822 | N87: =M87 -> -3822 | O87: 放棄 | P87: 元大期貨
A88: 45545 | C88: 入金 | L88: 30000 | M88: =L88 -> 30000
A89: 45548 | B89: TXO | C89: 台指選 09 21500 P | D89: 新倉 | E89: 買 | F89: - | G89: 1 | H89: 109 | I89: -5450 | J89: 18 | K89: 5 | L89: =IF(B89="TXO",I89-SUM(J89:K89),IF(B89="FITX",IF(D89="新倉",-SUM(J89:K89),IF(E89="賣",(H89-H88)*G89*200-SUM(J89:K89),(H88-H89)*G89*200-SUM(J89:K89))),IF(D89="新倉",-SUM(J89:K89),IF(E89="賣",(H89-H88)*G89*50-SUM(J89:K89),(H88-H89)*G89*50-SUM(J89:K89))))) -> -5473 | M89: =L89 -> -5473 | N89: =M89 -> -5473 | O89: 放棄 | P89: 元大期貨
A90: 45551 | B90: TXO | C90: 台指選 09 22000 C | D90: 新倉 | E90: 買 | F90: - | G90: 1 | H90: 58 | I90: -2900 | J90: 18 | K90: 3 | L90: =IF(B90="TXO",I90-SUM(J90:K90),IF(B90="FITX",IF(D90="新倉",-SUM(J90:K90),IF(E90="賣",(H90-H89)*G90*200-SUM(J90:K90),(H89-H90)*G90*200-SUM(J90:K90))),IF(D90="新倉",-SUM(J90:K90),IF(E90="賣",(H90-H89)*G90*50-SUM(J90:K90),(H89-H90)*G90*50-SUM(J90:K90))))) -> -2921 | M90: =L90 -> -2921 | N90: =M90 -> -2921 | O90: 放棄 | P90: 元大期貨
A91: 45555 | B91: TXO | C91: 週W4 P 09 22000 P | D91: 新倉 | E91: 買 | F91: - | G91: 1 | H91: 100 | I91: -5000 | J91: 18 | K91: 5 | L91: =IF(B91="TXO",I91-SUM(J91:K91),IF(B91="FITX",IF(D91="新倉",-SUM(J91:K91),IF(E91="賣",(H91-H90)*G91*200-SUM(J91:K91),(H90-H91)*G91*200-SUM(J91:K91))),IF(D91="新倉",-SUM(J91:K91),IF(E91="賣",(H91-H90)*G91*50-SUM(J91:K91),(H90-H91)*G91*50-SUM(J91:K91))))) -> -5023 | M91: =L91 -> -5023 | N91: =M91 -> -5023 | O91: 放棄 | P91: 元大期貨
A92: 45560 | B92: TXO | C92: 週W4 P 09 22600 P | D92: 新倉 | E92: 買 | F92: - | G92: 1 | H92: 19 | I92: -950 | J92: 18 | K92: 1 | L92: =IF(B92="TXO",I92-SUM(J92:K92),IF(B92="FITX",IF(D92="新倉",-SUM(J92:K92),IF(E92="賣",(H92-H91)*G92*200-SUM(J92:K92),(H91-H92)*G92*200-SUM(J92:K92))),IF(D92="新倉",-SUM(J92:K92),IF(E92="賣",(H92-H91)*G92*50-SUM(J92:K92),(H91-H92)*G92*50-SUM(J92:K92))))) -> -969 | M92: =L92 -> -969 | N92: =M92 -> -969 | O92: 放棄 | P92: 元大期貨
